Workbook

Sheet BANK
A1: Day | B1: Date | C1: SALDO | D1: GLOBAL | E1: SISA USDT | F1: tambah modal | G1: OUT | H1: TOTAL | I1: PROFIT | K1: REMARK | L1: BCA | M1: BCA BISNIS | N1: BLU BCA | O1: MANDIRI | P1: BRI | Q1: BRI VEGA | R1: BNI | S1: SINARMAS | T1: TOTAL | U1: USDT | V1: RATE | W1: TOTAL USDT
A2: =IF(ISBLANK(B2),"",TEXT(B2,"dddd")) -> Wednesday | B2: 46267 | C2: START | D2: =T2 -> 0 | E2: 0 | H2: =SUM(D2+E2+F2) -> 0 | K2: START | L2: 0 | M2: 0 | N2: 0 | O2: 0 | P2: 0 | Q2: 0 | R2: 0 | S2: 0 | T2: =SUM(L2:S2) -> 0
C3: END | D3: =T3 -> 1894000 | E3: =W3 -> 9960071.5 | G3: 0 | H3: =SUM(D3+E3+F3+G3) -> 11854072 | I3: =H3-H2 -> 11854072 | K3: END | L3: 1894000 | M3: 0 | N3: 0 | O3: 0 | P3: 0 | Q3: 0 | R3: 0 | S3: 0 | T3: =SUM(J3:S3) -> 1894000 | U3: 564.31 | V3: 17650 | W3: =U3*V3 -> 9960071.5
A4: =IF(ISBLANK(B4),"",TEXT(B4,"dddd")) -> Thursday | B4: 46268 | C4: START | D4: =T4 -> 1894000 | K4: START | L4: 1894000 | M4: 0 | N4: 0 | O4: 0 | P4: 0 | Q4: 0 | R4: 0 | S4: 0 | T4: =SUM(L4:S4) -> 1894000 | W4: =U4*V4 -> 0
C5: END | D5: =T5 -> 31218000 | E5: =W5 -> -11190608 | G5: 1850000 | H5: =SUM(D5+E5+F5+G5) -> 21877392 | I5: =H5-H4 -> 21877392 | K5: END | L5: 6818000 | M5: 0 | N5: 24400000 | O5: 0 | P5: 0 | Q5: 0 | R5: 0 | S5: 0 | T5: =SUM(J5:S5) -> 31218000 | U5: -635.83 | V5: 17600 | W5: =U5*V5 -> -11190608
A6: =IF(ISBLANK(B6),"",TEXT(B6,"dddd")) -> Friday | B6: 46269 | C6: START | D6: =T6 -> 24418000 | K6: START | L6: 18000 | M6: 0 | N6: 24400000 | O6: 0 | P6: 0 | Q6: 0 | R6: 0 | S6: 0 | T6: =SUM(L6:S6) -> 24418000 | W6: =U6*V6 -> 0
C7: END | D7: =T7 -> 1309000 | E7: =W7 -> 15466000 | G7: 6800000 | H7: =SUM(D7+E7+F7+G7) -> 23575000 | I7: =H7-H6 -> 23575000 | K7: END | L7: 911000 | M7: 0 | N7: 398000 | O7: 0 | P7: 0 | Q7: 0 | R7: 0 | S7: 0 | T7: =SUM(J7:S7) -> 1309000 | U7: 880 | V7: 17575 | W7: =U7*V7 -> 15466000
A8: =IF(ISBLANK(B8),"",TEXT(B8,"dddd")) -> Saturday | B8: 46270 | C8: START | D8: =T8 -> 1309000 | K8: START | L8: 911000 | M8: 0 | N8: 398000 | O8: 0 | P8: 0 | Q8: 0 | R8: 0 | S8: 0 | T8: =SUM(L8:S8) -> 1309000 | W8: =U8*V8 -> 0
C9: END | D9: =T9 -> 0 | E9: =W9 -> 0 | G9: 5000000 | H9: =SUM(D9+E9+F9+G9) -> 5000000 | I9: =H9-H8 -> 5000000 | K9: END | R9: 0 | S9: 0 | T9: =SUM(J9:S9) -> 0 | W9: =U9*V9 -> 0
A10: =IF(ISBLANK(B10),"",TEXT(B10,"dddd")) -> Sunday | B10: 46271 | C10: START | D10: =T10 -> 0 | K10: START | R10: 0 | S10: 0 | T10: =SUM(L10:S10) -> 0 | W10: =U10*V10 -> 0
C11: END | D11: =T11 -> 0 | E11: =W11 -> 0 | I11: =H11-H10 -> 0 | K11: END | R11: 0 | S11: 0 | T11: =SUM(J11:S11) -> 0 | W11: =U11*V11 -> 0
A12: =IF(ISBLANK(B12),"",TEXT(B12,"dddd")) -> Saturday | B12: 46284 | C12: START | D12: =T12 -> 0 | K12: START | R12: 0 | S12: 0 | T12: =SUM(L12:S12) -> 0 | W12: =U12*V12 -> 0
C13: END | D13: =T13 -> 0 | E13: =W13 -> 0 | I13: =H13-H12 -> 0 | K13: END | R13: 0 | S13: 0 | T13: =SUM(J13:S13) -> 0 | W13: =U13*V13 -> 0
A14: =IF(ISBLANK(B14),"",TEXT(B14,"dddd")) -> Tuesday | B14: 46273 | C14: START | D14: =T14 -> 0 | K14: START | R14: 0 | S14: 0 | T14: =SUM(L14:S14) -> 0 | W14: =U14*V14 -> 0
C15: END | D15: =T15 -> 0 | E15: =W15 -> 0 | I15: =H15-H14 -> 0 | K15: END | R15: 0 | S15: 0 | T15: =SUM(J15:S15) -> 0 | W15: =U15*V15 -> 0
A16: =IF(ISBLANK(B16),"",TEXT(B16,"dddd")) -> Friday | B16: 46269 | C16: START | D16: =T16 -> 24418000 | K16: START | L16: 18000 | M16: 0 | N16: 24400000 | O16: 0 | P16: 0 | Q16: 0 | R16: 0 | S16: 0 | T16: =SUM(L16:S16) -> 24418000 | W16: =U16*V16 -> 0
C17: END | D17: =T17 -> 0 | E17: =W17 -> 0 | I17: =H17-H16 -> 0 | K17: END | R17: 0 | S17: 0 | T17: =SUM(J17:S17) -> 0 | W17: =U17*V17 -> 0
A18: =IF(ISBLANK(B18),"",TEXT(B18,"dddd")) -> Saturday | B18: 46270 | C18: START | D18: =T18 -> 0 | K18: START | R18: 0 | S18: 0 | T18: =SUM(L18:S18) -> 0 | W18: =U18*V18 -> 0
C19: END | D19: =T19 -> 0 | E19: =W19 -> 0 | I19: =H19-H18 -> 0 | K19: END | R19: 0 | S19: 0 | T19: =SUM(J19:S19) -> 0 | W19: =U19*V19 -> 0
A20: =IF(ISBLANK(B20),"",TEXT(B20,"dddd")) -> Sunday | B20: 46271 | C20: START | D20: =T20 -> 0 | K20: START | R20: 0 | S20: 0 | T20: =SUM(L20:S20) -> 0 | W20: =U20*V20 -> 0
C21: END | D21: =T21 -> 0 | E21: =W21 -> 0 | I21: =H21-H20 -> 0 | K21: END | R21: 0 | S21: 0 | T21: =SUM(J21:S21) -> 0 | W21: =U21*V21 -> 0
A22: =IF(ISBLANK(B22),"",TEXT(B22,"dddd")) -> Monday | B22: 46272 | C22: START | D22: =T22 -> 0 | K22: START | R22: 0 | S22: 0 | T22: =SUM(L22:S22) -> 0 | W22: =U22*V22 -> 0
C23: END | D23: =T23 -> 0 | E23: =W23 -> 0 | I23: =H23-H22 -> 0 | K23: END | R23: 0 | S23: 0 | T23: =SUM(J23:S23) -> 0 | W23: =U23*V23 -> 0
A24: =IF(ISBLANK(B24),"",TEXT(B24,"dddd")) -> Tuesday | B24: 46273 | C24: START | D24: =T24 -> 0 | K24: START | R24: 0 | S24: 0 | T24: =SUM(L24:S24) -> 0 | W24: =U24*V24 -> 0
C25: END | D25: =T25 -> 0 | E25: =W25 -> 0 | I25: =H25-H24 -> 0 | K25: END | R25: 0 | S25: 0 | T25: =SUM(J25:S25) -> 0 | W25: =U25*V25 -> 0
A26: =IF(ISBLANK(B26),"",TEXT(B26,"dddd")) -> Friday | B26: 46269 | C26: START | D26: =T26 -> 24418000 | K26: START | L26: 18000 | M26: 0 | N26: 24400000 | O26: 0 | P26: 0 | Q26: 0 | R26: 0 | S26: 0 | T26: =SUM(L26:S26) -> 24418000 | W26: =U26*V26 -> 0
C27: END | D27: =T27 -> 0 | E27: =W27 -> 0 | I27: =H27-H26 -> 0 | K27: END | R27: 0 | S27: 0 | T27: =SUM(J27:S27) -> 0 | W27: =U27*V27 -> 0
A28: =IF(ISBLANK(B28),"",TEXT(B28,"dddd")) -> Saturday | B28: 46270 | C28: START | D28: =T28 -> 0 | K28: START | R28: 0 | S28: 0 | T28: =SUM(L28:S28) -> 0 | W28: =U28*V28 -> 0
C29: END | D29: =T29 -> 0 | E29: =W29 -> 0 | I29: =H29-H28 -> 0 | K29: END | R29: 0 | S29: 0 | T29: =SUM(J29:S29) -> 0 | W29: =U29*V29 -> 0
A30: =IF(ISBLANK(B30),"",TEXT(B30,"dddd")) -> Sunday | B30: 46271 | C30: START | D30: =T30 -> 0 | K30: START | R30: 0 | S30: 0 | T30: =SUM(L30:S30) -> 0 | W30: =U30*V30 -> 0
C31: END | D31: =T31 -> 0 | E31: =W31 -> 0 | I31: =H31-H30 -> 0 | K31: END | R31: 0 | S31: 0 | T31: =SUM(J31:S31) -> 0 | W31: =U31*V31 -> 0
A32: =IF(ISBLANK(B32),"",TEXT(B32,"dddd")) -> Monday | B32: 46272 | C32: START | D32: =T32 -> 0 | K32: START | R32: 0 | S32: 0 | T32: =SUM(L32:S32) -> 0 | W32: =U32*V32 -> 0
C33: END | D33: =T33 -> 0 | E33: =W33 -> 0 | I33: =H33-H32 -> 0 | K33: END | R33: 0 | S33: 0 | T33: =SUM(J33:S33) -> 0 | W33: =U33*V33 -> 0
A34: =IF(ISBLANK(B34),"",TEXT(B34,"dddd")) -> Tuesday | B34: 46273 | C34: START | D34: =T34 -> 0 | K34: START | R34: 0 | S34: 0 | T34: =SUM(L34:S34) -> 0 | W34: =U34*V34 -> 0
C35: END | D35: =T35 -> 0 | E35: =W35 -> 0 | I35: =H35-H34 -> 0 | K35: END | R35: 0 | S35: 0 | T35: =SUM(J35:S35) -> 0 | W35: =U35*V35 -> 0
A36: =IF(ISBLANK(B36),"",TEXT(B36,"dddd")) -> Friday | B36: 46269 | C36: START | D36: =T36 -> 24418000 | K36: START | L36: 18000 | M36: 0 | N36: 24400000 | O36: 0 | P36: 0 | Q36: 0 | R36: 0 | S36: 0 | T36: =SUM(L36:S36) -> 24418000 | W36: =U36*V36 -> 0
C37: END | D37: =T37 -> 0 | E37: =W37 -> 0 | I37: =H37-H36 -> 0 | K37: END | R37: 0 | S37: 0 | T37: =SUM(J37:S37) -> 0 | W37: =U37*V37 -> 0
A38: =IF(ISBLANK(B38),"",TEXT(B38,"dddd")) -> Saturday | B38: 46270 | C38: START | D38: =T38 -> 0 | K38: START | R38: 0 | S38: 0 | T38: =SUM(L38:S38) -> 0 | W38: =U38*V38 -> 0
C39: END | D39: =T39 -> 0 | E39: =W39 -> 0 | I39: =H39-H38 -> 0 | K39: END | R39: 0 | S39: 0 | T39: =SUM(J39:S39) -> 0 | W39: =U39*V39 -> 0
A40: =IF(ISBLANK(B40),"",TEXT(B40,"dddd")) -> Sunday | B40: 46271 | C40: START | D40: =T40 -> 0 | K40: START | R40: 0 | S40: 0 | T40: =SUM(L40:S40) -> 0 | W40: =U40*V40 -> 0
C41: END | D41: =T41 -> 0 | E41: =W41 -> 0 | I41: =H41-H40 -> 0 | K41: END | R41: 0 | S41: 0 | T41: =SUM(J41:S41) -> 0 | W41: =U41*V41 -> 0
A42: =IF(ISBLANK(B42),"",TEXT(B42,"dddd")) -> Monday | B42: 46272 | C42: START | D42: =T42 -> 0 | K42: START | R42: 0 | S42: 0 | T42: =SUM(L42:S42) -> 0 | W42: =U42*V42 -> 0
C43: END | D43: =T43 -> 0 | E43: =W43 -> 0 | I43: =H43-H42 -> 0 | K43: END | R43: 0 | S43: 0 | T43: =SUM(J43:S43) -> 0 | W43: =U43*V43 -> 0
A44: =IF(ISBLANK(B44),"",TEXT(B44,"dddd")) -> Tuesday | B44: 46273 | C44: START | D44: =T44 -> 0 | K44: START | R44: 0 | S44: 0 | T44: =SUM(L44:S44) -> 0 | W44: =U44*V44 -> 0
C45: END | D45: =T45 -> 0 | E45: =W45 -> 0 | I45: =H45-H44 -> 0 | K45: END | R45: 0 | S45: 0 | T45: =SUM(J45:S45) -> 0 | W45: =U45*V45 -> 0
A46: =IF(ISBLANK(B46),"",TEXT(B46,"dddd")) -> Friday | B46: 46269 | C46: START | D46: =T46 -> 24418000 | K46: START | L46: 18000 | M46: 0 | N46: 24400000 | O46: 0 | P46: 0 | Q46: 0 | R46: 0 | S46: 0 | T46: =SUM(L46:S46) -> 24418000 | W46: =U46*V46 -> 0
C47: END | D47: =T47 -> 0 | E47: =W47 -> 0 | I47: =H47-H46 -> 0 | K47: END | R47: 0 | S47: 0 | T47: =SUM(J47:S47) -> 0 | W47: =U47*V47 -> 0
A48: =IF(ISBLANK(B48),"",TEXT(B48,"dddd")) -> Saturday | B48: 46270 | C48: START | D48: =T48 -> 0 | K48: START | R48: 0 | S48: 0 | T48: =SUM(L48:S48) -> 0 | W48: =U48*V48 -> 0
C49: END | D49: =T49 -> 0 | E49: =W49 -> 0 | I49: =H49-H48 -> 0 | K49: END | R49: 0 | S49: 0 | T49: =SUM(J49:S49) -> 0 | W49: =U49*V49 -> 0
A50: =IF(ISBLANK(B50),"",TEXT(B50,"dddd")) -> Sunday | B50: 46271 | C50: START | D50: =T50 -> 0 | K50: START | R50: 0 | S50: 0 | T50: =SUM(L50:S50) -> 0 | W50: =U50*V50 -> 0
C51: END | D51: =T51 -> 0 | E51: =W51 -> 0 | I51: =H51-H50 -> 0 | K51: END | R51: 0 | S51: 0 | T51: =SUM(J51:S51) -> 0 | W51: =U51*V51 -> 0
A52: =IF(ISBLANK(B52),"",TEXT(B52,"dddd")) -> Monday | B52: 46272 | C52: START | D52: =T52 -> 0 | K52: START | R52: 0 | S52: 0 | T52: =SUM(L52:S52) -> 0 | W52: =U52*V52 -> 0
C53: END | D53: =T53 -> 0 | E53: =W53 -> 0 | I53: =H53-H52 -> 0 | K53: END | R53: 0 | S53: 0 | T53: =SUM(J53:S53) -> 0 | W53: =U53*V53 -> 0
A54: =IF(ISBLANK(B54),"",TEXT(B54,"dddd")) -> Tuesday | B54: 46273 | C54: START | D54: =T54 -> 0 | K54: START | R54: 0 | S54: 0 | T54: =SUM(L54:S54) -> 0 | W54: =U54*V54 -> 0
C55: END | D55: =T55 -> 0 | E55: =W55 -> 0 | I55: =H55-H54 -> 0 | K55: END | R55: 0 | S55: 0 | T55: =SUM(J55:S55) -> 0 | W55: =U55*V55 -> 0
A56: =IF(ISBLANK(B56),"",TEXT(B56,"dddd")) -> Friday | B56: 46269 | C56: START | D56: =T56 -> 24418000 | K56: START | L56: 18000 | M56: 0 | N56: 24400000 | O56: 0 | P56: 0 | Q56: 0 | R56: 0 | S56: 0 | T56: =SUM(L56:S56) -> 24418000 | W56: =U56*V56 -> 0
C57: END | D57: =T57 -> 0 | E57: =W57 -> 0 | I57: =H57-H56 -> 0 | K57: END | R57: 0 | S57: 0 | T57: =SUM(J57:S57) -> 0 | W57: =U57*V57 -> 0
A58: =IF(ISBLANK(B58),"",TEXT(B58,"dddd")) -> Saturday | B58: 46270 | C58: START | D58: =T58 -> 0 | K58: START | R58: 0 | S58: 0 | T58: =SUM(L58:S58) -> 0 | W58: =U58*V58 -> 0
C59: END | D59: =T59 -> 0 | E59: =W59 -> 0 | I59: =H59-H58 -> 0 | K59: END | R59: 0 | S59: 0 | T59: =SUM(J59:S59) -> 0 | W59: =U59*V59 -> 0
A60: =IF(ISBLANK(B60),"",TEXT(B60,"dddd")) -> Sunday | B60: 46271 | C60: START | D60: =T60 -> 0 | K60: START | R60: 0 | S60: 0 | T60: =SUM(L60:S60) -> 0 | W60: =U60*V60 -> 0
C61: END | D61: =T61 -> 0 | E61: =W61 -> 0 | I61: =H61-H60 -> 0 | K61: END | R61: 0 | S61: 0 | T61: =SUM(J61:S61) -> 0 | W61: =U61*V61 -> 0
A62: =IF(ISBLANK(B62),"",TEXT(B62,"dddd")) -> Monday | B62: 46272 | C62: START | D62: =T62 -> 0 | K62: START | R62: 0 | S62: 0 | T62: =SUM(L62:S62) -> 0 | W62: =U62*V62 -> 0
C63: END | D63: =T63 -> 0 | E63: =W63 -> 0 | I63: =H63-H62 -> 0 | K63: END | R63: 0 | S63: 0 | T63: =SUM(J63:S63) -> 0 | W63: =U63*V63 -> 0
A64: =IF(ISBLANK(B64),"",TEXT(B64,"dddd")) -> Tuesday | B64: 46273 | C64: START | D64: =T64 -> 0 | K64: START | R64: 0 | S64: 0 | T64: =SUM(L64:S64) -> 0 | W64: =U64*V64 -> 0
C65: END | D65: =T65 -> 0 | E65: =W65 -> 0 | I65: =H65-H64 -> 0 | K65: END | R65: 0 | S65: 0 | T65: =SUM(J65:S65) -> 0 | W65: =U65*V65 -> 0

Sheet SUMMARY
A1: p | C1: EXCHANGE | N1: MONTHLY
A2: DAY | B2: DATE | C2: NOMINAL | D2: RATE BUY | E2: BUY | F2: RATE SELL | G2: SELL | H2: FEE | I2: OMSET | J2: PROFIT | N2: MONTH | O2: NOMINAL | P2: RATE BUY | Q2: BUY | R2: RATE SELL | S2: SELL | T2: FEE | U2: PROFIT
T3: 0.0007
A4: AUG | N4: =IFERROR(__xludf.DUMMYFUNCTION("UNIQUE(FILTER(A2:A153,(A2:A153<>"""")*(COUNTIF(LEGEND!B2:B13,A2:A153)>0)))"),"AUG") -> AUG | O4: =IFERROR(SUM( INDEX($C:$C,MATCH($N4,$A:$A,0)+1): INDEX($C:$C,MATCH($N4&"_TOTAL",$A:$A,0)-1) ),0) -> 1139465.6 | P4: =IFERROR(AVERAGE( INDEX(D:D,MATCH($N4,$A:$A,0)+1): INDEX(D:D,MATCH($N4&"_TOTAL",$A:$A,0)-1) ),0) -> 17737.582 | Q4: =IFERROR(SUM( INDEX(E:E,MATCH($N4,$A:$A,0)+1): INDEX(E:E,MATCH($N4&"_TOTAL",$A:$A,0)-1) ),0) -> 20209889639 | R4: =IFERROR(AVERAGE( INDEX(F:F,MATCH($N4,$A:$A,0)+1): INDEX(F:F,MATCH($N4&"_TOTAL",$A:$A,0)-1) ),0) -> 17762.5 | S4: =IFERROR(SUM( INDEX(G:G,MATCH($N4,$A:$A,0)+1): INDEX(G:G,MATCH($N4&"_TOTAL",$A:$A,0)-1) ),0) -> 20249998209 | T4: =IFERROR(SUM( INDEX(H:H,MATCH($N4,$A:$A,0)+1): INDEX(H:H,MATCH($N4&"_TOTAL",$A:$A,0)-1) ),0) -> 14146923 | U4: =IFERROR(SUM( INDEX(J:J,MATCH($N4,$A:$A,0)+1): INDEX(J:J,MATCH($N4&"_TOTAL",$A:$A,0)-1) ),0) -> 25961647
A5: =IF(ISBLANK(B5),"",TEXT(B5,"dddd")) -> Saturday | B5: 46235 | C5: =SUMIF(AUG!$B$3:$B$100, B5, AUG!$D$3:$D$100) -> 0 | D5: =IFERROR(__xludf.DUMMYFUNCTION("IFNA(INDEX(FILTER(AUG!$E$3:$E$100, AUG!$B$3:$B$100=B5), 1), ""-"")"),"-") -> - | E5: =SUMIF(AUG!$B$3:$B$100, B5, AUG!$F$3:$F$100) -> 0 | F5: =IFERROR(__xludf.DUMMYFUNCTION("IFNA(INDEX(FILTER(AUG!$G$3:$G$100, AUG!$B$3:$B$100=B5), 1), ""-"")"),"-") -> - | G5: =IFNA(SUMIF(AUG!$B$3:$B$100,B5,AUG!$H$3:$H$100),"-") -> 0 | H5: =E5*0.07% -> 0 | I5: =SUMIF(AUG!B:B, B5, AUG!K:K) -> 0 | J5: =G5-E5-H5 -> 0 | N5: =IFERROR(__xludf.DUMMYFUNCTION("""COMPUTED_VALUE"""),"SEP") -> SEP | O5: =IFERROR(SUM( INDEX($C:$C,MATCH($N5,$A:$A,0)+1): INDEX($C:$C,MATCH($N5&"_TOTAL",$A:$A,0)-1) ),0) -> 11639891 | P5: =IFERROR(AVERAGE( INDEX(D:D,MATCH($N5,$A:$A,0)+1): INDEX(D:D,MATCH($N5&"_TOTAL",$A:$A,0)-1) ),0) -> 17635.512 | Q5: =IFERROR(SUM( INDEX(E:E,MATCH($N5,$A:$A,0)+1): INDEX(E:E,MATCH($N5&"_TOTAL",$A:$A,0)-1) ),0) -> 205573414297 | R5: =IFERROR(AVERAGE( INDEX(F:F,MATCH($N5,$A:$A,0)+1): INDEX(F:F,MATCH($N5&"_TOTAL",$A:$A,0)-1) ),0) -> 17663.643 | S5: =IFERROR(SUM( INDEX(G:G,MATCH($N5,$A:$A,0)+1): INDEX(G:G,MATCH($N5&"_TOTAL",$A:$A,0)-1) ),0) -> 205910516613 | T5: =IFERROR(SUM( INDEX(H:H,MATCH($N5,$A:$A,0)+1): INDEX(H:H,MATCH($N5&"_TOTAL",$A:$A,0)-1) ),0) -> 43454634 | U5: =IFERROR(SUM( INDEX(J:J,MATCH($N5,$A:$A,0)+1): INDEX(J:J,MATCH($N5&"_TOTAL",$A:$A,0)-1) ),0) -> 2.9364768e+08
A6: =IF(ISBLANK(B6),"",TEXT(B6,"dddd")) -> Sunday | B6: 46236 | C6: =SUMIF(AUG!$B$3:$B$100, B6, AUG!$D$3:$D$100) -> 0 | D6: =IFERROR(__xludf.DUMMYFUNCTION("IFNA(INDEX(FILTER(AUG!$E$3:$E$100, AUG!$B$3:$B$100=B6), 1), ""-"")"),"-") -> - | E6: =SUMIF(AUG!$B$3:$B$100, B6, AUG!$F$3:$F$100) -> 0 | F6: =IFERROR(__xludf.DUMMYFUNCTION("IFNA(INDEX(FILTER(AUG!$G$3:$G$100, AUG!$B$3:$B$100=B6), 1), ""-"")"),"-") -> - | G6: =IFNA(SUMIF(AUG!$B$3:$B$100,B6,AUG!$H$3:$H$100),"-") -> 0 | H6: =E6*0.07% -> 0 | I6: =SUMIF(AUG!B:B, B6, AUG!K:K) -> 0 | J6: =G6-E6-H6 -> 0 | N6: =IFERROR(__xludf.DUMMYFUNCTION("""COMPUTED_VALUE"""),"OCT") -> OCT | O6: =IFERROR(SUM( INDEX($C:$C,MATCH($N6,$A:$A,0)+1): INDEX($C:$C,MATCH($N6&"_TOTAL",$A:$A,0)-1) ),0) -> 0 | P6: =IFERROR(AVERAGE( INDEX(D:D,MATCH($N6,$A:$A,0)+1): INDEX(D:D,MATCH($N6&"_TOTAL",$A:$A,0)-1) ),0) -> 0 | Q6: =IFERROR(SUM( INDEX(E:E,MATCH($N6,$A:$A,0)+1): INDEX(E:E,MATCH($N6&"_TOTAL",$A:$A,0)-1) ),0) -> 0 | R6: =IFERROR(AVERAGE( INDEX(F:F,MATCH($N6,$A:$A,0)+1): INDEX(F:F,MATCH($N6&"_TOTAL",$A:$A,0)-1) ),0) -> 0 | S6: =IFERROR(SUM( INDEX(G:G,MATCH($N6,$A:$A,0)+1): INDEX(G:G,MATCH($N6&"_TOTAL",$A:$A,0)-1) ),0) -> 0 | T6: =IFERROR(SUM( INDEX(H:H,MATCH($N6,$A:$A,0)+1): INDEX(H:H,MATCH($N6&"_TOTAL",$A:$A,0)-1) ),0) -> 0 | U6: =IFERROR(SUM( INDEX(J:J,MATCH($N6,$A:$A,0)+1): INDEX(J:J,MATCH($N6&"_TOTAL",$A:$A,0)-1) ),0) -> 0
A7: =IF(ISBLANK(B7),"",TEXT(B7,"dddd")) -> Monday | B7: 46237 | C7: =SUMIF(AUG!$B$3:$B$100, B7, AUG!$D$3:$D$100) -> 0 | D7: =IFERROR(__xludf.DUMMYFUNCTION("IFNA(INDEX(FILTER(AUG!$E$3:$E$100, AUG!$B$3:$B$100=B7), 1), ""-"")"),"-") -> - | E7: =SUMIF(AUG!$B$3:$B$100, B7, AUG!$F$3:$F$100) -> 0 | F7: =IFERROR(__xludf.DUMMYFUNCTION("IFNA(INDEX(FILTER(AUG!$G$3:$G$100, AUG!$B$3:$B$100=B7), 1), ""-"")"),"-") -> - | G7: =IFNA(SUMIF(AUG!$B$3:$B$100,B7,AUG!$H$3:$H$100),"-") -> 0 | H7: =E7*0.07% -> 0 | I7: =SUMIF(AUG!B:B, B7, AUG!K:K) -> 0 | J7: =G7-E7-H7 -> 0 | N7: =IFERROR(__xludf.DUMMYFUNCTION("""COMPUTED_VALUE"""),"NOV") -> NOV | O7: =IFERROR(SUM( INDEX($C:$C,MATCH($N7,$A:$A,0)+1): INDEX($C:$C,MATCH($N7&"_TOTAL",$A:$A,0)-1) ),0) -> 0 | P7: =IFERROR(AVERAGE( INDEX(D:D,MATCH($N7,$A:$A,0)+1): INDEX(D:D,MATCH($N7&"_TOTAL",$A:$A,0)-1) ),0) -> 0 | Q7: =IFERROR(SUM( INDEX(E:E,MATCH($N7,$A:$A,0)+1): INDEX(E:E,MATCH($N7&"_TOTAL",$A:$A,0)-1) ),0) -> 0 | R7: =IFERROR(AVERAGE( INDEX(F:F,MATCH($N7,$A:$A,0)+1): INDEX(F:F,MATCH($N7&"_TOTAL",$A:$A,0)-1) ),0) -> 0 | S7: =IFERROR(SUM( INDEX(G:G,MATCH($N7,$A:$A,0)+1): INDEX(G:G,MATCH($N7&"_TOTAL",$A:$A,0)-1) ),0) -> 0 | T7: =IFERROR(SUM( INDEX(H:H,MATCH($N7,$A:$A,0)+1): INDEX(H:H,MATCH($N7&"_TOTAL",$A:$A,0)-1) ),0) -> 0 | U7: =IFERROR(SUM( INDEX(J:J,MATCH($N7,$A:$A,0)+1): INDEX(J:J,MATCH($N7&"_TOTAL",$A:$A,0)-1) ),0) -> 0
A8: =IF(ISBLANK(B8),"",TEXT(B8,"dddd")) -> Tuesday | B8: 46238 | C8: =SUMIF(AUG!$B$3:$B$100, B8, AUG!$D$3:$D$100) -> 0 | D8: =IFERROR(__xludf.DUMMYFUNCTION("IFNA(INDEX(FILTER(AUG!$E$3:$E$100, AUG!$B$3:$B$100=B8), 1), ""-"")"),"-") -> - | E8: =SUMIF(AUG!$B$3:$B$100, B8, AUG!$F$3:$F$100) -> 0 | F8: =IFERROR(__xludf.DUMMYFUNCTION("IFNA(INDEX(FILTER(AUG!$G$3:$G$100, AUG!$B$3:$B$100=B8), 1), ""-"")"),"-") -> - | G8: =IFNA(SUMIF(AUG!$B$3:$B$100,B8,AUG!$H$3:$H$100),"-") -> 0 | H8: =E8*0.07% -> 0 | I8: =SUMIF(AUG!B:B, B8, AUG!K:K) -> 0 | J8: =G8-E8-H8 -> 0 | N8: =IFERROR(__xludf.DUMMYFUNCTION("""COMPUTED_VALUE"""),"DEC") -> DEC | O8: =IFERROR(SUM( INDEX($C:$C,MATCH($N8,$A:$A,0)+1): INDEX($C:$C,MATCH($N8&"_TOTAL",$A:$A,0)-1) ),0) -> 0 | P8: =IFERROR(AVERAGE( INDEX(D:D,MATCH($N8,$A:$A,0)+1): INDEX(D:D,MATCH($N8&"_TOTAL",$A:$A,0)-1) ),0) -> 0 | Q8: =IFERROR(SUM( INDEX(E:E,MATCH($N8,$A:$A,0)+1): INDEX(E:E,MATCH($N8&"_TOTAL",$A:$A,0)-1) ),0) -> 0 | R8: =IFERROR(AVERAGE( INDEX(F:F,MATCH($N8,$A:$A,0)+1): INDEX(F:F,MATCH($N8&"_TOTAL",$A:$A,0)-1) ),0) -> 0 | S8: =IFERROR(SUM( INDEX(G:G,MATCH($N8,$A:$A,0)+1): INDEX(G:G,MATCH($N8&"_TOTAL",$A:$A,0)-1) ),0) -> 0 | T8: =IFERROR(SUM( INDEX(H:H,MATCH($N8,$A:$A,0)+1): INDEX(H:H,MATCH($N8&"_TOTAL",$A:$A,0)-1) ),0) -> 0 | U8: =IFERROR(SUM( INDEX(J:J,MATCH($N8,$A:$A,0)+1): INDEX(J:J,MATCH($N8&"_TOTAL",$A:$A,0)-1) ),0) -> 0
A9: =IF(ISBLANK(B9),"",TEXT(B9,"dddd")) -> Wednesday | B9: 46239 | C9: =SUMIF(AUG!$B$3:$B$100, B9, AUG!$D$3:$D$100) -> 0 | D9: =IFERROR(__xludf.DUMMYFUNCTION("IFNA(INDEX(FILTER(AUG!$E$3:$E$100, AUG!$B$3:$B$100=B9), 1), ""-"")"),"-") -> - | E9: =SUMIF(AUG!$B$3:$B$100, B9, AUG!$F$3:$F$100) -> 0 | F9: =IFERROR(__xludf.DUMMYFUNCTION("IFNA(INDEX(FILTER(AUG!$G$3:$G$100, AUG!$B$3:$B$100=B9), 1), ""-"")"),"-") -> - | G9: =IFNA(SUMIF(AUG!$B$3:$B$100,B9,AUG!$H$3:$H$100),"-") -> 0 | H9: =E9*0.07% -> 0 | I9: =SUMIF(AUG!B:B, B9, AUG!K:K) -> 0 | J9: =G9-E9-H9 -> 0 | O9: =IFERROR(SUM( INDEX($C:$C,MATCH($N9,$A:$A,0)+1): INDEX($C:$C,MATCH($N9&"_TOTAL",$A:$A,0)-1) ),0) -> 0 | P9: =IFERROR(AVERAGE( INDEX(D:D,MATCH($N9,$A:$A,0)+1): INDEX(D:D,MATCH($N9&"_TOTAL",$A:$A,0)-1) ),0) -> 0 | Q9: =IFERROR(SUM( INDEX(E:E,MATCH($N9,$A:$A,0)+1): INDEX(E:E,MATCH($N9&"_TOTAL",$A:$A,0)-1) ),0) -> 0 | R9: =IFERROR(AVERAGE( INDEX(F:F,MATCH($N9,$A:$A,0)+1): INDEX(F:F,MATCH($N9&"_TOTAL",$A:$A,0)-1) ),0) -> 0 | S9: =IFERROR(SUM( INDEX(G:G,MATCH($N9,$A:$A,0)+1): INDEX(G:G,MATCH($N9&"_TOTAL",$A:$A,0)-1) ),0) -> 0 | T9: =IFERROR(SUM( INDEX(H:H,MATCH($N9,$A:$A,0)+1): INDEX(H:H,MATCH($N9&"_TOTAL",$A:$A,0)-1) ),0) -> 0 | U9: =IFERROR(SUM( INDEX(J:J,MATCH($N9,$A:$A,0)+1): INDEX(J:J,MATCH($N9&"_TOTAL",$A:$A,0)-1) ),0) -> 0
A10: =IF(ISBLANK(B10),"",TEXT(B10,"dddd")) -> Thursday | B10: 46240 | C10: =SUMIF(AUG!$B$3:$B$100, B10, AUG!$D$3:$D$100) -> 0 | D10: =IFERROR(__xludf.DUMMYFUNCTION("IFNA(INDEX(FILTER(AUG!$E$3:$E$100, AUG!$B$3:$B$100=B10), 1), ""-"")"),"-") -> - | E10: =SUMIF(AUG!$B$3:$B$100, B10, AUG!$F$3:$F$100) -> 0 | F10: =IFERROR(__xludf.DUMMYFUNCTION("IFNA(INDEX(FILTER(AUG!$G$3:$G$100, AUG!$B$3:$B$100=B10), 1), ""-"")"),"-") -> - | G10: =IFNA(SUMIF(AUG!$B$3:$B$100,B10,AUG!$H$3:$H$100),"-") -> 0 | H10: =E10*0.07% -> 0 | I10: =SUMIF(AUG!B:B, B10, AUG!K:K) -> 0 | J10: =G10-E10-H10 -> 0 | O10: =IFERROR(SUM( INDEX($C:$C,MATCH($N10,$A:$A,0)+1): INDEX($C:$C,MATCH($N10&"_TOTAL",$A:$A,0)-1) ),0) -> 0 | P10: =IFERROR(AVERAGE( INDEX(D:D,MATCH($N10,$A:$A,0)+1): INDEX(D:D,MATCH($N10&"_TOTAL",$A:$A,0)-1) ),0) -> 0 | Q10: =IFERROR(SUM( INDEX(E:E,MATCH($N10,$A:$A,0)+1): INDEX(E:E,MATCH($N10&"_TOTAL",$A:$A,0)-1) ),0) -> 0 | R10: =IFERROR(AVERAGE( INDEX(F:F,MATCH($N10,$A:$A,0)+1): INDEX(F:F,MATCH($N10&"_TOTAL",$A:$A,0)-1) ),0) -> 0 | S10: =IFERROR(SUM( INDEX(G:G,MATCH($N10,$A:$A,0)+1): INDEX(G:G,MATCH($N10&"_TOTAL",$A:$A,0)-1) ),0) -> 0 | T10: =IFERROR(SUM( INDEX(H:H,MATCH($N10,$A:$A,0)+1): INDEX(H:H,MATCH($N10&"_TOTAL",$A:$A,0)-1) ),0) -> 0 | U10: =IFERROR(SUM( INDEX(J:J,MATCH($N10,$A:$A,0)+1): INDEX(J:J,MATCH($N10&"_TOTAL",$A:$A,0)-1) ),0) -> 0
A11: =IF(ISBLANK(B11),"",TEXT(B11,"dddd")) -> Friday | B11: 46241 | C11: =SUMIF(AUG!$B$3:$B$100, B11, AUG!$D$3:$D$100) -> 0 | D11: =IFERROR(__xludf.DUMMYFUNCTION("IFNA(INDEX(FILTER(AUG!$E$3:$E$100, AUG!$B$3:$B$100=B11), 1), ""-"")"),"-") -> - | E11: =SUMIF(AUG!$B$3:$B$100, B11, AUG!$F$3:$F$100) -> 0 | F11: =IFERROR(__xludf.DUMMYFUNCTION("IFNA(INDEX(FILTER(AUG!$G$3:$G$100, AUG!$B$3:$B$100=B11), 1), ""-"")"),"-") -> - | G11: =IFNA(SUMIF(AUG!$B$3:$B$100,B11,AUG!$H$3:$H$100),"-") -> 0 | H11: =E11*0.07% -> 0 | I11: =SUMIF(AUG!B:B, B11, AUG!K:K) -> 0 | J11: =G11-E11-H11 -> 0 | O11: =IFERROR(SUM( INDEX($C:$C,MATCH($N11,$A:$A,0)+1): INDEX($C:$C,MATCH($N11&"_TOTAL",$A:$A,0)-1) ),0) -> 0 | P11: =IFERROR(AVERAGE( INDEX(D:D,MATCH($N11,$A:$A,0)+1): INDEX(D:D,MATCH($N11&"_TOTAL",$A:$A,0)-1) ),0) -> 0 | Q11: =IFERROR(SUM( INDEX(E:E,MATCH($N11,$A:$A,0)+1): INDEX(E:E,MATCH($N11&"_TOTAL",$A:$A,0)-1) ),0) -> 0 | R11: =IFERROR(AVERAGE( INDEX(F:F,MATCH($N11,$A:$A,0)+1): INDEX(F:F,MATCH($N11&"_TOTAL",$A:$A,0)-1) ),0) -> 0 | S11: =IFERROR(SUM( INDEX(G:G,MATCH($N11,$A:$A,0)+1): INDEX(G:G,MATCH($N11&"_TOTAL",$A:$A,0)-1) ),0) -> 0 | T11: =IFERROR(SUM( INDEX(H:H,MATCH($N11,$A:$A,0)+1): INDEX(H:H,MATCH($N11&"_TOTAL",$A:$A,0)-1) ),0) -> 0 | U11: =IFERROR(SUM( INDEX(J:J,MATCH($N11,$A:$A,0)+1): INDEX(J:J,MATCH($N11&"_TOTAL",$A:$A,0)-1) ),0) -> 0
A12: =IF(ISBLANK(B12),"",TEXT(B12,"dddd")) -> Saturday | B12: 46242 | C12: =SUMIF(AUG!$B$3:$B$100, B12, AUG!$D$3:$D$100) -> 0 | D12: =IFERROR(__xludf.DUMMYFUNCTION("IFNA(INDEX(FILTER(AUG!$E$3:$E$100, AUG!$B$3:$B$100=B12), 1), ""-"")"),"-") -> - | E12: =SUMIF(AUG!$B$3:$B$100, B12, AUG!$F$3:$F$100) -> 0 | F12: =IFERROR(__xludf.DUMMYFUNCTION("IFNA(INDEX(FILTER(AUG!$G$3:$G$100, AUG!$B$3:$B$100=B12), 1), ""-"")"),"-") -> - | G12: =IFNA(SUMIF(AUG!$B$3:$B$100,B12,AUG!$H$3:$H$100),"-") -> 0 | H12: =E12*0.07% -> 0 | I12: =SUMIF(AUG!B:B, B12, AUG!K:K) -> 0 | J12: =G12-E12-H12 -> 0 | O12: =IFERROR(SUM( INDEX($C:$C,MATCH($N12,$A:$A,0)+1): INDEX($C:$C,MATCH($N12&"_TOTAL",$A:$A,0)-1) ),0) -> 0 | P12: =IFERROR(AVERAGE( INDEX(D:D,MATCH($N12,$A:$A,0)+1): INDEX(D:D,MATCH($N12&"_TOTAL",$A:$A,0)-1) ),0) -> 0 | Q12: =IFERROR(SUM( INDEX(E:E,MATCH($N12,$A:$A,0)+1): INDEX(E:E,MATCH($N12&"_TOTAL",$A:$A,0)-1) ),0) -> 0 | R12: =IFERROR(AVERAGE( INDEX(F:F,MATCH($N12,$A:$A,0)+1): INDEX(F:F,MATCH($N12&"_TOTAL",$A:$A,0)-1) ),0) -> 0 | S12: =IFERROR(SUM( INDEX(G:G,MATCH($N12,$A:$A,0)+1): INDEX(G:G,MATCH($N12&"_TOTAL",$A:$A,0)-1) ),0) -> 0 | T12: =IFERROR(SUM( INDEX(H:H,MATCH($N12,$A:$A,0)+1): INDEX(H:H,MATCH($N12&"_TOTAL",$A:$A,0)-1) ),0) -> 0 | U12: =IFERROR(SUM( INDEX(J:J,MATCH($N12,$A:$A,0)+1): INDEX(J:J,MATCH($N12&"_TOTAL",$A:$A,0)-1) ),0) -> 0
A13: =IF(ISBLANK(B13),"",TEXT(B13,"dddd")) -> Sunday | B13: 46243 | C13: =SUMIF(AUG!$B$3:$B$100, B13, AUG!$D$3:$D$100) -> 0 | D13: =IFERROR(__xludf.DUMMYFUNCTION("IFNA(INDEX(FILTER(AUG!$E$3:$E$100, AUG!$B$3:$B$100=B13), 1), ""-"")"),"-") -> - | E13: =SUMIF(AUG!$B$3:$B$100, B13, AUG!$F$3:$F$100) -> 0 | F13: =IFERROR(__xludf.DUMMYFUNCTION("IFNA(INDEX(FILTER(AUG!$G$3:$G$100, AUG!$B$3:$B$100=B13), 1), ""-"")"),"-") -> - | G13: =IFNA(SUMIF(AUG!$B$3:$B$100,B13,AUG!$H$3:$H$100),"-") -> 0 | H13: =E13*0.07% -> 0 | I13: =SUMIF(AUG!B:B, B13, AUG!K:K) -> 0 | J13: =G13-E13-H13 -> 0 | O13: =IFERROR(SUM( INDEX($C:$C,MATCH($N13,$A:$A,0)+1): INDEX($C:$C,MATCH($N13&"_TOTAL",$A:$A,0)-1) ),0) -> 0 | P13: =IFERROR(AVERAGE( INDEX(D:D,MATCH($N13,$A:$A,0)+1): INDEX(D:D,MATCH($N13&"_TOTAL",$A:$A,0)-1) ),0) -> 0 | Q13: =IFERROR(SUM( INDEX(E:E,MATCH($N13,$A:$A,0)+1): INDEX(E:E,MATCH($N13&"_TOTAL",$A:$A,0)-1) ),0) -> 0 | R13: =IFERROR(AVERAGE( INDEX(F:F,MATCH($N13,$A:$A,0)+1): INDEX(F:F,MATCH($N13&"_TOTAL",$A:$A,0)-1) ),0) -> 0 | S13: =IFERROR(SUM( INDEX(G:G,MATCH($N13,$A:$A,0)+1): INDEX(G:G,MATCH($N13&"_TOTAL",$A:$A,0)-1) ),0) -> 0 | T13: =IFERROR(SUM( INDEX(H:H,MATCH($N13,$A:$A,0)+1): INDEX(H:H,MATCH($N13&"_TOTAL",$A:$A,0)-1) ),0) -> 0 | U13: =IFERROR(SUM( INDEX(J:J,MATCH($N13,$A:$A,0)+1): INDEX(J:J,MATCH($N13&"_TOTAL",$A:$A,0)-1) ),0) -> 0
A14: =IF(ISBLANK(B14),"",TEXT(B14,"dddd")) -> Monday | B14: 46244 | C14: =SUMIF(AUG!$B$3:$B$100, B14, AUG!$D$3:$D$100) -> 169571.35 | D14: =IFERROR(__xludf.DUMMYFUNCTION("IFNA(INDEX(FILTER(AUG!$E$3:$E$100, AUG!$B$3:$B$100=B14), 1), ""-"")"),17664.016100178887) -> 17664.016 | E14: =SUMIF(AUG!$B$3:$B$100, B14, AUG!$F$3:$F$100) -> 2995016202 | F14: =IFERROR(__xludf.DUMMYFUNCTION("IFNA(INDEX(FILTER(AUG!$G$3:$G$100, AUG!$B$3:$B$100=B14), 1), ""-"")"),17690.0) -> 17690 | G14: =IFNA(SUMIF(AUG!$B$3:$B$100,B14,AUG!$H$3:$H$100),"-") -> 2999999747 | H14: =E14*0.07% -> 2096511.3 | I14: =SUMIF(AUG!B:B, B14, AUG!K:K) -> 4983544.9 | J14: =G14-E14-H14 -> 2887033.6 | O14: =IFERROR(SUM( INDEX($C:$C,MATCH($N14,$A:$A,0)+1): INDEX($C:$C,MATCH($N14&"_TOTAL",$A:$A,0)-1) ),0) -> 0 | P14: =IFERROR(AVERAGE( INDEX(D:D,MATCH($N14,$A:$A,0)+1): INDEX(D:D,MATCH($N14&"_TOTAL",$A:$A,0)-1) ),0) -> 0 | Q14: =IFERROR(SUM( INDEX(E:E,MATCH($N14,$A:$A,0)+1): INDEX(E:E,MATCH($N14&"_TOTAL",$A:$A,0)-1) ),0) -> 0 | R14: =IFERROR(AVERAGE( INDEX(F:F,MATCH($N14,$A:$A,0)+1): INDEX(F:F,MATCH($N14&"_TOTAL",$A:$A,0)-1) ),0) -> 0 | S14: =IFERROR(SUM( INDEX(G:G,MATCH($N14,$A:$A,0)+1): INDEX(G:G,MATCH($N14&"_TOTAL",$A:$A,0)-1) ),0) -> 0 | T14: =IFERROR(SUM( INDEX(H:H,MATCH($N14,$A:$A,0)+1): INDEX(H:H,MATCH($N14&"_TOTAL",$A:$A,0)-1) ),0) -> 0 | U14: =IFERROR(SUM( INDEX(J:J,MATCH($N14,$A:$A,0)+1): INDEX(J:J,MATCH($N14&"_TOTAL",$A:$A,0)-1) ),0) -> 0
A15: =IF(ISBLANK(B15),"",TEXT(B15,"dddd")) -> Tuesday | B15: 46245 | C15: =SUMIF(AUG!$B$3:$B$100, B15, AUG!$D$3:$D$100) -> 112867.13 | D15: =IFERROR(__xludf.DUMMYFUNCTION("IFNA(INDEX(FILTER(AUG!$E$3:$E$100, AUG!$B$3:$B$100=B15), 1), ""-"")"),17706.222945928384) -> 17706.223 | E15: =SUMIF(AUG!$B$3:$B$100, B15, AUG!$F$3:$F$100) -> 1998872404 | F15: =IFERROR(__xludf.DUMMYFUNCTION("IFNA(INDEX(FILTER(AUG!$G$3:$G$100, AUG!$B$3:$B$100=B15), 1), ""-"")"),17690.0) -> 17690 | G15: =IFNA(SUMIF(AUG!$B$3:$B$100,B15,AUG!$H$3:$H$100),"-") -> 1999999811 | H15: =E15*0.07% -> 1399210.7 | I15: =SUMIF(AUG!B:B, B15, AUG!K:K) -> 1127407.3 | J15: =G15-E15-H15 -> -271803.38 | O15: =IFERROR(SUM( INDEX($C:$C,MATCH($N15,$A:$A,0)+1): INDEX($C:$C,MATCH($N15&"_TOTAL",$A:$A,0)-1) ),0) -> 0 | P15: =IFERROR(AVERAGE( INDEX(D:D,MATCH($N15,$A:$A,0)+1): INDEX(D:D,MATCH($N15&"_TOTAL",$A:$A,0)-1) ),0) -> 0 | Q15: =IFERROR(SUM( INDEX(E:E,MATCH($N15,$A:$A,0)+1): INDEX(E:E,MATCH($N15&"_TOTAL",$A:$A,0)-1) ),0) -> 0 | R15: =IFERROR(AVERAGE( INDEX(F:F,MATCH($N15,$A:$A,0)+1): INDEX(F:F,MATCH($N15&"_TOTAL",$A:$A,0)-1) ),0) -> 0 | S15: =IFERROR(SUM( INDEX(G:G,MATCH($N15,$A:$A,0)+1): INDEX(G:G,MATCH($N15&"_TOTAL",$A:$A,0)-1) ),0) -> 0 | T15: =IFERROR(SUM( INDEX(H:H,MATCH($N15,$A:$A,0)+1): INDEX(H:H,MATCH($N15&"_TOTAL",$A:$A,0)-1) ),0) -> 0 | U15: =IFERROR(SUM( INDEX(J:J,MATCH($N15,$A:$A,0)+1): INDEX(J:J,MATCH($N15&"_TOTAL",$A:$A,0)-1) ),0) -> 0
A16: =IF(ISBLANK(B16),"",TEXT(B16,"dddd")) -> Wednesday | B16: 46246 | C16: =SUMIF(AUG!$B$3:$B$100, B16, AUG!$D$3:$D$100) -> 280725.49 | D16: =IFERROR(__xludf.DUMMYFUNCTION("IFNA(INDEX(FILTER(AUG!$E$3:$E$100, AUG!$B$3:$B$100=B16), 1), ""-"")"),17778.171636799914) -> 17778.172 | E16: =SUMIF(AUG!$B$3:$B$100, B16, AUG!$F$3:$F$100) -> 4988596546 | F16: =IFERROR(__xludf.DUMMYFUNCTION("IFNA(INDEX(FILTER(AUG!$G$3:$G$100, AUG!$B$3:$B$100=B16), 1), ""-"")"),17825.0) -> 17825 | G16: =IFNA(SUMIF(AUG!$B$3:$B$100,B16,AUG!$H$3:$H$100),"-") -> 4999999591 | H16: =E16*0.07% -> 3492017.6 | I16: =SUMIF(AUG!B:B, B16, AUG!K:K) -> 11403045 | J16: =G16-E16-H16 -> 7911027 | O16: =IFERROR(SUM( INDEX($C:$C,MATCH($N16,$A:$A,0)+1): INDEX($C:$C,MATCH($N16&"_TOTAL",$A:$A,0)-1) ),0) -> 0 | P16: =IFERROR(AVERAGE( INDEX(D:D,MATCH($N16,$A:$A,0)+1): INDEX(D:D,MATCH($N16&"_TOTAL",$A:$A,0)-1) ),0) -> 0 | Q16: =IFERROR(SUM( INDEX(E:E,MATCH($N16,$A:$A,0)+1): INDEX(E:E,MATCH($N16&"_TOTAL",$A:$A,0)-1) ),0) -> 0 | R16: =IFERROR(AVERAGE( INDEX(F:F,MATCH($N16,$A:$A,0)+1): INDEX(F:F,MATCH($N16&"_TOTAL",$A:$A,0)-1) ),0) -> 0 | S16: =IFERROR(SUM( INDEX(G:G,MATCH($N16,$A:$A,0)+1): INDEX(G:G,MATCH($N16&"_TOTAL",$A:$A,0)-1) ),0) -> 0 | T16: =IFERROR(SUM( INDEX(H:H,MATCH($N16,$A:$A,0)+1): INDEX(H:H,MATCH($N16&"_TOTAL",$A:$A,0)-1) ),0) -> 0 | U16: =IFERROR(SUM( INDEX(J:J,MATCH($N16,$A:$A,0)+1): INDEX(J:J,MATCH($N16&"_TOTAL",$A:$A,0)-1) ),0) -> 0
A17: =IF(ISBLANK(B17),"",TEXT(B17,"dddd")) -> Thursday | B17: 46247 | C17: =SUMIF(AUG!$B$3:$B$100, B17, AUG!$D$3:$D$100) -> 224482.63 | D17: =IFERROR(__xludf.DUMMYFUNCTION("IFNA(INDEX(FILTER(AUG!$E$3:$E$100, AUG!$B$3:$B$100=B17), 1), ""-"")"),17799.999999999996) -> 17800 | E17: =SUMIF(AUG!$B$3:$B$100, B17, AUG!$F$3:$F$100) -> 3991544223 | F17: =IFERROR(__xludf.DUMMYFUNCTION("IFNA(INDEX(FILTER(AUG!$G$3:$G$100, AUG!$B$3:$B$100=B17), 1), ""-"")"),17820.0) -> 17820 | G17: =IFNA(SUMIF(AUG!$B$3:$B$100,B17,AUG!$H$3:$H$100),"-") -> 3999999804 | H17: =E17*0.07% -> 2794081 | I17: =SUMIF(AUG!B:B, B17, AUG!K:K) -> 8455581.7 | J17: =G17-E17-H17 -> 5661500.8
A18: =IF(ISBLANK(B18),"",TEXT(B18,"dddd")) -> Friday | B18: 46248 | C18: =SUMIF(AUG!$B$3:$B$100, B18, AUG!$D$3:$D$100) -> 168760.54 | D18: =IFERROR(__xludf.DUMMYFUNCTION("IFNA(INDEX(FILTER(AUG!$E$3:$E$100, AUG!$B$3:$B$100=B18), 1), ""-"")"),17740.336250307795) -> 17740.336 | E18: =SUMIF(AUG!$B$3:$B$100, B18, AUG!$F$3:$F$100) -> 2992263337 | F18: =IFERROR(__xludf.DUMMYFUNCTION("IFNA(INDEX(FILTER(AUG!$G$3:$G$100, AUG!$B$3:$B$100=B18), 1), ""-"")"),17780.0) -> 17780 | G18: =IFNA(SUMIF(AUG!$B$3:$B$100,B18,AUG!$H$3:$H$100),"-") -> 2999999813 | H18: =E18*0.07% -> 2094584.3 | I18: =SUMIF(AUG!B:B, B18, AUG!K:K) -> 7736476.1 | J18: =G18-E18-H18 -> 5641891.7
A19: =IF(ISBLANK(B19),"",TEXT(B19,"dddd")) -> Saturday | B19: 46249 | C19: =SUMIF(AUG!$B$3:$B$100, B19, AUG!$D$3:$D$100) -> 98651.13 | D19: =IFERROR(__xludf.DUMMYFUNCTION("IFNA(INDEX(FILTER(AUG!$E$3:$E$100, AUG!$B$3:$B$100=B19), 1), ""-"")"),17708.98471159263) -> 17708.985 | E19: =SUMIF(AUG!$B$3:$B$100, B19, AUG!$F$3:$F$100) -> 1746056544 | F19: =IFERROR(__xludf.DUMMYFUNCTION("IFNA(INDEX(FILTER(AUG!$G$3:$G$100, AUG!$B$3:$B$100=B19), 1), ""-"")"),17750.0) -> 17750 | G19: =IFNA(SUMIF(AUG!$B$3:$B$100,B19,AUG!$H$3:$H$100),"-") -> 1749999730 | H19: =E19*0.07% -> 1222239.6 | I19: =SUMIF(AUG!B:B, B19, AUG!K:K) -> 3943185.3 | J19: =G19-E19-H19 -> 2720945.7
A20: =IF(ISBLANK(B20),"",TEXT(B20,"dddd")) -> Sunday | B20: 46250 | C20: =SUMIF(AUG!$B$3:$B$100, B20, AUG!$D$3:$D$100) -> 0 | D20: =IFERROR(__xludf.DUMMYFUNCTION("IFNA(INDEX(FILTER(AUG!$E$3:$E$100, AUG!$B$3:$B$100=B20), 1), ""-"")"),"-") -> - | E20: =SUMIF(AUG!$B$3:$B$100, B20, AUG!$F$3:$F$100) -> 0 | F20: =IFERROR(__xludf.DUMMYFUNCTION("IFNA(INDEX(FILTER(AUG!$G$3:$G$100, AUG!$B$3:$B$100=B20), 1), ""-"")"),"-") -> - | G20: =IFNA(SUMIF(AUG!$B$3:$B$100,B20,AUG!$H$3:$H$100),"-") -> 0 | H20: =E20*0.07% -> 0 | I20: =SUMIF(AUG!B:B, B20, AUG!K:K) -> 0 | J20: =G20-E20-H20 -> 0
A21: =IF(ISBLANK(B21),"",TEXT(B21,"dddd")) -> Monday | B21: 46251 | C21: =SUMIF(AUG!$B$3:$B$100, B21, AUG!$D$3:$D$100) -> 56317.42 | D21: =IFERROR(__xludf.DUMMYFUNCTION("IFNA(INDEX(FILTER(AUG!$E$3:$E$100, AUG!$B$3:$B$100=B21), 1), ""-"")"),17732.924200571902) -> 17732.924 | E21: =SUMIF(AUG!$B$3:$B$100, B21, AUG!$F$3:$F$100) -> 9.9838322e+08 | F21: =IFERROR(__xludf.DUMMYFUNCTION("IFNA(INDEX(FILTER(AUG!$G$3:$G$100, AUG!$B$3:$B$100=B21), 1), ""-"")"),17745.0) -> 17745 | G21: =IFNA(SUMIF(AUG!$B$3:$B$100,B21,AUG!$H$3:$H$100),"-") -> 9.9999985e+08 | H21: =E21*0.07% -> 698868.25 | I21: =SUMIF(AUG!B:B, B21, AUG!K:K) -> 1616633.4 | J21: =G21-E21-H21 -> 917765.12
A22: =IF(ISBLANK(B22),"",TEXT(B22,"dddd")) -> Tuesday | B22: 46252 | C22: =SUMIF(AUG!$B$3:$B$100, B22, AUG!$D$3:$D$100) -> 28089.88 | D22: =IFERROR(__xludf.DUMMYFUNCTION("IFNA(INDEX(FILTER(AUG!$E$3:$E$100, AUG!$B$3:$B$100=B22), 1), ""-"")"),17770.0) -> 17770 | E22: =SUMIF(AUG!$B$3:$B$100, B22, AUG!$F$3:$F$100) -> 4.9915717e+08 | F22: =IFERROR(__xludf.DUMMYFUNCTION("IFNA(INDEX(FILTER(AUG!$G$3:$G$100, AUG!$B$3:$B$100=B22), 1), ""-"")"),17800.0) -> 17800 | G22: =IFNA(SUMIF(AUG!$B$3:$B$100,B22,AUG!$H$3:$H$100),"-") -> 499999864 | H22: =E22*0.07% -> 349410.02 | I22: =SUMIF(AUG!B:B, B22, AUG!K:K) -> 842696.4 | J22: =G22-E22-H22 -> 493286.38
A23: =IF(ISBLANK(B23),"",TEXT(B23,"dddd")) -> Wednesday | B23: 46253 | C23: =SUMIF(AUG!$B$3:$B$100, B23, AUG!$D$3:$D$100) -> 0 | D23: =IFERROR(__xludf.DUMMYFUNCTION("IFNA(INDEX(FILTER(AUG!$E$3:$E$100, AUG!$B$3:$B$100=B23), 1), ""-"")"),"-") -> - | E23: =SUMIF(AUG!$B$3:$B$100, B23, AUG!$F$3:$F$100) -> 0 | F23: =IFERROR(__xludf.DUMMYFUNCTION("IFNA(INDEX(FILTER(AUG!$G$3:$G$100, AUG!$B$3:$B$100=B23), 1), ""-"")"),"-") -> - | G23: =IFNA(SUMIF(AUG!$B$3:$B$100,B23,AUG!$H$3:$H$100),"-") -> 0 | H23: =E23*0.07% -> 0 | I23: =SUMIF(AUG!B:B, B23, AUG!K:K) -> 0 | J23: =G23-E23-H23 -> 0
A24: =IF(ISBLANK(B24),"",TEXT(B24,"dddd")) -> Thursday | B24: 46254 | C24: =SUMIF(AUG!$B$3:$B$100, B24, AUG!$D$3:$D$100) -> 0 | D24: =IFERROR(__xludf.DUMMYFUNCTION("IFNA(INDEX(FILTER(AUG!$E$3:$E$100, AUG!$B$3:$B$100=B24), 1), ""-"")"),"-") -> - | E24: =SUMIF(AUG!$B$3:$B$100, B24, AUG!$F$3:$F$100) -> 0 | F24: =IFERROR(__xludf.DUMMYFUNCTION("IFNA(INDEX(FILTER(AUG!$G$3:$G$100, AUG!$B$3:$B$100=B24), 1), ""-"")"),"-") -> - | G24: =IFNA(SUMIF(AUG!$B$3:$B$100,B24,AUG!$H$3:$H$100),"-") -> 0 | H24: =E24*0.07% -> 0 | I24: =SUMIF(AUG!B:B, B24, AUG!K:K) -> 0 | J24: =G24-E24-H24 -> 0
A25: =IF(ISBLANK(B25),"",TEXT(B25,"dddd")) -> Friday | B25: 46255 | C25: =SUMIF(AUG!$B$3:$B$100, B25, AUG!$D$3:$D$100) -> 0 | D25: =IFERROR(__xludf.DUMMYFUNCTION("IFNA(INDEX(FILTER(AUG!$E$3:$E$100, AUG!$B$3:$B$100=B25), 1), ""-"")"),"-") -> - | E25: =SUMIF(AUG!$B$3:$B$100, B25, AUG!$F$3:$F$100) -> 0 | F25: =IFERROR(__xludf.DUMMYFUNCTION("IFNA(INDEX(FILTER(AUG!$G$3:$G$100, AUG!$B$3:$B$100=B25), 1), ""-"")"),"-") -> - | G25: =IFNA(SUMIF(AUG!$B$3:$B$100,B25,AUG!$H$3:$H$100),"-") -> 0 | H25: =E25*0.07% -> 0 | I25: =SUMIF(AUG!B:B, B25, AUG!K:K) -> 0 | J25: =G25-E25-H25 -> 0
A26: =IF(ISBLANK(B26),"",TEXT(B26,"dddd")) -> Saturday | B26: 46256 | C26: =SUMIF(AUG!$B$3:$B$100, B26, AUG!$D$3:$D$100) -> 0 | D26: =IFERROR(__xludf.DUMMYFUNCTION("IFNA(INDEX(FILTER(AUG!$E$3:$E$100, AUG!$B$3:$B$100=B26), 1), ""-"")"),"-") -> - | E26: =SUMIF(AUG!$B$3:$B$100, B26, AUG!$F$3:$F$100) -> 0 | F26: =IFERROR(__xludf.DUMMYFUNCTION("IFNA(INDEX(FILTER(AUG!$G$3:$G$100, AUG!$B$3:$B$100=B26), 1), ""-"")"),"-") -> - | G26: =IFNA(SUMIF(AUG!$B$3:$B$100,B26,AUG!$H$3:$H$100),"-") -> 0 | H26: =E26*0.07% -> 0 | I26: =SUMIF(AUG!B:B, B26, AUG!K:K) -> 0 | J26: =G26-E26-H26 -> 0
A27: =IF(ISBLANK(B27),"",TEXT(B27,"dddd")) -> Sunday | B27: 46257 | C27: =SUMIF(AUG!$B$3:$B$100, B27, AUG!$D$3:$D$100) -> 0 | D27: =IFERROR(__xludf.DUMMYFUNCTION("IFNA(INDEX(FILTER(AUG!$E$3:$E$100, AUG!$B$3:$B$100=B27), 1), ""-"")"),"-") -> - | E27: =SUMIF(AUG!$B$3:$B$100, B27, AUG!$F$3:$F$100) -> 0 | F27: =IFERROR(__xludf.DUMMYFUNCTION("IFNA(INDEX(FILTER(AUG!$G$3:$G$100, AUG!$B$3:$B$100=B27), 1), ""-"")"),"-") -> - | G27: =IFNA(SUMIF(AUG!$B$3:$B$100,B27,AUG!$H$3:$H$100),"-") -> 0 | H27: =E27*0.07% -> 0 | I27: =SUMIF(AUG!B:B, B27, AUG!K:K) -> 0 | J27: =G27-E27-H27 -> 0
A28: =IF(ISBLANK(B28),"",TEXT(B28,"dddd")) -> Monday | B28: 46258 | C28: =SUMIF(AUG!$B$3:$B$100, B28, AUG!$D$3:$D$100) -> 0 | D28: =IFERROR(__xludf.DUMMYFUNCTION("IFNA(INDEX(FILTER(AUG!$E$3:$E$100, AUG!$B$3:$B$100=B28), 1), ""-"")"),"-") -> - | E28: =SUMIF(AUG!$B$3:$B$100, B28, AUG!$F$3:$F$100) -> 0 | F28: =IFERROR(__xludf.DUMMYFUNCTION("IFNA(INDEX(FILTER(AUG!$G$3:$G$100, AUG!$B$3:$B$100=B28), 1), ""-"")"),"-") -> - | G28: =IFNA(SUMIF(AUG!$B$3:$B$100,B28,AUG!$H$3:$H$100),"-") -> 0 | H28: =E28*0.07% -> 0 | I28: =SUMIF(AUG!B:B, B28, AUG!K:K) -> 0 | J28: =G28-E28-H28 -> 0
A29: =IF(ISBLANK(B29),"",TEXT(B29,"dddd")) -> Tuesday | B29: 46259 | C29: =SUMIF(AUG!$B$3:$B$100, B29, AUG!$D$3:$D$100) -> 0 | D29: =IFERROR(__xludf.DUMMYFUNCTION("IFNA(INDEX(FILTER(AUG!$E$3:$E$100, AUG!$B$3:$B$100=B29), 1), ""-"")"),"-") -> - | E29: =SUMIF(AUG!$B$3:$B$100, B29, AUG!$F$3:$F$100) -> 0 | F29: =IFERROR(__xludf.DUMMYFUNCTION("IFNA(INDEX(FILTER(AUG!$G$3:$G$100, AUG!$B$3:$B$100=B29), 1), ""-"")"),"-") -> - | G29: =IFNA(SUMIF(AUG!$B$3:$B$100,B29,AUG!$H$3:$H$100),"-") -> 0 | H29: =E29*0.07% -> 0 | I29: =SUMIF(AUG!B:B, B29, AUG!K:K) -> 0 | J29: =G29-E29-H29 -> 0
A30: =IF(ISBLANK(B30),"",TEXT(B30,"dddd")) -> Wednesday | B30: 46260 | C30: =SUMIF(AUG!$B$3:$B$100, B30, AUG!$D$3:$D$100) -> 0 | D30: =IFERROR(__xludf.DUMMYFUNCTION("IFNA(INDEX(FILTER(AUG!$E$3:$E$100, AUG!$B$3:$B$100=B30), 1), ""-"")"),"-") -> - | E30: =SUMIF(AUG!$B$3:$B$100, B30, AUG!$F$3:$F$100) -> 0 | F30: =IFERROR(__xludf.DUMMYFUNCTION("IFNA(INDEX(FILTER(AUG!$G$3:$G$100, AUG!$B$3:$B$100=B30), 1), ""-"")"),"-") -> - | G30: =IFNA(SUMIF(AUG!$B$3:$B$100,B30,AUG!$H$3:$H$100),"-") -> 0 | H30: =E30*0.07% -> 0 | I30: =SUMIF(AUG!B:B, B30, AUG!K:K) -> 0 | J30: =G30-E30-H30 -> 0
A31: =IF(ISBLANK(B31),"",TEXT(B31,"dddd")) -> Thursday | B31: 46261 | C31: =SUMIF(AUG!$B$3:$B$100, B31, AUG!$D$3:$D$100) -> 0 | D31: =IFERROR(__xludf.DUMMYFUNCTION("IFNA(INDEX(FILTER(AUG!$E$3:$E$100, AUG!$B$3:$B$100=B31), 1), ""-"")"),"-") -> - | E31: =SUMIF(AUG!$B$3:$B$100, B31, AUG!$F$3:$F$100) -> 0 | F31: =IFERROR(__xludf.DUMMYFUNCTION("IFNA(INDEX(FILTER(AUG!$G$3:$G$100, AUG!$B$3:$B$100=B31), 1), ""-"")"),"-") -> - | G31: =IFNA(SUMIF(AUG!$B$3:$B$100,B31,AUG!$H$3:$H$100),"-") -> 0 | H31: =E31*0.07% -> 0 | I31: =SUMIF(AUG!B:B, B31, AUG!K:K) -> 0 | J31: =G31-E31-H31 -> 0
A32: =IF(ISBLANK(B32),"",TEXT(B32,"dddd")) -> Friday | B32: 46262 | C32: =SUMIF(AUG!$B$3:$B$100, B32, AUG!$D$3:$D$100) -> 0 | D32: =IFERROR(__xludf.DUMMYFUNCTION("IFNA(INDEX(FILTER(AUG!$E$3:$E$100, AUG!$B$3:$B$100=B32), 1), ""-"")"),"-") -> - | E32: =SUMIF(AUG!$B$3:$B$100, B32, AUG!$F$3:$F$100) -> 0 | F32: =IFERROR(__xludf.DUMMYFUNCTION("IFNA(INDEX(FILTER(AUG!$G$3:$G$100, AUG!$B$3:$B$100=B32), 1), ""-"")"),"-") -> - | G32: =IFNA(SUMIF(AUG!$B$3:$B$100,B32,AUG!$H$3:$H$100),"-") -> 0 | H32: =E32*0.07% -> 0 | I32: =SUMIF(AUG!B:B, B32, AUG!K:K) -> 0 | J32: =G32-E32-H32 -> 0
A33: =IF(ISBLANK(B33),"",TEXT(B33,"dddd")) -> Saturday | B33: 46263 | C33: =SUMIF(AUG!$B$3:$B$100, B33, AUG!$D$3:$D$100) -> 0 | D33: =IFERROR(__xludf.DUMMYFUNCTION("IFNA(INDEX(FILTER(AUG!$E$3:$E$100, AUG!$B$3:$B$100=B33), 1), ""-"")"),"-") -> - | E33: =SUMIF(AUG!$B$3:$B$100, B33, AUG!$F$3:$F$100) -> 0 | F33: =IFERROR(__xludf.DUMMYFUNCTION("IFNA(INDEX(FILTER(AUG!$G$3:$G$100, AUG!$B$3:$B$100=B33), 1), ""-"")"),"-") -> - | G33: =IFNA(SUMIF(AUG!$B$3:$B$100,B33,AUG!$H$3:$H$100),"-") -> 0 | H33: =E33*0.07% -> 0 | I33: =SUMIF(AUG!B:B, B33, AUG!K:K) -> 0 | J33: =G33-E33-H33 -> 0
A34: =IF(ISBLANK(B34),"",TEXT(B34,"dddd")) -> Sunday | B34: 46264 | C34: =SUMIF(AUG!$B$3:$B$100, B34, AUG!$D$3:$D$100) -> 0 | D34: =IFERROR(__xludf.DUMMYFUNCTION("IFNA(INDEX(FILTER(AUG!$E$3:$E$100, AUG!$B$3:$B$100=B34), 1), ""-"")"),"-") -> - | E34: =SUMIF(AUG!$B$3:$B$100, B34, AUG!$F$3:$F$100) -> 0 | F34: =IFERROR(__xludf.DUMMYFUNCTION("IFNA(INDEX(FILTER(AUG!$G$3:$G$100, AUG!$B$3:$B$100=B34), 1), ""-"")"),"-") -> - | G34: =IFNA(SUMIF(AUG!$B$3:$B$100,B34,AUG!$H$3:$H$100),"-") -> 0 | H34: =E34*0.07% -> 0 | I34: =SUMIF(AUG!B:B, B34, AUG!K:K) -> 0 | J34: =G34-E34-H34 -> 0
A35: =IF(ISBLANK(B35),"",TEXT(B35,"dddd")) -> Monday | B35: 46265 | C35: =SUMIF(AUG!$B$3:$B$100, B35, AUG!$D$3:$D$100) -> 0 | D35: =IFERROR(__xludf.DUMMYFUNCTION("IFNA(INDEX(FILTER(AUG!$E$3:$E$100, AUG!$B$3:$B$100=B35), 1), ""-"")"),"-") -> - | E35: =SUMIF(AUG!$B$3:$B$100, B35, AUG!$F$3:$F$100) -> 0 | F35: =IFERROR(__xludf.DUMMYFUNCTION("IFNA(INDEX(FILTER(AUG!$G$3:$G$100, AUG!$B$3:$B$100=B35), 1), ""-"")"),"-") -> - | G35: =IFNA(SUMIF(AUG!$B$3:$B$100,B35,AUG!$H$3:$H$100),"-") -> 0 | H35: =E35*0.07% -> 0 | I35: =SUMIF(AUG!B:B, B35, AUG!K:K) -> 0 | J35: =G35-E35-H35 -> 0
A36: =CONCAT(A4,"_TOTAL") -> AUG_TOTAL | C36: =sum(C5:C35) -> 1139465.6 | D36: =IFERROR(IF(AVERAGE(D5:D35)=0,"-",AVERAGE(D5:D35)),"-") -> 17737.582 | E36: =sum(E5:E35) -> 20209889639 | F36: =IFERROR(IF(AVERAGE(F5:F35)=0,"-",AVERAGE(F5:F35)),"-") -> 17762.5 | G36: =sum(G5:G35) -> 20249998209 | H36: =sum(H5:H35) -> 14146923 | I36: =sum(I5:I35) -> 40108570 | J36: =sum(J5:J35) -> 25961647
A37: SEP
A38: =IF(ISBLANK(B38),"",TEXT(B38,"dddd")) -> Tuesday | B38: 46266 | C38: =SUMIF(SEP!$B$3:$B$101, B38, SEP!$D$3:$D$101) -> 263607.97 | D38: =IFERROR(__xludf.DUMMYFUNCTION("IFNA(INDEX(FILTER(SEP!$E$3:$E$100, SEP!$B$3:$B$100=B38), 1), ""-"")"),17631.61273918904) -> 17631.613 | E38: =SUMIF(SEP!$B$3:$B$101, B38, SEP!$F$3:$F$101) -> 4648033379 | F38: =IFERROR(__xludf.DUMMYFUNCTION("IFNA(INDEX(FILTER(SEP!$G$3:$G$100, SEP!$B$3:$B$100=B38), 1), ""-"")"),17675.0) -> 17675 | G38: =IFNA(SUMIF(SEP!$B$3:$B$900,B38,SEP!$H$3:$H$900),"-") -> 4656949679 | H38: =SUMIF(SEP!B:B, B38, SEP!J:J) -> 812399.11 | I38: =SUMIF(SEP!B:B, B38, SEP!K:K) -> 8916300.3 | J38: =G38-E38-H38 -> 8103901.2
A39: =IF(ISBLANK(B39),"",TEXT(B39,"dddd")) -> Wednesday | B39: 46267 | C39: =SUMIF(SEP!$B$3:$B$101, B39, SEP!$D$3:$D$101) -> 426052.27 | D39: =IFERROR(__xludf.DUMMYFUNCTION("IFNA(INDEX(FILTER(SEP!$E$3:$E$100, SEP!$B$3:$B$100=B39), 1), ""-"")"),17669.94174431459) -> 17669.942 | E39: =SUMIF(SEP!$B$3:$B$101, B39, SEP!$F$3:$F$101) -> 7522792266 | F39: =IFERROR(__xludf.DUMMYFUNCTION("IFNA(INDEX(FILTER(SEP!$G$3:$G$100, SEP!$B$3:$B$100=B39), 1), ""-"")"),17695.0) -> 17695 | G39: =IFNA(SUMIF(SEP!$B$3:$B$900,B39,SEP!$H$3:$H$900),"-") -> 7538920615 | H39: =SUMIF(SEP!B:B, B39, SEP!J:J) -> 3761396.1 | I39: =SUMIF(SEP!B:B, B39, SEP!K:K) -> 16128349 | J39: =G39-E39-H39 -> 12366953
A40: =IF(ISBLANK(B40),"",TEXT(B40,"dddd")) -> Thursday | B40: 46268 | C40: =SUMIF(SEP!$B$3:$B$101, B40, SEP!$D$3:$D$101) -> 605342.11 | D40: =IFERROR(__xludf.DUMMYFUNCTION("IFNA(INDEX(FILTER(SEP!$E$3:$E$100, SEP!$B$3:$B$100=B40), 1), ""-"")"),17628.226888880523) -> 17628.227 | E40: =SUMIF(SEP!$B$3:$B$101, B40, SEP!$F$3:$F$101) -> 10664145199 | F40: =IFERROR(__xludf.DUMMYFUNCTION("IFNA(INDEX(FILTER(SEP!$G$3:$G$100, SEP!$B$3:$B$100=B40), 1), ""-"")"),17665.0) -> 17665 | G40: =IFNA(SUMIF(SEP!$B$3:$B$900,B40,SEP!$H$3:$H$900),"-") -> 10685630581 | H40: =SUMIF(SEP!B:B, B40, SEP!J:J) -> 1495800.9 | I40: =SUMIF(SEP!B:B, B40, SEP!K:K) -> 21485382 | J40: =G40-E40-H40 -> 19989582
A41: =IF(ISBLANK(B41),"",TEXT(B41,"dddd")) -> Friday | B41: 46269 | C41: =SUMIF(SEP!$B$3:$B$101, B41, SEP!$D$3:$D$101) -> 716616.9 | D41: =IFERROR(__xludf.DUMMYFUNCTION("IFNA(INDEX(FILTER(SEP!$E$3:$E$100, SEP!$B$3:$B$100=B41), 1), ""-"")"),17570.0) -> 17570 | E41: =SUMIF(SEP!$B$3:$B$101, B41, SEP!$F$3:$F$101) -> 12584890170 | F41: =IFERROR(__xludf.DUMMYFUNCTION("IFNA(INDEX(FILTER(SEP!$G$3:$G$100, SEP!$B$3:$B$100=B41), 1), ""-"")"),17610.0) -> 17610 | G41: =IFNA(SUMIF(SEP!$B$3:$B$900,B41,SEP!$H$3:$H$900),"-") -> 12610984812 | H41: =SUMIF(SEP!B:B, B41, SEP!J:J) -> 498893.43 | I41: =SUMIF(SEP!B:B, B41, SEP!K:K) -> 26094642 | J41: =G41-E41-H41 -> 25595749
A42: =IF(ISBLANK(B42),"",TEXT(B42,"dddd")) -> Saturday | B42: 46270 | C42: =SUMIF(SEP!$B$3:$B$101, B42, SEP!$D$3:$D$101) -> 85348.5 | D42: =IFERROR(__xludf.DUMMYFUNCTION("IFNA(INDEX(FILTER(SEP!$E$3:$E$100, SEP!$B$3:$B$100=B42), 1), ""-"")"),17550.0) -> 17550 | E42: =SUMIF(SEP!$B$3:$B$101, B42, SEP!$F$3:$F$101) -> 1497866175 | F42: =IFERROR(__xludf.DUMMYFUNCTION("IFNA(INDEX(FILTER(SEP!$G$3:$G$100, SEP!$B$3:$B$100=B42), 1), ""-"")"),17575.0) -> 17575 | G42: =IFNA(SUMIF(SEP!$B$3:$B$900,B42,SEP!$H$3:$H$900),"-") -> 1499999888 | H42: =SUMIF(SEP!B:B, B42, SEP!J:J) -> 0 | I42: =SUMIF(SEP!B:B, B42, SEP!K:K) -> 2133712.5 | J42: =G42-E42-H42 -> 2133712.5
A43: =IF(ISBLANK(B43),"",TEXT(B43,"dddd")) -> Sunday | B43: 46271 | C43: =SUMIF(SEP!$B$3:$B$101, B43, SEP!$D$3:$D$101) -> 0 | D43: =IFERROR(__xludf.DUMMYFUNCTION("IFNA(INDEX(FILTER(SEP!$E$3:$E$100, SEP!$B$3:$B$100=B43), 1), ""-"")"),"-") -> - | E43: =SUMIF(SEP!$B$3:$B$101, B43, SEP!$F$3:$F$101) -> 0 | F43: =IFERROR(__xludf.DUMMYFUNCTION("IFNA(INDEX(FILTER(SEP!$G$3:$G$100, SEP!$B$3:$B$100=B43), 1), ""-"")"),"-") -> - | G43: =IFNA(SUMIF(SEP!$B$3:$B$900,B43,SEP!$H$3:$H$900),"-") -> 0 | H43: =SUMIF(SEP!B:B, B43, SEP!J:J) -> 0 | I43: =SUMIF(SEP!B:B, B43, SEP!K:K) -> 0 | J43: =G43-E43-H43 -> 0
A44: =IF(ISBLANK(B44),"",TEXT(B44,"dddd")) -> Monday | B44: 46272 | C44: =SUMIF(SEP!$B$3:$B$101, B44, SEP!$D$3:$D$101) -> 113749.49 | D44: =IFERROR(__xludf.DUMMYFUNCTION("IFNA(INDEX(FILTER(SEP!$E$3:$E$100, SEP!$B$3:$B$100=B44), 1), ""-"")"),17559.53413496284) -> 17559.534 | E44: =SUMIF(SEP!$B$3:$B$101, B44, SEP!$F$3:$F$101) -> 1997388052 | F44: =IFERROR(__xludf.DUMMYFUNCTION("IFNA(INDEX(FILTER(SEP!$G$3:$G$100, SEP!$B$3:$B$100=B44), 1), ""-"")"),17575.0) -> 17575 | G44: =IFNA(SUMIF(SEP!$B$3:$B$900,B44,SEP!$H$3:$H$900),"-") -> 2000000044 | H44: =SUMIF(SEP!B:B, B44, SEP!J:J) -> 998694.03 | I44: =SUMIF(SEP!B:B, B44, SEP!K:K) -> 2611991.5 | J44: =G44-E44-H44 -> 1613297.4
A45: =IF(ISBLANK(B45),"",TEXT(B45,"dddd")) -> Tuesday | B45: 46273 | C45: =SUMIF(SEP!$B$3:$B$101, B45, SEP!$D$3:$D$101) -> 396456.04 | D45: =IFERROR(__xludf.DUMMYFUNCTION("IFNA(INDEX(FILTER(SEP!$E$3:$E$100, SEP!$B$3:$B$100=B45), 1), ""-"")"),17556.0) -> 17556 | E45: =SUMIF(SEP!$B$3:$B$101, B45, SEP!$F$3:$F$101) -> 6959255251 | F45: =IFERROR(__xludf.DUMMYFUNCTION("IFNA(INDEX(FILTER(SEP!$G$3:$G$100, SEP!$B$3:$B$100=B45), 1), ""-"")"),17572.0) -> 17572 | G45: =IFNA(SUMIF(SEP!$B$3:$B$900,B45,SEP!$H$3:$H$900),"-") -> 6966525535 | H45: =SUMIF(SEP!B:B, B45, SEP!J:J) -> 499015.49 | I45: =SUMIF(SEP!B:B, B45, SEP!K:K) -> 7270284.1 | J45: =G45-E45-H45 -> 6771268.6
A46: =IF(ISBLANK(B46),"",TEXT(B46,"dddd")) -> Wednesday | B46: 46274 | C46: =SUMIF(SEP!$B$3:$B$101, B46, SEP!$D$3:$D$101) -> 57208.23 | D46: =IFERROR(__xludf.DUMMYFUNCTION("IFNA(INDEX(FILTER(SEP!$E$3:$E$100, SEP!$B$3:$B$100=B46), 1), ""-"")"),17452.500670195415) -> 17452.501 | E46: =SUMIF(SEP!$B$3:$B$101, B46, SEP!$F$3:$F$101) -> 9.9842667e+08 | F46: =IFERROR(__xludf.DUMMYFUNCTION("IFNA(INDEX(FILTER(SEP!$G$3:$G$100, SEP!$B$3:$B$100=B46), 1), ""-"")"),17480.0) -> 17480 | G46: =IFNA(SUMIF(SEP!$B$3:$B$900,B46,SEP!$H$3:$H$900),"-") -> 9.9999986e+08 | H46: =SUMIF(SEP!B:B, B46, SEP!J:J) -> 499213.34 | I46: =SUMIF(SEP!B:B, B46, SEP!K:K) -> 1573188 | J46: =G46-E46-H46 -> 1073974.6
A47: =IF(ISBLANK(B47),"",TEXT(B47,"dddd")) -> Thursday | B47: 46275 | C47: =SUMIF(SEP!$B$3:$B$101, B47, SEP!$D$3:$D$101) -> 144667.12 | D47: =IFERROR(__xludf.DUMMYFUNCTION("IFNA(INDEX(FILTER(SEP!$E$3:$E$100, SEP!$B$3:$B$100=B47), 1), ""-"")"),17480.0) -> 17480 | E47: =SUMIF(SEP!$B$3:$B$101, B47, SEP!$F$3:$F$101) -> 2529218879 | F47: =IFERROR(__xludf.DUMMYFUNCTION("IFNA(INDEX(FILTER(SEP!$G$3:$G$100, SEP!$B$3:$B$100=B47), 1), ""-"")"),17500.0) -> 17500 | G47: =IFNA(SUMIF(SEP!$B$3:$B$900,B47,SEP!$H$3:$H$900),"-") -> 2531674600 | H47: =SUMIF(SEP!B:B, B47, SEP!J:J) -> 0 | I47: =SUMIF(SEP!B:B, B47, SEP!K:K) -> 2455721 | J47: =G47-E47-H47 -> 2455721
A48: =IF(ISBLANK(B48),"",TEXT(B48,"dddd")) -> Friday | B48: 46276 | C48: =SUMIF(SEP!$B$3:$B$101, B48, SEP!$D$3:$D$101) -> 158035.51 | D48: =IFERROR(__xludf.DUMMYFUNCTION("IFNA(INDEX(FILTER(SEP!$E$3:$E$100, SEP!$B$3:$B$100=B48), 1), ""-"")"),17516.302133926034) -> 17516.302 | E48: =SUMIF(SEP!$B$3:$B$101, B48, SEP!$F$3:$F$101) -> 2767381430 | F48: =IFERROR(__xludf.DUMMYFUNCTION("IFNA(INDEX(FILTER(SEP!$G$3:$G$100, SEP!$B$3:$B$100=B48), 1), ""-"")"),17540.0) -> 17540 | G48: =IFNA(SUMIF(SEP!$B$3:$B$900,B48,SEP!$H$3:$H$900),"-") -> 2769999907 | H48: =SUMIF(SEP!B:B, B48, SEP!J:J) -> 249662.22 | I48: =SUMIF(SEP!B:B, B48, SEP!K:K) -> 2618476.4 | J48: =G48-E48-H48 -> 2368814.1
A49: =IF(ISBLANK(B49),"",TEXT(B49,"dddd")) -> Saturday | B49: 46277 | C49: =SUMIF(SEP!$B$3:$B$101, B49, SEP!$D$3:$D$101) -> 183157.29 | D49: =IFERROR(__xludf.DUMMYFUNCTION("IFNA(INDEX(FILTER(SEP!$E$3:$E$100, SEP!$B$3:$B$100=B49), 1), ""-"")"),17495.0) -> 17495 | E49: =SUMIF(SEP!$B$3:$B$101, B49, SEP!$F$3:$F$101) -> 3204336789 | F49: =IFERROR(__xludf.DUMMYFUNCTION("IFNA(INDEX(FILTER(SEP!$G$3:$G$100, SEP!$B$3:$B$100=B49), 1), ""-"")"),17515.0) -> 17515 | G49: =IFNA(SUMIF(SEP!$B$3:$B$900,B49,SEP!$H$3:$H$900),"-") -> 3207999934 | H49: =SUMIF(SEP!B:B, B49, SEP!J:J) -> 0 | I49: =SUMIF(SEP!B:B, B49, SEP!K:K) -> 3663145.8 | J49: =G49-E49-H49 -> 3663145.8
A50: =IF(ISBLANK(B50),"",TEXT(B50,"dddd")) -> Sunday | B50: 46278 | C50: =SUMIF(SEP!$B$3:$B$101, B50, SEP!$D$3:$D$101) -> 344075.18 | D50: =IFERROR(__xludf.DUMMYFUNCTION("IFNA(INDEX(FILTER(SEP!$E$3:$E$100, SEP!$B$3:$B$100=B50), 1), ""-"")"),17490.0) -> 17490 | E50: =SUMIF(SEP!$B$3:$B$101, B50, SEP!$F$3:$F$101) -> 6017874898 | F50: =IFERROR(__xludf.DUMMYFUNCTION("IFNA(INDEX(FILTER(SEP!$G$3:$G$100, SEP!$B$3:$B$100=B50), 1), ""-"")"),17515.0) -> 17515 | G50: =IFNA(SUMIF(SEP!$B$3:$B$900,B50,SEP!$H$3:$H$900),"-") -> 6025042585 | H50: =SUMIF(SEP!B:B, B50, SEP!J:J) -> 0 | I50: =SUMIF(SEP!B:B, B50, SEP!K:K) -> 7167687 | J50: =G50-E50-H50 -> 7167687
A51: =IF(ISBLANK(B51),"",TEXT(B51,"dddd")) -> Monday | B51: 46279 | C51: =SUMIF(SEP!$B$3:$B$101, B51, SEP!$D$3:$D$101) -> 758019.9 | D51: =IFERROR(__xludf.DUMMYFUNCTION("IFNA(INDEX(FILTER(SEP!$E$3:$E$100, SEP!$B$3:$B$100=B51), 1), ""-"")"),17555.0) -> 17555 | E51: =SUMIF(SEP!$B$3:$B$101, B51, SEP!$F$3:$F$101) -> 13308751774 | F51: =IFERROR(__xludf.DUMMYFUNCTION("IFNA(INDEX(FILTER(SEP!$G$3:$G$100, SEP!$B$3:$B$100=B51), 1), ""-"")"),17575.0) -> 17575 | G51: =IFNA(SUMIF(SEP!$B$3:$B$900,B51,SEP!$H$3:$H$900),"-") -> 13319187959 | H51: =SUMIF(SEP!B:B, B51, SEP!J:J) -> 0 | I51: =SUMIF(SEP!B:B, B51, SEP!K:K) -> 10436185 | J51: =G51-E51-H51 -> 10436185
A52: =IF(ISBLANK(B52),"",TEXT(B52,"dddd")) -> Tuesday | B52: 46280 | C52: =SUMIF(SEP!$B$3:$B$901, B52, SEP!$D$3:$D$901) -> 130496.45 | D52: =IFERROR(__xludf.DUMMYFUNCTION("IFNA(INDEX(FILTER(SEP!$E$3:$E$900, SEP!$B$3:$B$900=B52), 1), ""-"")"),17615.0) -> 17615 | E52: =SUMIF(SEP!$B$3:$B$901, B52, SEP!$F$3:$F$901) -> 2298694967 | F52: =IFERROR(__xludf.DUMMYFUNCTION("IFNA(INDEX(FILTER(SEP!$G$3:$G$900, SEP!$B$3:$B$900=B52), 1), ""-"")"),17625.0) -> 17625 | G52: =IFNA(SUMIF(SEP!$B$3:$B$900,B52,SEP!$H$3:$H$900),"-") -> 2299999931 | H52: =SUMIF(SEP!B:B, B52, SEP!J:J) -> 0 | I52: =SUMIF(SEP!B:B, B52, SEP!K:K) -> 1304964.5 | J52: =G52-E52-H52 -> 1304964.5
A53: =IF(ISBLANK(B53),"",TEXT(B53,"dddd")) -> Wednesday | B53: 46281 | C53: =SUMIF(SEP!$B$3:$B$901, B53, SEP!$D$3:$D$901) -> 452351.73 | D53: =IFERROR(__xludf.DUMMYFUNCTION("IFNA(INDEX(FILTER(SEP!$E$3:$E$900, SEP!$B$3:$B$900=B53), 1), ""-"")"),17582.045894924104) -> 17582.046 | E53: =SUMIF(SEP!$B$3:$B$901, B53, SEP!$F$3:$F$901) -> 7945525449 | F53: =IFERROR(__xludf.DUMMYFUNCTION("IFNA(INDEX(FILTER(SEP!$G$3:$G$900, SEP!$B$3:$B$900=B53), 1), ""-"")"),17610.0) -> 17610 | G53: =IFNA(SUMIF(SEP!$B$3:$B$900,B53,SEP!$H$3:$H$900),"-") -> 7959999328 | H53: =SUMIF(SEP!B:B, B53, SEP!J:J) -> 499236.47 | I53: =SUMIF(SEP!B:B, B53, SEP!K:K) -> 14473879 | J53: =G53-E53-H53 -> 13974642
A54: =IF(ISBLANK(B54),"",TEXT(B54,"dddd")) -> Thursday | B54: 46282 | C54: =SUMIF(SEP!$B$3:$B$901, B54, SEP!$D$3:$D$901) -> 241333.91 | D54: =IFERROR(__xludf.DUMMYFUNCTION("IFNA(INDEX(FILTER(SEP!$E$3:$E$900, SEP!$B$3:$B$900=B54), 1), ""-"")"),17640.0) -> 17640 | E54: =SUMIF(SEP!$B$3:$B$901, B54, SEP!$F$3:$F$901) -> 4253816901 | F54: =IFERROR(__xludf.DUMMYFUNCTION("IFNA(INDEX(FILTER(SEP!$G$3:$G$900, SEP!$B$3:$B$900=B54), 1), ""-"")"),17660.0) -> 17660 | G54: =IFNA(SUMIF(SEP!$B$3:$B$900,B54,SEP!$H$3:$H$900),"-") -> 4259973236 | H54: =SUMIF(SEP!B:B, B54, SEP!J:J) -> 1247692.8 | I54: =SUMIF(SEP!B:B, B54, SEP!K:K) -> 6156334.9 | J54: =G54-E54-H54 -> 4908642.1
A55: =IF(ISBLANK(B55),"",TEXT(B55,"dddd")) -> Friday | B55: 46283 | C55: =SUMIF(SEP!$B$3:$B$901, B55, SEP!$D$3:$D$901) -> 751246.13 | D55: =IFERROR(__xludf.DUMMYFUNCTION("IFNA(INDEX(FILTER(SEP!$E$3:$E$900, SEP!$B$3:$B$900=B55), 1), ""-"")"),17614.687437208722) -> 17614.687 | E55: =SUMIF(SEP!$B$3:$B$901, B55, SEP!$F$3:$F$901) -> 13234571621 | F55: =IFERROR(__xludf.DUMMYFUNCTION("IFNA(INDEX(FILTER(SEP!$G$3:$G$900, SEP!$B$3:$B$900=B55), 1), ""-"")"),17650.0) -> 17650 | G55: =IFNA(SUMIF(SEP!$B$3:$B$900,B55,SEP!$H$3:$H$900),"-") -> 13258363812 | H55: =SUMIF(SEP!B:B, B55, SEP!J:J) -> 4641469.5 | I55: =SUMIF(SEP!B:B, B55, SEP!K:K) -> 23792191 | J55: =G55-E55-H55 -> 19150722
A56: =IF(ISBLANK(B56),"",TEXT(B56,"dddd")) -> Saturday | B56: 46284 | C56: =SUMIF(SEP!$B$3:$B$901, B56, SEP!$D$3:$D$901) -> 515268.95 | D56: =IFERROR(__xludf.DUMMYFUNCTION("IFNA(INDEX(FILTER(SEP!$E$3:$E$900, SEP!$B$3:$B$900=B56), 1), ""-"")"),17560.0) -> 17560 | E56: =SUMIF(SEP!$B$3:$B$901, B56, SEP!$F$3:$F$901) -> 9043326788 | F56: =IFERROR(__xludf.DUMMYFUNCTION("IFNA(INDEX(FILTER(SEP!$G$3:$G$900, SEP!$B$3:$B$900=B56), 1), ""-"")"),17600.0) -> 17600 | G56: =IFNA(SUMIF(SEP!$B$3:$B$900,B56,SEP!$H$3:$H$900),"-") -> 9062048973 | H56: =SUMIF(SEP!B:B, B56, SEP!J:J) -> 2499922.6 | I56: =SUMIF(SEP!B:B, B56, SEP!K:K) -> 18722185 | J56: =G56-E56-H56 -> 16222263
A57: =IF(ISBLANK(B57),"",TEXT(B57,"dddd")) -> Sunday | B57: 46285 | C57: =SUMIF(SEP!$B$3:$B$901, B57, SEP!$D$3:$D$901) -> 396983.12 | D57: =IFERROR(__xludf.DUMMYFUNCTION("IFNA(INDEX(FILTER(SEP!$E$3:$E$900, SEP!$B$3:$B$900=B57), 1), ""-"")"),17537.167388945163) -> 17537.167 | E57: =SUMIF(SEP!$B$3:$B$901, B57, SEP!$F$3:$F$901) -> 6960980670 | F57: =IFERROR(__xludf.DUMMYFUNCTION("IFNA(INDEX(FILTER(SEP!$G$3:$G$900, SEP!$B$3:$B$900=B57), 1), ""-"")"),17580.0) -> 17580 | G57: =IFNA(SUMIF(SEP!$B$3:$B$900,B57,SEP!$H$3:$H$900),"-") -> 6975999571 | H57: =SUMIF(SEP!B:B, B57, SEP!J:J) -> 2332303.5 | I57: =SUMIF(SEP!B:B, B57, SEP!K:K) -> 15018902 | J57: =G57-E57-H57 -> 12686598
A58: =IF(ISBLANK(B58),"",TEXT(B58,"dddd")) -> Monday | B58: 46286 | C58: =SUMIF(SEP!$B$3:$B$901, B58, SEP!$D$3:$D$901) -> 471032.54 | D58: =IFERROR(__xludf.DUMMYFUNCTION("IFNA(INDEX(FILTER(SEP!$E$3:$E$900, SEP!$B$3:$B$900=B58), 1), ""-"")"),17660.430256656822) -> 17660.43 | E58: =SUMIF(SEP!$B$3:$B$901, B58, SEP!$F$3:$F$901) -> 8327191970 | F58: =IFERROR(__xludf.DUMMYFUNCTION("IFNA(INDEX(FILTER(SEP!$G$3:$G$900, SEP!$B$3:$B$900=B58), 1), ""-"")"),17685.0) -> 17685 | G58: =IFNA(SUMIF(SEP!$B$3:$B$900,B58,SEP!$H$3:$H$900),"-") -> 8344589933 | H58: =SUMIF(SEP!B:B, B58, SEP!J:J) -> 3913934.9 | I58: =SUMIF(SEP!B:B, B58, SEP!K:K) -> 17397962 | J58: =G58-E58-H58 -> 13484028
A59: =IF(ISBLANK(B59),"",TEXT(B59,"dddd")) -> Tuesday | B59: 46287 | C59: =SUMIF(SEP!$B$3:$B$901, B59, SEP!$D$3:$D$901) -> 706865.44 | D59: =IFERROR(__xludf.DUMMYFUNCTION("IFNA(INDEX(FILTER(SEP!$E$3:$E$900, SEP!$B$3:$B$900=B59), 1), ""-"")"),17750.0) -> 17750 | E59: =SUMIF(SEP!$B$3:$B$901, B59, SEP!$F$3:$F$901) -> 12547633576 | F59: =IFERROR(__xludf.DUMMYFUNCTION("IFNA(INDEX(FILTER(SEP!$G$3:$G$900, SEP!$B$3:$B$900=B59), 1), ""-"")"),17790.0) -> 17790 | G59: =IFNA(SUMIF(SEP!$B$3:$B$900,B59,SEP!$H$3:$H$900),"-") -> 12572998945 | H59: =SUMIF(SEP!B:B, B59, SEP!J:J) -> 4391028.4 | I59: =SUMIF(SEP!B:B, B59, SEP!K:K) -> 25365369 | J59: =G59-E59-H59 -> 20974341
A60: =IF(ISBLANK(B60),"",TEXT(B60,"dddd")) -> Wednesday | B60: 46288 | C60: =SUMIF(SEP!$B$3:$B$901, B60, SEP!$D$3:$D$901) -> 312423.22 | D60: =IFERROR(__xludf.DUMMYFUNCTION("IFNA(INDEX(FILTER(SEP!$E$3:$E$900, SEP!$B$3:$B$900=B60), 1), ""-"")"),17764.860600943943) -> 17764.861 | E60: =SUMIF(SEP!$B$3:$B$901, B60, SEP!$F$3:$F$901) -> 5547628549 | F60: =IFERROR(__xludf.DUMMYFUNCTION("IFNA(INDEX(FILTER(SEP!$G$3:$G$900, SEP!$B$3:$B$900=B60), 1), ""-"")"),17790.0) -> 17790 | G60: =IFNA(SUMIF(SEP!$B$3:$B$900,B60,SEP!$H$3:$H$900),"-") -> 5555602548 | H60: =SUMIF(SEP!B:B, B60, SEP!J:J) -> 776907.2 | I60: =SUMIF(SEP!B:B, B60, SEP!K:K) -> 7973998.7 | J60: =G60-E60-H60 -> 7197091.5
A61: =IF(ISBLANK(B61),"",TEXT(B61,"dddd")) -> Thursday | B61: 46289 | C61: =SUMIF(SEP!$B$3:$B$901, B61, SEP!$D$3:$D$901) -> 949677.41 | D61: =IFERROR(__xludf.DUMMYFUNCTION("IFNA(INDEX(FILTER(SEP!$E$3:$E$900, SEP!$B$3:$B$900=B61), 1), ""-"")"),17771.892147587514) -> 17771.892 | E61: =SUMIF(SEP!$B$3:$B$901, B61, SEP!$F$3:$F$901) -> 16898633690 | F61: =IFERROR(__xludf.DUMMYFUNCTION("IFNA(INDEX(FILTER(SEP!$G$3:$G$900, SEP!$B$3:$B$900=B61), 1), ""-"")"),17800.0) -> 17800 | G61: =IFNA(SUMIF(SEP!$B$3:$B$900,B61,SEP!$H$3:$H$900),"-") -> 16924999351 | H61: =SUMIF(SEP!B:B, B61, SEP!J:J) -> 5953670.9 | I61: =SUMIF(SEP!B:B, B61, SEP!K:K) -> 26365661 | J61: =G61-E61-H61 -> 20411990
A62: =IF(ISBLANK(B62),"",TEXT(B62,"dddd")) -> Friday | B62: 46290 | C62: =SUMIF(SEP!$B$3:$B$901, B62, SEP!$D$3:$D$901) -> 775711.04 | D62: =IFERROR(__xludf.DUMMYFUNCTION("IFNA(INDEX(FILTER(SEP!$E$3:$E$900, SEP!$B$3:$B$900=B62), 1), ""-"")"),17826.0) -> 17826 | E62: =SUMIF(SEP!$B$3:$B$901, B62, SEP!$F$3:$F$901) -> 13794873681 | F62: =IFERROR(__xludf.DUMMYFUNCTION("IFNA(INDEX(FILTER(SEP!$G$3:$G$900, SEP!$B$3:$B$900=B62), 1), ""-"")"),17870.0) -> 17870 | G62: =IFNA(SUMIF(SEP!$B$3:$B$900,B62,SEP!$H$3:$H$900),"-") -> 13820025788 | H62: =SUMIF(SEP!B:B, B62, SEP!J:J) -> 2273477 | I62: =SUMIF(SEP!B:B, B62, SEP!K:K) -> 25152107 | J62: =G62-E62-H62 -> 22878630
A63: =IF(ISBLANK(B63),"",TEXT(B63,"dddd")) -> Saturday | B63: 46291 | C63: =SUMIF(SEP!$B$3:$B$901, B63, SEP!$D$3:$D$901) -> 557390.92 | D63: =IFERROR(__xludf.DUMMYFUNCTION("IFNA(INDEX(FILTER(SEP!$E$3:$E$900, SEP!$B$3:$B$900=B63), 1), ""-"")"),17735.604469365175) -> 17735.604 | E63: =SUMIF(SEP!$B$3:$B$901, B63, SEP!$F$3:$F$901) -> 9889242747 | F63: =IFERROR(__xludf.DUMMYFUNCTION("IFNA(INDEX(FILTER(SEP!$G$3:$G$900, SEP!$B$3:$B$900=B63), 1), ""-"")"),17770.0) -> 17770 | G63: =IFNA(SUMIF(SEP!$B$3:$B$900,B63,SEP!$H$3:$H$900),"-") -> 9904999839 | H63: =SUMIF(SEP!B:B, B63, SEP!J:J) -> 499032.2 | I63: =SUMIF(SEP!B:B, B63, SEP!K:K) -> 15757091 | J63: =G63-E63-H63 -> 15258059
A64: =IF(ISBLANK(B64),"",TEXT(B64,"dddd")) -> Sunday | B64: 46292 | C64: =SUMIF(SEP!$B$3:$B$901, B64, SEP!$D$3:$D$901) -> 322486.34 | D64: =IFERROR(__xludf.DUMMYFUNCTION("IFNA(INDEX(FILTER(SEP!$E$3:$E$900, SEP!$B$3:$B$900=B64), 1), ""-"")"),17815.0) -> 17815 | E64: =SUMIF(SEP!$B$3:$B$901, B64, SEP!$F$3:$F$901) -> 5741292407 | F64: =IFERROR(__xludf.DUMMYFUNCTION("IFNA(INDEX(FILTER(SEP!$G$3:$G$900, SEP!$B$3:$B$900=B64), 1), ""-"")"),17835.0) -> 17835 | G64: =IFNA(SUMIF(SEP!$B$3:$B$900,B64,SEP!$H$3:$H$900),"-") -> 5749999798 | H64: =SUMIF(SEP!B:B, B64, SEP!J:J) -> 2321572.7 | I64: =SUMIF(SEP!B:B, B64, SEP!K:K) -> 8707390.8 | J64: =G64-E64-H64 -> 6385818.2
A65: =IF(ISBLANK(B65),"",TEXT(B65,"dddd")) -> Monday | B65: 46293 | C65: =SUMIF(SEP!$B$3:$B$901, B65, SEP!$D$3:$D$901) -> 399897.91 | D65: =IFERROR(__xludf.DUMMYFUNCTION("IFNA(INDEX(FILTER(SEP!$E$3:$E$900, SEP!$B$3:$B$900=B65), 1), ""-"")"),17840.0) -> 17840 | E65: =SUMIF(SEP!$B$3:$B$901, B65, SEP!$F$3:$F$901) -> 7146539468 | F65: =IFERROR(__xludf.DUMMYFUNCTION("IFNA(INDEX(FILTER(SEP!$G$3:$G$900, SEP!$B$3:$B$900=B65), 1), ""-"")"),17875.0) -> 17875 | G65: =IFNA(SUMIF(SEP!$B$3:$B$900,B65,SEP!$H$3:$H$900),"-") -> 7157999612 | H65: =SUMIF(SEP!B:B, B65, SEP!J:J) -> 2290563.9 | I65: =SUMIF(SEP!B:B, B65, SEP!K:K) -> 11460145 | J65: =G65-E65-H65 -> 9169580.7
A66: =IF(ISBLANK(B66),"",TEXT(B66,"dddd")) -> Tuesday | B66: 46294 | C66: =SUMIF(SEP!$B$3:$B$901, B66, SEP!$D$3:$D$901) -> 404389.36 | D66: =IFERROR(__xludf.DUMMYFUNCTION("IFNA(INDEX(FILTER(SEP!$E$3:$E$900, SEP!$B$3:$B$900=B66), 1), ""-"")"),17927.521775346693) -> 17927.522 | E66: =SUMIF(SEP!$B$3:$B$901, B66, SEP!$F$3:$F$901) -> 7243100881 | F66: =IFERROR(__xludf.DUMMYFUNCTION("IFNA(INDEX(FILTER(SEP!$G$3:$G$900, SEP!$B$3:$B$900=B66), 1), ""-"")"),17950.0) -> 17950 | G66: =IFNA(SUMIF(SEP!$B$3:$B$900,B66,SEP!$H$3:$H$900),"-") -> 7249999950 | H66: =SUMIF(SEP!B:B, B66, SEP!J:J) -> 998747.71 | I66: =SUMIF(SEP!B:B, B66, SEP!K:K) -> 6899068.8 | J66: =G66-E66-H66 -> 5900321
A67: =IF(ISBLANK(B67),"",TEXT(B67,"dddd")) -> Wednesday | B67: 46295 | C67: =SUMIF(SEP!$B$3:$B$901, B67, SEP!$D$3:$D$901) -> 0 | D67: =IFERROR(__xludf.DUMMYFUNCTION("IFNA(INDEX(FILTER(SEP!$E$3:$E$900, SEP!$B$3:$B$900=B67), 1), ""-"")"),"-") -> - | E67: =SUMIF(SEP!$B$3:$B$901, B67, SEP!$F$3:$F$901) -> 0 | F67: =IFERROR(__xludf.DUMMYFUNCTION("IFNA(INDEX(FILTER(SEP!$G$3:$G$900, SEP!$B$3:$B$900=B67), 1), ""-"")"),"") | G67: =IFNA(SUMIF(SEP!$B$3:$B$900,B67,SEP!$H$3:$H$900),"-") -> 0 | H67: =SUMIF(SEP!B:B, B67, SEP!J:J) -> 0 | I67: =SUMIF(SEP!B:B, B67, SEP!K:K) -> 0 | J67: =G67-E67-H67 -> 0
A68: =CONCAT(A37,"_TOTAL") -> SEP_TOTAL | C68: =sum(C38:C67) -> 11639891 | D68: =IFERROR(IF(AVERAGE(D38:D67)=0,"-",AVERAGE(D38:D67)),"-") -> 17635.512 | E68: =sum(E38:E67) -> 205573414297 | F68: =IFERROR(IF(AVERAGE(F38:F67)=0,"-",AVERAGE(F38:F67)),"-") -> 17663.643 | G68: =sum(G38:G67) -> 205910516613 | H68: =sum(H38:H67) -> 43454634 | I68: =sum(I38:I67) -> 337102316 | J68: =G68-E68-H68 -> 2.9364768e+08
A69: OCT
A70: =IF(ISBLANK(B70),"",TEXT(B70,"dddd")) -> Thursday | B70: 46296 | C70: =SUMIF(AUG!$B$3:$B$100, B70, AUG!$D$3:$D$100) -> 0 | D70: =IFERROR(__xludf.DUMMYFUNCTION("IFNA(INDEX(FILTER(AUG!$E$3:$E$100, AUG!$B$3:$B$100=B70), 1), ""-"")"),"-") -> - | E70: =SUMIF(AUG!$B$3:$B$100, B70, AUG!$F$3:$F$100) -> 0 | F70: =IFERROR(__xludf.DUMMYFUNCTION("IFNA(INDEX(FILTER(AUG!$G$3:$G$100, AUG!$B$3:$B$100=B70), 1), ""-"")"),"-") -> - | G70: =IFNA(SUMIF(AUG!$B$3:$B$100,B70,AUG!$H$3:$H$100),"-") -> 0 | H70: =E70*0.07% -> 0 | I70: =SUMIF(OCT!B:B, B70, OCT!K:K) -> 0 | J70: =G70-E70-H70 -> 0
A71: =IF(ISBLANK(B71),"",TEXT(B71,"dddd")) -> Friday | B71: 46297 | C71: =SUMIF(AUG!$B$3:$B$100, B71, AUG!$D$3:$D$100) -> 0 | D71: =IFERROR(__xludf.DUMMYFUNCTION("IFNA(INDEX(FILTER(AUG!$E$3:$E$100, AUG!$B$3:$B$100=B71), 1), ""-"")"),"-") -> - | E71: =SUMIF(AUG!$B$3:$B$100, B71, AUG!$F$3:$F$100) -> 0 | F71: =IFERROR(__xludf.DUMMYFUNCTION("IFNA(INDEX(FILTER(AUG!$G$3:$G$100, AUG!$B$3:$B$100=B71), 1), ""-"")"),"-") -> - | G71: =IFNA(SUMIF(AUG!$B$3:$B$100,B71,AUG!$H$3:$H$100),"-") -> 0 | H71: =E71*0.07% -> 0 | I71: =SUMIF(OCT!B:B, B71, OCT!K:K) -> 9283849.8 | J71: =G71-E71-H71 -> 0
A72: =IF(ISBLANK(B72),"",TEXT(B72,"dddd")) -> Saturday | B72: 46298 | C72: =SUMIF(AUG!$B$3:$B$100, B72, AUG!$D$3:$D$100) -> 0 | D72: =IFERROR(__xludf.DUMMYFUNCTION("IFNA(INDEX(FILTER(AUG!$E$3:$E$100, AUG!$B$3:$B$100=B72), 1), ""-"")"),"-") -> - | E72: =SUMIF(AUG!$B$3:$B$100, B72, AUG!$F$3:$F$100) -> 0 | F72: =IFERROR(__xludf.DUMMYFUNCTION("IFNA(INDEX(FILTER(AUG!$G$3:$G$100, AUG!$B$3:$B$100=B72), 1), ""-"")"),"-") -> - | G72: =IFNA(SUMIF(AUG!$B$3:$B$100,B72,AUG!$H$3:$H$100),"-") -> 0 | H72: =E72*0.07% -> 0 | I72: =SUMIF(OCT!B:B, B72, OCT!K:K) -> 135971.2 | J72: =G72-E72-H72 -> 0
A73: =IF(ISBLANK(B73),"",TEXT(B73,"dddd")) -> Sunday | B73: 46299 | C73: =SUMIF(AUG!$B$3:$B$100, B73, AUG!$D$3:$D$100) -> 0 | D73: =IFERROR(__xludf.DUMMYFUNCTION("IFNA(INDEX(FILTER(AUG!$E$3:$E$100, AUG!$B$3:$B$100=B73), 1), ""-"")"),"-") -> - | E73: =SUMIF(AUG!$B$3:$B$100, B73, AUG!$F$3:$F$100) -> 0 | F73: =IFERROR(__xludf.DUMMYFUNCTION("IFNA(INDEX(FILTER(AUG!$G$3:$G$100, AUG!$B$3:$B$100=B73), 1), ""-"")"),"-") -> - | G73: =IFNA(SUMIF(AUG!$B$3:$B$100,B73,AUG!$H$3:$H$100),"-") -> 0 | H73: =E73*0.07% -> 0 | I73: =SUMIF(OCT!B:B, B73, OCT!K:K) -> -1275961.5 | J73: =G73-E73-H73 -> 0
A74: =IF(ISBLANK(B74),"",TEXT(B74,"dddd")) -> Monday | B74: 46300 | C74: =SUMIF(AUG!$B$3:$B$100, B74, AUG!$D$3:$D$100) -> 0 | D74: =IFERROR(__xludf.DUMMYFUNCTION("IFNA(INDEX(FILTER(AUG!$E$3:$E$100, AUG!$B$3:$B$100=B74), 1), ""-"")"),"-") -> - | E74: =SUMIF(AUG!$B$3:$B$100, B74, AUG!$F$3:$F$100) -> 0 | F74: =IFERROR(__xludf.DUMMYFUNCTION("IFNA(INDEX(FILTER(AUG!$G$3:$G$100, AUG!$B$3:$B$100=B74), 1), ""-"")"),"-") -> - | G74: =IFNA(SUMIF(AUG!$B$3:$B$100,B74,AUG!$H$3:$H$100),"-") -> 0 | H74: =E74*0.07% -> 0 | I74: =SUMIF(OCT!B:B, B74, OCT!K:K) -> 13145039 | J74: =G74-E74-H74 -> 0
A75: =IF(ISBLANK(B75),"",TEXT(B75,"dddd")) -> Tuesday | B75: 46301 | C75: =SUMIF(AUG!$B$3:$B$100, B75, AUG!$D$3:$D$100) -> 0 | D75: =IFERROR(__xludf.DUMMYFUNCTION("IFNA(INDEX(FILTER(AUG!$E$3:$E$100, AUG!$B$3:$B$100=B75), 1), ""-"")"),"-") -> - | E75: =SUMIF(AUG!$B$3:$B$100, B75, AUG!$F$3:$F$100) -> 0 | F75: =IFERROR(__xludf.DUMMYFUNCTION("IFNA(INDEX(FILTER(AUG!$G$3:$G$100, AUG!$B$3:$B$100=B75), 1), ""-"")"),"-") -> - | G75: =IFNA(SUMIF(AUG!$B$3:$B$100,B75,AUG!$H$3:$H$100),"-") -> 0 | H75: =E75*0.07% -> 0 | I75: =SUMIF(OCT!B:B, B75, OCT!K:K) -> 0 | J75: =G75-E75-H75 -> 0
A76: =IF(ISBLANK(B76),"",TEXT(B76,"dddd")) -> Wednesday | B76: 46302 | C76: =SUMIF(AUG!$B$3:$B$100, B76, AUG!$D$3:$D$100) -> 0 | D76: =IFERROR(__xludf.DUMMYFUNCTION("IFNA(INDEX(FILTER(AUG!$E$3:$E$100, AUG!$B$3:$B$100=B76), 1), ""-"")"),"-") -> - | E76: =SUMIF(AUG!$B$3:$B$100, B76, AUG!$F$3:$F$100) -> 0 | F76: =IFERROR(__xludf.DUMMYFUNCTION("IFNA(INDEX(FILTER(AUG!$G$3:$G$100, AUG!$B$3:$B$100=B76), 1), ""-"")"),"-") -> - | G76: =IFNA(SUMIF(AUG!$B$3:$B$100,B76,AUG!$H$3:$H$100),"-") -> 0 | H76: =E76*0.07% -> 0 | I76: =SUMIF(OCT!B:B, B76, OCT!K:K) -> 0 | J76: =G76-E76-H76 -> 0
A77: =IF(ISBLANK(B77),"",TEXT(B77,"dddd")) -> Thursday | B77: 46303 | C77: =SUMIF(AUG!$B$3:$B$100, B77, AUG!$D$3:$D$100) -> 0 | D77: =IFERROR(__xludf.DUMMYFUNCTION("IFNA(INDEX(FILTER(AUG!$E$3:$E$100, AUG!$B$3:$B$100=B77), 1), ""-"")"),"-") -> - | E77: =SUMIF(AUG!$B$3:$B$100, B77, AUG!$F$3:$F$100) -> 0 | F77: =IFERROR(__xludf.DUMMYFUNCTION("IFNA(INDEX(FILTER(AUG!$G$3:$G$100, AUG!$B$3:$B$100=B77), 1), ""-"")"),"-") -> - | G77: =IFNA(SUMIF(AUG!$B$3:$B$100,B77,AUG!$H$3:$H$100),"-") -> 0 | H77: =E77*0.07% -> 0 | I77: =SUMIF(OCT!B:B, B77, OCT!K:K) -> 0 | J77: =G77-E77-H77 -> 0
A78: =IF(ISBLANK(B78),"",TEXT(B78,"dddd")) -> Friday | B78: 46304 | C78: =SUMIF(AUG!$B$3:$B$100, B78, AUG!$D$3:$D$100) -> 0 | D78: =IFERROR(__xludf.DUMMYFUNCTION("IFNA(INDEX(FILTER(AUG!$E$3:$E$100, AUG!$B$3:$B$100=B78), 1), ""-"")"),"-") -> - | E78: =SUMIF(AUG!$B$3:$B$100, B78, AUG!$F$3:$F$100) -> 0 | F78: =IFERROR(__xludf.DUMMYFUNCTION("IFNA(INDEX(FILTER(AUG!$G$3:$G$100, AUG!$B$3:$B$100=B78), 1), ""-"")"),"-") -> - | G78: =IFNA(SUMIF(AUG!$B$3:$B$100,B78,AUG!$H$3:$H$100),"-") -> 0 | H78: =E78*0.07% -> 0 | I78: =SUMIF(OCT!B:B, B78, OCT!K:K) -> 0 | J78: =G78-E78-H78 -> 0
A79: =IF(ISBLANK(B79),"",TEXT(B79,"dddd")) -> Saturday | B79: 46305 | C79: =SUMIF(AUG!$B$3:$B$100, B79, AUG!$D$3:$D$100) -> 0 | D79: =IFERROR(__xludf.DUMMYFUNCTION("IFNA(INDEX(FILTER(AUG!$E$3:$E$100, AUG!$B$3:$B$100=B79), 1), ""-"")"),"-") -> - | E79: =SUMIF(AUG!$B$3:$B$100, B79, AUG!$F$3:$F$100) -> 0 | F79: =IFERROR(__xludf.DUMMYFUNCTION("IFNA(INDEX(FILTER(AUG!$G$3:$G$100, AUG!$B$3:$B$100=B79), 1), ""-"")"),"-") -> - | G79: =IFNA(SUMIF(AUG!$B$3:$B$100,B79,AUG!$H$3:$H$100),"-") -> 0 | H79: =E79*0.07% -> 0 | I79: =SUMIF(OCT!B:B, B79, OCT!K:K) -> 0 | J79: =G79-E79-H79 -> 0
A80: =IF(ISBLANK(B80),"",TEXT(B80,"dddd")) -> Sunday | B80: 46306 | C80: =SUMIF(AUG!$B$3:$B$100, B80, AUG!$D$3:$D$100) -> 0 | D80: =IFERROR(__xludf.DUMMYFUNCTION("IFNA(INDEX(FILTER(AUG!$E$3:$E$100, AUG!$B$3:$B$100=B80), 1), ""-"")"),"-") -> - | E80: =SUMIF(AUG!$B$3:$B$100, B80, AUG!$F$3:$F$100) -> 0 | F80: =IFERROR(__xludf.DUMMYFUNCTION("IFNA(INDEX(FILTER(AUG!$G$3:$G$100, AUG!$B$3:$B$100=B80), 1), ""-"")"),"-") -> - | G80: =IFNA(SUMIF(AUG!$B$3:$B$100,B80,AUG!$H$3:$H$100),"-") -> 0 | H80: =E80*0.07% -> 0 | I80: =SUMIF(OCT!B:B, B80, OCT!K:K) -> 0 | J80: =G80-E80-H80 -> 0
A81: =IF(ISBLANK(B81),"",TEXT(B81,"dddd")) -> Monday | B81: 46307 | C81: =SUMIF(AUG!$B$3:$B$100, B81, AUG!$D$3:$D$100) -> 0 | D81: =IFERROR(__xludf.DUMMYFUNCTION("IFNA(INDEX(FILTER(AUG!$E$3:$E$100, AUG!$B$3:$B$100=B81), 1), ""-"")"),"-") -> - | E81: =SUMIF(AUG!$B$3:$B$100, B81, AUG!$F$3:$F$100) -> 0 | F81: =IFERROR(__xludf.DUMMYFUNCTION("IFNA(INDEX(FILTER(AUG!$G$3:$G$100, AUG!$B$3:$B$100=B81), 1), ""-"")"),"-") -> - | G81: =IFNA(SUMIF(AUG!$B$3:$B$100,B81,AUG!$H$3:$H$100),"-") -> 0 | H81: =E81*0.07% -> 0 | I81: =SUMIF(OCT!B:B, B81, OCT!K:K) -> 0 | J81: =G81-E81-H81 -> 0
A82: =IF(ISBLANK(B82),"",TEXT(B82,"dddd")) -> Tuesday | B82: 46308 | C82: =SUMIF(AUG!$B$3:$B$100, B82, AUG!$D$3:$D$100) -> 0 | D82: =IFERROR(__xludf.DUMMYFUNCTION("IFNA(INDEX(FILTER(AUG!$E$3:$E$100, AUG!$B$3:$B$100=B82), 1), ""-"")"),"-") -> - | E82: =SUMIF(AUG!$B$3:$B$100, B82, AUG!$F$3:$F$100) -> 0 | F82: =IFERROR(__xludf.DUMMYFUNCTION("IFNA(INDEX(FILTER(AUG!$G$3:$G$100, AUG!$B$3:$B$100=B82), 1), ""-"")"),"-") -> - | G82: =IFNA(SUMIF(AUG!$B$3:$B$100,B82,AUG!$H$3:$H$100),"-") -> 0 | H82: =E82*0.07% -> 0 | I82: =SUMIF(OCT!B:B, B82, OCT!K:K) -> 0 | J82: =G82-E82-H82 -> 0
A83: =IF(ISBLANK(B83),"",TEXT(B83,"dddd")) -> Wednesday | B83: 46309 | C83: =SUMIF(AUG!$B$3:$B$100, B83, AUG!$D$3:$D$100) -> 0 | D83: =IFERROR(__xludf.DUMMYFUNCTION("IFNA(INDEX(FILTER(AUG!$E$3:$E$100, AUG!$B$3:$B$100=B83), 1), ""-"")"),"-") -> - | E83: =SUMIF(AUG!$B$3:$B$100, B83, AUG!$F$3:$F$100) -> 0 | F83: =IFERROR(__xludf.DUMMYFUNCTION("IFNA(INDEX(FILTER(AUG!$G$3:$G$100, AUG!$B$3:$B$100=B83), 1), ""-"")"),"-") -> - | G83: =IFNA(SUMIF(AUG!$B$3:$B$100,B83,AUG!$H$3:$H$100),"-") -> 0 | H83: =E83*0.07% -> 0 | I83: =SUMIF(OCT!B:B, B83, OCT!K:K) -> 0 | J83: =G83-E83-H83 -> 0
A84: =IF(ISBLANK(B84),"",TEXT(B84,"dddd")) -> Thursday | B84: 46310 | C84: =SUMIF(AUG!$B$3:$B$100, B84, AUG!$D$3:$D$100) -> 0 | D84: =IFERROR(__xludf.DUMMYFUNCTION("IFNA(INDEX(FILTER(AUG!$E$3:$E$100, AUG!$B$3:$B$100=B84), 1), ""-"")"),"-") -> - | E84: =SUMIF(AUG!$B$3:$B$100, B84, AUG!$F$3:$F$100) -> 0 | F84: =IFERROR(__xludf.DUMMYFUNCTION("IFNA(INDEX(FILTER(AUG!$G$3:$G$100, AUG!$B$3:$B$100=B84), 1), ""-"")"),"-") -> - | G84: =IFNA(SUMIF(AUG!$B$3:$B$100,B84,AUG!$H$3:$H$100),"-") -> 0 | H84: =E84*0.07% -> 0 | I84: =SUMIF(OCT!B:B, B84, OCT!K:K) -> 0 | J84: =G84-E84-H84 -> 0
A85: =IF(ISBLANK(B85),"",TEXT(B85,"dddd")) -> Friday | B85: 46311 | C85: =SUMIF(AUG!$B$3:$B$100, B85, AUG!$D$3:$D$100) -> 0 | D85: =IFERROR(__xludf.DUMMYFUNCTION("IFNA(INDEX(FILTER(AUG!$E$3:$E$100, AUG!$B$3:$B$100=B85), 1), ""-"")"),"-") -> - | E85: =SUMIF(AUG!$B$3:$B$100, B85, AUG!$F$3:$F$100) -> 0 | F85: =IFERROR(__xludf.DUMMYFUNCTION("IFNA(INDEX(FILTER(AUG!$G$3:$G$100, AUG!$B$3:$B$100=B85), 1), ""-"")"),"-") -> - | G85: =IFNA(SUMIF(AUG!$B$3:$B$100,B85,AUG!$H$3:$H$100),"-") -> 0 | H85: =E85*0.07% -> 0 | I85: =SUMIF(OCT!B:B, B85, OCT!K:K) -> 0 | J85: =G85-E85-H85 -> 0
A86: =IF(ISBLANK(B86),"",TEXT(B86,"dddd")) -> Saturday | B86: 46312 | C86: =SUMIF(AUG!$B$3:$B$100, B86, AUG!$D$3:$D$100) -> 0 | D86: =IFERROR(__xludf.DUMMYFUNCTION("IFNA(INDEX(FILTER(AUG!$E$3:$E$100, AUG!$B$3:$B$100=B86), 1), ""-"")"),"-") -> - | E86: =SUMIF(AUG!$B$3:$B$100, B86, AUG!$F$3:$F$100) -> 0 | F86: =IFERROR(__xludf.DUMMYFUNCTION("IFNA(INDEX(FILTER(AUG!$G$3:$G$100, AUG!$B$3:$B$100=B86), 1), ""-"")"),"-") -> - | G86: =IFNA(SUMIF(AUG!$B$3:$B$100,B86,AUG!$H$3:$H$100),"-") -> 0 | H86: =E86*0.07% -> 0 | I86: =SUMIF(OCT!B:B, B86, OCT!K:K) -> 0 | J86: =G86-E86-H86 -> 0
A87: =IF(ISBLANK(B87),"",TEXT(B87,"dddd")) -> Sunday | B87: 46313 | C87: =SUMIF(AUG!$B$3:$B$100, B87, AUG!$D$3:$D$100) -> 0 | D87: =IFERROR(__xludf.DUMMYFUNCTION("IFNA(INDEX(FILTER(AUG!$E$3:$E$100, AUG!$B$3:$B$100=B87), 1), ""-"")"),"-") -> - | E87: =SUMIF(AUG!$B$3:$B$100, B87, AUG!$F$3:$F$100) -> 0 | F87: =IFERROR(__xludf.DUMMYFUNCTION("IFNA(INDEX(FILTER(AUG!$G$3:$G$100, AUG!$B$3:$B$100=B87), 1), ""-"")"),"-") -> - | G87: =IFNA(SUMIF(AUG!$B$3:$B$100,B87,AUG!$H$3:$H$100),"-") -> 0 | H87: =E87*0.07% -> 0 | I87: =SUMIF(OCT!B:B, B87, OCT!K:K) -> 0 | J87: =G87-E87-H87 -> 0
A88: =IF(ISBLANK(B88),"",TEXT(B88,"dddd")) -> Monday | B88: 46314 | C88: =SUMIF(AUG!$B$3:$B$100, B88, AUG!$D$3:$D$100) -> 0 | D88: =IFERROR(__xludf.DUMMYFUNCTION("IFNA(INDEX(FILTER(AUG!$E$3:$E$100, AUG!$B$3:$B$100=B88), 1), ""-"")"),"-") -> - | E88: =SUMIF(AUG!$B$3:$B$100, B88, AUG!$F$3:$F$100) -> 0 | F88: =IFERROR(__xludf.DUMMYFUNCTION("IFNA(INDEX(FILTER(AUG!$G$3:$G$100, AUG!$B$3:$B$100=B88), 1), ""-"")"),"-") -> - | G88: =IFNA(SUMIF(AUG!$B$3:$B$100,B88,AUG!$H$3:$H$100),"-") -> 0 | H88: =E88*0.07% -> 0 | I88: =SUMIF(OCT!B:B, B88, OCT!K:K) -> 0 | J88: =G88-E88-H88 -> 0
A89: =IF(ISBLANK(B89),"",TEXT(B89,"dddd")) -> Tuesday | B89: 46315 | C89: =SUMIF(AUG!$B$3:$B$100, B89, AUG!$D$3:$D$100) -> 0 | D89: =IFERROR(__xludf.DUMMYFUNCTION("IFNA(INDEX(FILTER(AUG!$E$3:$E$100, AUG!$B$3:$B$100=B89), 1), ""-"")"),"-") -> - | E89: =SUMIF(AUG!$B$3:$B$100, B89, AUG!$F$3:$F$100) -> 0 | F89: =IFERROR(__xludf.DUMMYFUNCTION("IFNA(INDEX(FILTER(AUG!$G$3:$G$100, AUG!$B$3:$B$100=B89), 1), ""-"")"),"-") -> - | G89: =IFNA(SUMIF(AUG!$B$3:$B$100,B89,AUG!$H$3:$H$100),"-") -> 0 | H89: =E89*0.07% -> 0 | I89: =SUMIF(OCT!B:B, B89, OCT!K:K) -> 0 | J89: =G89-E89-H89 -> 0
A90: =IF(ISBLANK(B90),"",TEXT(B90,"dddd")) -> Wednesday | B90: 46316 | C90: =SUMIF(AUG!$B$3:$B$100, B90, AUG!$D$3:$D$100) -> 0 | D90: =IFERROR(__xludf.DUMMYFUNCTION("IFNA(INDEX(FILTER(AUG!$E$3:$E$100, AUG!$B$3:$B$100=B90), 1), ""-"")"),"-") -> - | E90: =SUMIF(AUG!$B$3:$B$100, B90, AUG!$F$3:$F$100) -> 0 | F90: =IFERROR(__xludf.DUMMYFUNCTION("IFNA(INDEX(FILTER(AUG!$G$3:$G$100, AUG!$B$3:$B$100=B90), 1), ""-"")"),"-") -> - | G90: =IFNA(SUMIF(AUG!$B$3:$B$100,B90,AUG!$H$3:$H$100),"-") -> 0 | H90: =E90*0.07% -> 0 | I90: =SUMIF(OCT!B:B, B90, OCT!K:K) -> 0 | J90: =G90-E90-H90 -> 0
A91: =IF(ISBLANK(B91),"",TEXT(B91,"dddd")) -> Thursday | B91: 46317 | C91: =SUMIF(AUG!$B$3:$B$100, B91, AUG!$D$3:$D$100) -> 0 | D91: =IFERROR(__xludf.DUMMYFUNCTION("IFNA(INDEX(FILTER(AUG!$E$3:$E$100, AUG!$B$3:$B$100=B91), 1), ""-"")"),"-") -> - | E91: =SUMIF(AUG!$B$3:$B$100, B91, AUG!$F$3:$F$100) -> 0 | F91: =IFERROR(__xludf.DUMMYFUNCTION("IFNA(INDEX(FILTER(AUG!$G$3:$G$100, AUG!$B$3:$B$100=B91), 1), ""-"")"),"-") -> - | G91: =IFNA(SUMIF(AUG!$B$3:$B$100,B91,AUG!$H$3:$H$100),"-") -> 0 | H91: =E91*0.07% -> 0 | I91: =SUMIF(OCT!B:B, B91, OCT!K:K) -> 0 | J91: =G91-E91-H91 -> 0
A92: =IF(ISBLANK(B92),"",TEXT(B92,"dddd")) -> Friday | B92: 46318 | C92: =SUMIF(AUG!$B$3:$B$100, B92, AUG!$D$3:$D$100) -> 0 | D92: =IFERROR(__xludf.DUMMYFUNCTION("IFNA(INDEX(FILTER(AUG!$E$3:$E$100, AUG!$B$3:$B$100=B92), 1), ""-"")"),"-") -> - | E92: =SUMIF(AUG!$B$3:$B$100, B92, AUG!$F$3:$F$100) -> 0 | F92: =IFERROR(__xludf.DUMMYFUNCTION("IFNA(INDEX(FILTER(AUG!$G$3:$G$100, AUG!$B$3:$B$100=B92), 1), ""-"")"),"-") -> - | G92: =IFNA(SUMIF(AUG!$B$3:$B$100,B92,AUG!$H$3:$H$100),"-") -> 0 | H92: =E92*0.07% -> 0 | I92: =SUMIF(OCT!B:B, B92, OCT!K:K) -> 0 | J92: =G92-E92-H92 -> 0
A93: =IF(ISBLANK(B93),"",TEXT(B93,"dddd")) -> Saturday | B93: 46319 | C93: =SUMIF(AUG!$B$3:$B$100, B93, AUG!$D$3:$D$100) -> 0 | D93: =IFERROR(__xludf.DUMMYFUNCTION("IFNA(INDEX(FILTER(AUG!$E$3:$E$100, AUG!$B$3:$B$100=B93), 1), ""-"")"),"-") -> - | E93: =SUMIF(AUG!$B$3:$B$100, B93, AUG!$F$3:$F$100) -> 0 | F93: =IFERROR(__xludf.DUMMYFUNCTION("IFNA(INDEX(FILTER(AUG!$G$3:$G$100, AUG!$B$3:$B$100=B93), 1), ""-"")"),"-") -> - | G93: =IFNA(SUMIF(AUG!$B$3:$B$100,B93,AUG!$H$3:$H$100),"-") -> 0 | H93: =E93*0.07% -> 0 | I93: =SUMIF(OCT!B:B, B93, OCT!K:K) -> 0 | J93: =G93-E93-H93 -> 0
A94: =IF(ISBLANK(B94),"",TEXT(B94,"dddd")) -> Sunday | B94: 46320 | C94: =SUMIF(AUG!$B$3:$B$100, B94, AUG!$D$3:$D$100) -> 0 | D94: =IFERROR(__xludf.DUMMYFUNCTION("IFNA(INDEX(FILTER(AUG!$E$3:$E$100, AUG!$B$3:$B$100=B94), 1), ""-"")"),"-") -> - | E94: =SUMIF(AUG!$B$3:$B$100, B94, AUG!$F$3:$F$100) -> 0 | F94: =IFERROR(__xludf.DUMMYFUNCTION("IFNA(INDEX(FILTER(AUG!$G$3:$G$100, AUG!$B$3:$B$100=B94), 1), ""-"")"),"-") -> - | G94: =IFNA(SUMIF(AUG!$B$3:$B$100,B94,AUG!$H$3:$H$100),"-") -> 0 | H94: =E94*0.07% -> 0 | I94: =SUMIF(OCT!B:B, B94, OCT!K:K) -> 0 | J94: =G94-E94-H94 -> 0
A95: =IF(ISBLANK(B95),"",TEXT(B95,"dddd")) -> Monday | B95: 46321 | C95: =SUMIF(AUG!$B$3:$B$100, B95, AUG!$D$3:$D$100) -> 0 | D95: =IFERROR(__xludf.DUMMYFUNCTION("IFNA(INDEX(FILTER(AUG!$E$3:$E$100, AUG!$B$3:$B$100=B95), 1), ""-"")"),"-") -> - | E95: =SUMIF(AUG!$B$3:$B$100, B95, AUG!$F$3:$F$100) -> 0 | F95: =IFERROR(__xludf.DUMMYFUNCTION("IFNA(INDEX(FILTER(AUG!$G$3:$G$100, AUG!$B$3:$B$100=B95), 1), ""-"")"),"-") -> - | G95: =IFNA(SUMIF(AUG!$B$3:$B$100,B95,AUG!$H$3:$H$100),"-") -> 0 | H95: =E95*0.07% -> 0 | I95: =SUMIF(OCT!B:B, B95, OCT!K:K) -> 0 | J95: =G95-E95-H95 -> 0
A96: =IF(ISBLANK(B96),"",TEXT(B96,"dddd")) -> Tuesday | B96: 46322 | C96: =SUMIF(AUG!$B$3:$B$100, B96, AUG!$D$3:$D$100) -> 0 | D96: =IFERROR(__xludf.DUMMYFUNCTION("IFNA(INDEX(FILTER(AUG!$E$3:$E$100, AUG!$B$3:$B$100=B96), 1), ""-"")"),"-") -> - | E96: =SUMIF(AUG!$B$3:$B$100, B96, AUG!$F$3:$F$100) -> 0 | F96: =IFERROR(__xludf.DUMMYFUNCTION("IFNA(INDEX(FILTER(AUG!$G$3:$G$100, AUG!$B$3:$B$100=B96), 1), ""-"")"),"-") -> - | G96: =IFNA(SUMIF(AUG!$B$3:$B$100,B96,AUG!$H$3:$H$100),"-") -> 0 | H96: =E96*0.07% -> 0 | I96: =SUMIF(OCT!B:B, B96, OCT!K:K) -> 0 | J96: =G96-E96-H96 -> 0
A97: =IF(ISBLANK(B97),"",TEXT(B97,"dddd")) -> Wednesday | B97: 46323 | C97: =SUMIF(AUG!$B$3:$B$100, B97, AUG!$D$3:$D$100) -> 0 | D97: =IFERROR(__xludf.DUMMYFUNCTION("IFNA(INDEX(FILTER(AUG!$E$3:$E$100, AUG!$B$3:$B$100=B97), 1), ""-"")"),"-") -> - | E97: =SUMIF(AUG!$B$3:$B$100, B97, AUG!$F$3:$F$100) -> 0 | F97: =IFERROR(__xludf.DUMMYFUNCTION("IFNA(INDEX(FILTER(AUG!$G$3:$G$100, AUG!$B$3:$B$100=B97), 1), ""-"")"),"-") -> - | G97: =IFNA(SUMIF(AUG!$B$3:$B$100,B97,AUG!$H$3:$H$100),"-") -> 0 | H97: =E97*0.07% -> 0 | I97: =SUMIF(OCT!B:B, B97, OCT!K:K) -> 0 | J97: =G97-E97-H97 -> 0
A98: =IF(ISBLANK(B98),"",TEXT(B98,"dddd")) -> Thursday | B98: 46324 | C98: =SUMIF(AUG!$B$3:$B$100, B98, AUG!$D$3:$D$100) -> 0 | D98: =IFERROR(__xludf.DUMMYFUNCTION("IFNA(INDEX(FILTER(AUG!$E$3:$E$100, AUG!$B$3:$B$100=B98), 1), ""-"")"),"-") -> - | E98: =SUMIF(AUG!$B$3:$B$100, B98, AUG!$F$3:$F$100) -> 0 | F98: =IFERROR(__xludf.DUMMYFUNCTION("IFNA(INDEX(FILTER(AUG!$G$3:$G$100, AUG!$B$3:$B$100=B98), 1), ""-"")"),"-") -> - | G98: =IFNA(SUMIF(AUG!$B$3:$B$100,B98,AUG!$H$3:$H$100),"-") -> 0 | H98: =E98*0.07% -> 0 | I98: =SUMIF(OCT!B:B, B98, OCT!K:K) -> 0 | J98: =G98-E98-H98 -> 0
A99: =IF(ISBLANK(B99),"",TEXT(B99,"dddd")) -> Friday | B99: 46325 | C99: =SUMIF(AUG!$B$3:$B$100, B99, AUG!$D$3:$D$100) -> 0 | D99: =IFERROR(__xludf.DUMMYFUNCTION("IFNA(INDEX(FILTER(AUG!$E$3:$E$100, AUG!$B$3:$B$100=B99), 1), ""-"")"),"-") -> - | E99: =SUMIF(AUG!$B$3:$B$100, B99, AUG!$F$3:$F$100) -> 0 | F99: =IFERROR(__xludf.DUMMYFUNCTION("IFNA(INDEX(FILTER(AUG!$G$3:$G$100, AUG!$B$3:$B$100=B99), 1), ""-"")"),"-") -> - | G99: =IFNA(SUMIF(AUG!$B$3:$B$100,B99,AUG!$H$3:$H$100),"-") -> 0 | H99: =E99*0.07% -> 0 | I99: =SUMIF(OCT!B:B, B99, OCT!K:K) -> 0 | J99: =G99-E99-H99 -> 0
A100: =IF(ISBLANK(B100),"",TEXT(B100,"dddd")) -> Saturday | B100: 46326 | C100: =SUMIF(AUG!$B$3:$B$100, B100, AUG!$D$3:$D$100) -> 0 | D100: =IFERROR(__xludf.DUMMYFUNCTION("IFNA(INDEX(FILTER(AUG!$E$3:$E$100, AUG!$B$3:$B$100=B100), 1), ""-"")"),"-") -> - | E100: =SUMIF(AUG!$B$3:$B$100, B100, AUG!$F$3:$F$100) -> 0 | F100: =IFERROR(__xludf.DUMMYFUNCTION("IFNA(INDEX(FILTER(AUG!$G$3:$G$100, AUG!$B$3:$B$100=B100), 1), ""-"")"),"-") -> - | G100: =IFNA(SUMIF(AUG!$B$3:$B$100,B100,AUG!$H$3:$H$100),"-") -> 0 | H100: =E100*0.07% -> 0 | I100: =SUMIF(OCT!B:B, B100, OCT!K:K) -> 0 | J100: =G100-E100-H100 -> 0
...

Sheet MONTHLY
A1: MONTHLY SUMMARY 2026
A2: MONTH | B2: NOMINAL | C2: RATE BUY (AVG) | D2: BUY | E2: RATE SELL (AVG) | F2: SELL | G2: FEE 0.07% | H2: PROFIT
A3: =IFERROR(__xludf.DUMMYFUNCTION("UNIQUE(FILTER(SUMMARY!A2:A153,(SUMMARY!A2:A153<>"""")*(COUNTIF(LEGEND!B2:B13,SUMMARY!A2:A153)>0)))"),"AUG") -> AUG | B3: {=IFERROR(SUM( INDEX(SUMMARY!$C:$C,MATCH($A3,SUMMARY!$A:$A,0)+1): INDEX(SUMMARY!$C:$C,MATCH($A3&"_TOTAL",SUMMARY!$A:$A,0)-1) ),0)} -> 1139465.6 | C3: {=IFERROR( AVERAGE( INDEX(SUMMARY!D:D,MATCH($A3,SUMMARY!$A:$A,0)+1): INDEX(SUMMARY!D:D,MATCH($A3&"_TOTAL",SUMMARY!$A:$A,0)-1) ),0)} -> 17737.582 | D3: {=IFERROR(SUM( INDEX(SUMMARY!E:E,MATCH($A3,SUMMARY!$A:$A,0)+1): INDEX(SUMMARY!E:E,MATCH($A3&"_TOTAL",SUMMARY!$A:$A,0)-1) ),0)} -> 20209889639 | E3: {=IFERROR(AVERAGE( INDEX(SUMMARY!F:F,MATCH($A3,SUMMARY!$A:$A,0)+1): INDEX(SUMMARY!F:F,MATCH($A3&"_TOTAL",SUMMARY!$A:$A,0)-1) ),0)} -> 17762.5 | F3: {=IFERROR(SUM( INDEX(SUMMARY!G:G,MATCH($A3,SUMMARY!$A:$A,0)+1): INDEX(SUMMARY!G:G,MATCH($A3&"_TOTAL",SUMMARY!$A:$A,0)-1) ),0)} -> 20249998209 | G3: {=IFERROR(SUM( INDEX(SUMMARY!H:H,MATCH($A3,SUMMARY!$A:$A,0)+1): INDEX(SUMMARY!H:H,MATCH($A3&"_TOTAL",SUMMARY!$A:$A,0)-1) ),0)} -> 14146923 | H3: {=IFERROR(SUM( INDEX(SUMMARY!J:J,MATCH($A3,SUMMARY!$A:$A,0)+1): INDEX(SUMMARY!J:J,MATCH($A3&"_TOTAL",SUMMARY!$A:$A,0)-1) ),0)} -> 25961647
A4: =IFERROR(__xludf.DUMMYFUNCTION("""COMPUTED_VALUE"""),"SEP") -> SEP | B4: {=IFERROR(SUM( INDEX(SUMMARY!$C:$C,MATCH($A4,SUMMARY!$A:$A,0)+1): INDEX(SUMMARY!$C:$C,MATCH($A4&"_TOTAL",SUMMARY!$A:$A,0)-1) ),0)} -> 11639891 | C4: {=IFERROR( AVERAGE( INDEX(SUMMARY!D:D,MATCH($A4,SUMMARY!$A:$A,0)+1): INDEX(SUMMARY!D:D,MATCH($A4&"_TOTAL",SUMMARY!$A:$A,0)-1) ),0)} -> 17635.512 | D4: {=IFERROR(SUM( INDEX(SUMMARY!E:E,MATCH($A4,SUMMARY!$A:$A,0)+1): INDEX(SUMMARY!E:E,MATCH($A4&"_TOTAL",SUMMARY!$A:$A,0)-1) ),0)} -> 205573414297 | E4: {=IFERROR(AVERAGE( INDEX(SUMMARY!F:F,MATCH($A4,SUMMARY!$A:$A,0)+1): INDEX(SUMMARY!F:F,MATCH($A4&"_TOTAL",SUMMARY!$A:$A,0)-1) ),0)} -> 17663.643 | F4: {=IFERROR(SUM( INDEX(SUMMARY!G:G,MATCH($A4,SUMMARY!$A:$A,0)+1): INDEX(SUMMARY!G:G,MATCH($A4&"_TOTAL",SUMMARY!$A:$A,0)-1) ),0)} -> 205910516613 | G4: =IFERROR(SUM( INDEX(#REF!,MATCH($K4,$A:$A,0)+1): INDEX(#REF!,MATCH($K4&"_TOTAL",$A:$A,0)-1) ),0) -> 0 | H4: {=IFERROR(SUM( INDEX(SUMMARY!J:J,MATCH($A4,SUMMARY!$A:$A,0)+1): INDEX(SUMMARY!J:J,MATCH($A4&"_TOTAL",SUMMARY!$A:$A,0)-1) ),0)} -> 2.9364768e+08
A5: =IFERROR(__xludf.DUMMYFUNCTION("""COMPUTED_VALUE"""),"OCT") -> OCT | B5: {=IFERROR(SUM( INDEX(SUMMARY!$C:$C,MATCH($A5,SUMMARY!$A:$A,0)+1): INDEX(SUMMARY!$C:$C,MATCH($A5&"_TOTAL",SUMMARY!$A:$A,0)-1) ),0)} -> 0 | C5: {=IFERROR( AVERAGE( INDEX(SUMMARY!D:D,MATCH($A5,SUMMARY!$A:$A,0)+1): INDEX(SUMMARY!D:D,MATCH($A5&"_TOTAL",SUMMARY!$A:$A,0)-1) ),0)} -> 0 | D5: {=IFERROR(SUM( INDEX(SUMMARY!E:E,MATCH($A5,SUMMARY!$A:$A,0)+1): INDEX(SUMMARY!E:E,MATCH($A5&"_TOTAL",SUMMARY!$A:$A,0)-1) ),0)} -> 0 | E5: {=IFERROR(AVERAGE( INDEX(SUMMARY!F:F,MATCH($A5,SUMMARY!$A:$A,0)+1): INDEX(SUMMARY!F:F,MATCH($A5&"_TOTAL",SUMMARY!$A:$A,0)-1) ),0)} -> 0 | F5: {=IFERROR(SUM( INDEX(SUMMARY!G:G,MATCH($A5,SUMMARY!$A:$A,0)+1): INDEX(SUMMARY!G:G,MATCH($A5&"_TOTAL",SUMMARY!$A:$A,0)-1) ),0)} -> 0 | G5: =IFERROR(SUM( INDEX(#REF!,MATCH($K5,$A:$A,0)+1): INDEX(#REF!,MATCH($K5&"_TOTAL",$A:$A,0)-1) ),0) -> 0 | H5: {=IFERROR(SUM( INDEX(SUMMARY!J:J,MATCH($A5,SUMMARY!$A:$A,0)+1): INDEX(SUMMARY!J:J,MATCH($A5&"_TOTAL",SUMMARY!$A:$A,0)-1) ),0)} -> 0
A6: =IFERROR(__xludf.DUMMYFUNCTION("""COMPUTED_VALUE"""),"NOV") -> NOV | B6: {=IFERROR(SUM( INDEX(SUMMARY!$C:$C,MATCH($A6,SUMMARY!$A:$A,0)+1): INDEX(SUMMARY!$C:$C,MATCH($A6&"_TOTAL",SUMMARY!$A:$A,0)-1) ),0)} -> 0 | C6: {=IFERROR( AVERAGE( INDEX(SUMMARY!D:D,MATCH($A6,SUMMARY!$A:$A,0)+1): INDEX(SUMMARY!D:D,MATCH($A6&"_TOTAL",SUMMARY!$A:$A,0)-1) ),0)} -> 0 | D6: {=IFERROR(SUM( INDEX(SUMMARY!E:E,MATCH($A6,SUMMARY!$A:$A,0)+1): INDEX(SUMMARY!E:E,MATCH($A6&"_TOTAL",SUMMARY!$A:$A,0)-1) ),0)} -> 0 | E6: {=IFERROR(AVERAGE( INDEX(SUMMARY!F:F,MATCH($A6,SUMMARY!$A:$A,0)+1): INDEX(SUMMARY!F:F,MATCH($A6&"_TOTAL",SUMMARY!$A:$A,0)-1) ),0)} -> 0 | F6: {=IFERROR(SUM( INDEX(SUMMARY!G:G,MATCH($A6,SUMMARY!$A:$A,0)+1): INDEX(SUMMARY!G:G,MATCH($A6&"_TOTAL",SUMMARY!$A:$A,0)-1) ),0)} -> 0 | G6: =IFERROR(SUM( INDEX(#REF!,MATCH($K6,$A:$A,0)+1): INDEX(#REF!,MATCH($K6&"_TOTAL",$A:$A,0)-1) ),0) -> 0 | H6: {=IFERROR(SUM( INDEX(SUMMARY!J:J,MATCH($A6,SUMMARY!$A:$A,0)+1): INDEX(SUMMARY!J:J,MATCH($A6&"_TOTAL",SUMMARY!$A:$A,0)-1) ),0)} -> 0
A7: =IFERROR(__xludf.DUMMYFUNCTION("""COMPUTED_VALUE"""),"DEC") -> DEC | B7: {=IFERROR(SUM( INDEX(SUMMARY!$C:$C,MATCH($A7,SUMMARY!$A:$A,0)+1): INDEX(SUMMARY!$C:$C,MATCH($A7&"_TOTAL",SUMMARY!$A:$A,0)-1) ),0)} -> 0 | C7: {=IFERROR( AVERAGE( INDEX(SUMMARY!D:D,MATCH($A7,SUMMARY!$A:$A,0)+1): INDEX(SUMMARY!D:D,MATCH($A7&"_TOTAL",SUMMARY!$A:$A,0)-1) ),0)} -> 0 | D7: {=IFERROR(SUM( INDEX(SUMMARY!E:E,MATCH($A7,SUMMARY!$A:$A,0)+1): INDEX(SUMMARY!E:E,MATCH($A7&"_TOTAL",SUMMARY!$A:$A,0)-1) ),0)} -> 0 | E7: {=IFERROR(AVERAGE( INDEX(SUMMARY!F:F,MATCH($A7,SUMMARY!$A:$A,0)+1): INDEX(SUMMARY!F:F,MATCH($A7&"_TOTAL",SUMMARY!$A:$A,0)-1) ),0)} -> 0 | F7: {=IFERROR(SUM( INDEX(SUMMARY!G:G,MATCH($A7,SUMMARY!$A:$A,0)+1): INDEX(SUMMARY!G:G,MATCH($A7&"_TOTAL",SUMMARY!$A:$A,0)-1) ),0)} -> 0 | G7: =IFERROR(SUM( INDEX(#REF!,MATCH($K7,$A:$A,0)+1): INDEX(#REF!,MATCH($K7&"_TOTAL",$A:$A,0)-1) ),0) -> 0 | H7: {=IFERROR(SUM( INDEX(SUMMARY!J:J,MATCH($A7,SUMMARY!$A:$A,0)+1): INDEX(SUMMARY!J:J,MATCH($A7&"_TOTAL",SUMMARY!$A:$A,0)-1) ),0)} -> 0
B8: {=IFERROR(SUM( INDEX(SUMMARY!$C:$C,MATCH($A8,SUMMARY!$A:$A,0)+1): INDEX(SUMMARY!$C:$C,MATCH($A8&"_TOTAL",SUMMARY!$A:$A,0)-1) ),0)} -> 0 | C8: {=IFERROR( AVERAGE( INDEX(SUMMARY!D:D,MATCH($A8,SUMMARY!$A:$A,0)+1): INDEX(SUMMARY!D:D,MATCH($A8&"_TOTAL",SUMMARY!$A:$A,0)-1) ),0)} -> 0 | D8: {=IFERROR(SUM( INDEX(SUMMARY!E:E,MATCH($A8,SUMMARY!$A:$A,0)+1): INDEX(SUMMARY!E:E,MATCH($A8&"_TOTAL",SUMMARY!$A:$A,0)-1) ),0)} -> 0 | E8: {=IFERROR(AVERAGE( INDEX(SUMMARY!F:F,MATCH($A8,SUMMARY!$A:$A,0)+1): INDEX(SUMMARY!F:F,MATCH($A8&"_TOTAL",SUMMARY!$A:$A,0)-1) ),0)} -> 0 | F8: {=IFERROR(SUM( INDEX(SUMMARY!G:G,MATCH($A8,SUMMARY!$A:$A,0)+1): INDEX(SUMMARY!G:G,MATCH($A8&"_TOTAL",SUMMARY!$A:$A,0)-1) ),0)} -> 0 | G8: =IFERROR(SUM( INDEX(#REF!,MATCH($K8,$A:$A,0)+1): INDEX(#REF!,MATCH($K8&"_TOTAL",$A:$A,0)-1) ),0) -> 0 | H8: {=IFERROR(SUM( INDEX(SUMMARY!J:J,MATCH($A8,SUMMARY!$A:$A,0)+1): INDEX(SUMMARY!J:J,MATCH($A8&"_TOTAL",SUMMARY!$A:$A,0)-1) ),0)} -> 0
B9: {=IFERROR(SUM( INDEX(SUMMARY!$C:$C,MATCH($A9,SUMMARY!$A:$A,0)+1): INDEX(SUMMARY!$C:$C,MATCH($A9&"_TOTAL",SUMMARY!$A:$A,0)-1) ),0)} -> 0 | C9: {=IFERROR( AVERAGE( INDEX(SUMMARY!D:D,MATCH($A9,SUMMARY!$A:$A,0)+1): INDEX(SUMMARY!D:D,MATCH($A9&"_TOTAL",SUMMARY!$A:$A,0)-1) ),0)} -> 0 | D9: {=IFERROR(SUM( INDEX(SUMMARY!E:E,MATCH($A9,SUMMARY!$A:$A,0)+1): INDEX(SUMMARY!E:E,MATCH($A9&"_TOTAL",SUMMARY!$A:$A,0)-1) ),0)} -> 0 | E9: {=IFERROR(AVERAGE( INDEX(SUMMARY!F:F,MATCH($A9,SUMMARY!$A:$A,0)+1): INDEX(SUMMARY!F:F,MATCH($A9&"_TOTAL",SUMMARY!$A:$A,0)-1) ),0)} -> 0 | F9: {=IFERROR(SUM( INDEX(SUMMARY!G:G,MATCH($A9,SUMMARY!$A:$A,0)+1): INDEX(SUMMARY!G:G,MATCH($A9&"_TOTAL",SUMMARY!$A:$A,0)-1) ),0)} -> 0 | G9: =IFERROR(SUM( INDEX(#REF!,MATCH($K9,$A:$A,0)+1): INDEX(#REF!,MATCH($K9&"_TOTAL",$A:$A,0)-1) ),0) -> 0 | H9: {=IFERROR(SUM( INDEX(SUMMARY!J:J,MATCH($A9,SUMMARY!$A:$A,0)+1): INDEX(SUMMARY!J:J,MATCH($A9&"_TOTAL",SUMMARY!$A:$A,0)-1) ),0)} -> 0
B10: {=IFERROR(SUM( INDEX(SUMMARY!$C:$C,MATCH($A10,SUMMARY!$A:$A,0)+1): INDEX(SUMMARY!$C:$C,MATCH($A10&"_TOTAL",SUMMARY!$A:$A,0)-1) ),0)} -> 0 | C10: {=IFERROR( AVERAGE( INDEX(SUMMARY!D:D,MATCH($A10,SUMMARY!$A:$A,0)+1): INDEX(SUMMARY!D:D,MATCH($A10&"_TOTAL",SUMMARY!$A:$A,0)-1) ),0)} -> 0 | D10: {=IFERROR(SUM( INDEX(SUMMARY!E:E,MATCH($A10,SUMMARY!$A:$A,0)+1): INDEX(SUMMARY!E:E,MATCH($A10&"_TOTAL",SUMMARY!$A:$A,0)-1) ),0)} -> 0 | E10: {=IFERROR(AVERAGE( INDEX(SUMMARY!F:F,MATCH($A10,SUMMARY!$A:$A,0)+1): INDEX(SUMMARY!F:F,MATCH($A10&"_TOTAL",SUMMARY!$A:$A,0)-1) ),0)} -> 0 | F10: {=IFERROR(SUM( INDEX(SUMMARY!G:G,MATCH($A10,SUMMARY!$A:$A,0)+1): INDEX(SUMMARY!G:G,MATCH($A10&"_TOTAL",SUMMARY!$A:$A,0)-1) ),0)} -> 0 | G10: =IFERROR(SUM( INDEX(#REF!,MATCH($K10,$A:$A,0)+1): INDEX(#REF!,MATCH($K10&"_TOTAL",$A:$A,0)-1) ),0) -> 0 | H10: {=IFERROR(SUM( INDEX(SUMMARY!J:J,MATCH($A10,SUMMARY!$A:$A,0)+1): INDEX(SUMMARY!J:J,MATCH($A10&"_TOTAL",SUMMARY!$A:$A,0)-1) ),0)} -> 0
B11: {=IFERROR(SUM( INDEX(SUMMARY!$C:$C,MATCH($A11,SUMMARY!$A:$A,0)+1): INDEX(SUMMARY!$C:$C,MATCH($A11&"_TOTAL",SUMMARY!$A:$A,0)-1) ),0)} -> 0 | C11: {=IFERROR( AVERAGE( INDEX(SUMMARY!D:D,MATCH($A11,SUMMARY!$A:$A,0)+1): INDEX(SUMMARY!D:D,MATCH($A11&"_TOTAL",SUMMARY!$A:$A,0)-1) ),0)} -> 0 | D11: {=IFERROR(SUM( INDEX(SUMMARY!E:E,MATCH($A11,SUMMARY!$A:$A,0)+1): INDEX(SUMMARY!E:E,MATCH($A11&"_TOTAL",SUMMARY!$A:$A,0)-1) ),0)} -> 0 | E11: {=IFERROR(AVERAGE( INDEX(SUMMARY!F:F,MATCH($A11,SUMMARY!$A:$A,0)+1): INDEX(SUMMARY!F:F,MATCH($A11&"_TOTAL",SUMMARY!$A:$A,0)-1) ),0)} -> 0 | F11: {=IFERROR(SUM( INDEX(SUMMARY!G:G,MATCH($A11,SUMMARY!$A:$A,0)+1): INDEX(SUMMARY!G:G,MATCH($A11&"_TOTAL",SUMMARY!$A:$A,0)-1) ),0)} -> 0 | G11: =IFERROR(SUM( INDEX(#REF!,MATCH($K11,$A:$A,0)+1): INDEX(#REF!,MATCH($K11&"_TOTAL",$A:$A,0)-1) ),0) -> 0 | H11: {=IFERROR(SUM( INDEX(SUMMARY!J:J,MATCH($A11,SUMMARY!$A:$A,0)+1): INDEX(SUMMARY!J:J,MATCH($A11&"_TOTAL",SUMMARY!$A:$A,0)-1) ),0)} -> 0
B12: {=IFERROR(SUM( INDEX(SUMMARY!$C:$C,MATCH($A12,SUMMARY!$A:$A,0)+1): INDEX(SUMMARY!$C:$C,MATCH($A12&"_TOTAL",SUMMARY!$A:$A,0)-1) ),0)} -> 0 | C12: {=IFERROR( AVERAGE( INDEX(SUMMARY!D:D,MATCH($A12,SUMMARY!$A:$A,0)+1): INDEX(SUMMARY!D:D,MATCH($A12&"_TOTAL",SUMMARY!$A:$A,0)-1) ),0)} -> 0 | D12: {=IFERROR(SUM( INDEX(SUMMARY!E:E,MATCH($A12,SUMMARY!$A:$A,0)+1): INDEX(SUMMARY!E:E,MATCH($A12&"_TOTAL",SUMMARY!$A:$A,0)-1) ),0)} -> 0 | E12: {=IFERROR(AVERAGE( INDEX(SUMMARY!F:F,MATCH($A12,SUMMARY!$A:$A,0)+1): INDEX(SUMMARY!F:F,MATCH($A12&"_TOTAL",SUMMARY!$A:$A,0)-1) ),0)} -> 0 | F12: {=IFERROR(SUM( INDEX(SUMMARY!G:G,MATCH($A12,SUMMARY!$A:$A,0)+1): INDEX(SUMMARY!G:G,MATCH($A12&"_TOTAL",SUMMARY!$A:$A,0)-1) ),0)} -> 0 | G12: =IFERROR(SUM( INDEX(#REF!,MATCH($K12,$A:$A,0)+1): INDEX(#REF!,MATCH($K12&"_TOTAL",$A:$A,0)-1) ),0) -> 0 | H12: {=IFERROR(SUM( INDEX(SUMMARY!J:J,MATCH($A12,SUMMARY!$A:$A,0)+1): INDEX(SUMMARY!J:J,MATCH($A12&"_TOTAL",SUMMARY!$A:$A,0)-1) ),0)} -> 0
B13: {=IFERROR(SUM( INDEX(SUMMARY!$C:$C,MATCH($A13,SUMMARY!$A:$A,0)+1): INDEX(SUMMARY!$C:$C,MATCH($A13&"_TOTAL",SUMMARY!$A:$A,0)-1) ),0)} -> 0 | C13: {=IFERROR( AVERAGE( INDEX(SUMMARY!D:D,MATCH($A13,SUMMARY!$A:$A,0)+1): INDEX(SUMMARY!D:D,MATCH($A13&"_TOTAL",SUMMARY!$A:$A,0)-1) ),0)} -> 0 | D13: {=IFERROR(SUM( INDEX(SUMMARY!E:E,MATCH($A13,SUMMARY!$A:$A,0)+1): INDEX(SUMMARY!E:E,MATCH($A13&"_TOTAL",SUMMARY!$A:$A,0)-1) ),0)} -> 0 | E13: {=IFERROR(AVERAGE( INDEX(SUMMARY!F:F,MATCH($A13,SUMMARY!$A:$A,0)+1): INDEX(SUMMARY!F:F,MATCH($A13&"_TOTAL",SUMMARY!$A:$A,0)-1) ),0)} -> 0 | F13: {=IFERROR(SUM( INDEX(SUMMARY!G:G,MATCH($A13,SUMMARY!$A:$A,0)+1): INDEX(SUMMARY!G:G,MATCH($A13&"_TOTAL",SUMMARY!$A:$A,0)-1) ),0)} -> 0 | G13: =IFERROR(SUM( INDEX(#REF!,MATCH($K13,$A:$A,0)+1): INDEX(#REF!,MATCH($K13&"_TOTAL",$A:$A,0)-1) ),0) -> 0 | H13: {=IFERROR(SUM( INDEX(SUMMARY!J:J,MATCH($A13,SUMMARY!$A:$A,0)+1): INDEX(SUMMARY!J:J,MATCH($A13&"_TOTAL",SUMMARY!$A:$A,0)-1) ),0)} -> 0
B14: {=IFERROR(SUM( INDEX(SUMMARY!$C:$C,MATCH($A14,SUMMARY!$A:$A,0)+1): INDEX(SUMMARY!$C:$C,MATCH($A14&"_TOTAL",SUMMARY!$A:$A,0)-1) ),0)} -> 0 | C14: {=IFERROR( AVERAGE( INDEX(SUMMARY!D:D,MATCH($A14,SUMMARY!$A:$A,0)+1): INDEX(SUMMARY!D:D,MATCH($A14&"_TOTAL",SUMMARY!$A:$A,0)-1) ),0)} -> 0 | D14: {=IFERROR(SUM( INDEX(SUMMARY!E:E,MATCH($A14,SUMMARY!$A:$A,0)+1): INDEX(SUMMARY!E:E,MATCH($A14&"_TOTAL",SUMMARY!$A:$A,0)-1) ),0)} -> 0 | E14: {=IFERROR(AVERAGE( INDEX(SUMMARY!F:F,MATCH($A14,SUMMARY!$A:$A,0)+1): INDEX(SUMMARY!F:F,MATCH($A14&"_TOTAL",SUMMARY!$A:$A,0)-1) ),0)} -> 0 | F14: {=IFERROR(SUM( INDEX(SUMMARY!G:G,MATCH($A14,SUMMARY!$A:$A,0)+1): INDEX(SUMMARY!G:G,MATCH($A14&"_TOTAL",SUMMARY!$A:$A,0)-1) ),0)} -> 0 | G14: =IFERROR(SUM( INDEX(#REF!,MATCH($K14,$A:$A,0)+1): INDEX(#REF!,MATCH($K14&"_TOTAL",$A:$A,0)-1) ),0) -> 0 | H14: {=IFERROR(SUM( INDEX(SUMMARY!J:J,MATCH($A14,SUMMARY!$A:$A,0)+1): INDEX(SUMMARY!J:J,MATCH($A14&"_TOTAL",SUMMARY!$A:$A,0)-1) ),0)} -> 0
B15: {=IFERROR(SUM( INDEX(SUMMARY!$C:$C,MATCH($A15,SUMMARY!$A:$A,0)+1): INDEX(SUMMARY!$C:$C,MATCH($A15&"_TOTAL",SUMMARY!$A:$A,0)-1) ),0)} -> 0 | C15: {=IFERROR( AVERAGE( INDEX(SUMMARY!D:D,MATCH($A15,SUMMARY!$A:$A,0)+1): INDEX(SUMMARY!D:D,MATCH($A15&"_TOTAL",SUMMARY!$A:$A,0)-1) ),0)} -> 0 | D15: {=IFERROR(SUM( INDEX(SUMMARY!E:E,MATCH($A15,SUMMARY!$A:$A,0)+1): INDEX(SUMMARY!E:E,MATCH($A15&"_TOTAL",SUMMARY!$A:$A,0)-1) ),0)} -> 0 | E15: {=IFERROR(AVERAGE( INDEX(SUMMARY!F:F,MATCH($A15,SUMMARY!$A:$A,0)+1): INDEX(SUMMARY!F:F,MATCH($A15&"_TOTAL",SUMMARY!$A:$A,0)-1) ),0)} -> 0 | F15: {=IFERROR(SUM( INDEX(SUMMARY!G:G,MATCH($A15,SUMMARY!$A:$A,0)+1): INDEX(SUMMARY!G:G,MATCH($A15&"_TOTAL",SUMMARY!$A:$A,0)-1) ),0)} -> 0 | G15: =IFERROR(SUM( INDEX(#REF!,MATCH($K15,$A:$A,0)+1): INDEX(#REF!,MATCH($K15&"_TOTAL",$A:$A,0)-1) ),0) -> 0 | H15: {=IFERROR(SUM( INDEX(SUMMARY!J:J,MATCH($A15,SUMMARY!$A:$A,0)+1): INDEX(SUMMARY!J:J,MATCH($A15&"_TOTAL",SUMMARY!$A:$A,0)-1) ),0)} -> 0

Sheet BUY_JAN

Sheet BUY_FEB

Sheet BUY_MAR

Sheet BUY_APR

Sheet BUY_MAY

Sheet BUY_JUN

Sheet BUY_JUL

Sheet BUY_AUG
A1: Day | B1: Date | C1: ID | D1: Nominal | E1: Price | F1: Total | G1: >> AVG >> | H1: Date | I1: ID | J1: Nominal | K1: Total | L1: RATE | M1: >> DAILY >> | N1: Date | O1: Nominal | P1: Total | Q1: Rate | R1: Fee % | S1: Fee ($) | T1: GrandTotal | U1: Sisa | V1: Sisa (Rp)
A2: =IF(ISBLANK(B2),"",TEXT(B2,"dddd")) -> Monday | B2: 46244 | C2: 1 | D2: 27480.75 | E2: 17663 | F2: =D2*E2 -> 4.8539249e+08 | H2: {=INDEX(UNIQUE(B2:C999), , 1)} -> 46244 | I2: {=INDEX(UNIQUE(B2:C999), , 2)} -> 1 | J2: =SUMIFS($D$2:$D999, $B$2:$B999, H2, $C$2:$C999, I2) -> 55860.87 | K2: =SUMIFS($F$2:$F999, $B$2:$B999, H2, $C$2:$C999, I2) -> 9.8672731e+08 | L2: =IFERROR(K2/J2, 0) -> 17664.016 | N2: {=UNIQUE(H2:H100)} -> 46244 | O2: =SUMIF($H$2:$H999, N2, $J$2:$J999) -> 169529.07 | P2: =SUMIF($H$2:$H999, N2, $K$2:$K999) -> 2994242932 | Q2: =IF(N2="", "", IFERROR(P2/O2, "-")) -> 17662.121 | R2: 0.07 | S2: =O2*$R2% -> 118.67035 | T2: =O2-S2 -> 169410.4 | U2: =IFERROR(ROUND(ABS(VALUE(T2)-VALUE(SUMMARY!C14)), 2), "-") -> 160.95 | V2: =IFERROR(ROUND(VALUE(U2)*VALUE(Q2), 2), "-") -> 2842718.4 | X2: NOTE : sisa = grandtotal - nominal (summary) total pembelian - total transaksi
A3: =IF(ISBLANK(B3),"",TEXT(B3,"dddd")) -> Monday | B3: 46244 | C3: 1 | D3: 27480.75 | E3: 17665 | F3: =D3*E3 -> 4.8544745e+08 | H3: 46244 | I3: 2 | J3: =SUMIFS($D$2:$D1000, $B$2:$B1000, H3, $C$2:$C1000, I3) -> 53373.26 | K3: =SUMIFS($F$2:$F1000, $B$2:$B1000, H3, $C$2:$C1000, I3) -> 9.4283864e+08 | L3: =IFERROR(K3/J3, 0) -> 17665 | N3: 46245 | O3: =SUMIF($H$2:$H1000, N3, $J$2:$J1000) -> 110534.77 | P3: =SUMIF($H$2:$H1000, N3, $K$2:$K1000) -> 1957578144 | Q3: =IF(N3="", "", IFERROR(P3/O3, "-")) -> 17710.067 | R3: 0.07 | S3: =O3*$R3% -> 77.374339 | T3: =O3-S3 -> 110457.4 | U3: =IFERROR(ROUND(ABS(VALUE(T3)-VALUE(SUMMARY!C15)), 2), "-") -> 2409.73 | V3: =IFERROR(ROUND(VALUE(U3)*VALUE(Q3), 2), "-") -> 42676479
A4: =IF(ISBLANK(B4),"",TEXT(B4,"dddd")) -> Monday | B4: 46244 | C4: 1 | D4: 899.37 | E4: 17665 | F4: =D4*E4 -> 15887371 | H4: 46244 | I4: 3 | J4: =SUMIFS($D$2:$D1001, $B$2:$B1001, H4, $C$2:$C1001, I4) -> 60294.94 | K4: =SUMIFS($F$2:$F1001, $B$2:$B1001, H4, $C$2:$C1001, I4) -> 1064676987 | L4: =IFERROR(K4/J4, 0) -> 17657.817 | N4: 46246 | O4: =SUMIF($H$2:$H1001, N4, $J$2:$J1001) -> 281056.05 | P4: =SUMIF($H$2:$H1001, N4, $K$2:$K1001) -> 4994470881 | Q4: =IF(N4="", "", IFERROR(P4/O4, "-")) -> 17770.373 | R4: 0.07 | S4: =O4*$R4% -> 196.73924 | T4: =O4-S4 -> 280859.31 | U4: =IFERROR(ROUND(ABS(VALUE(T4)-VALUE(SUMMARY!C16)), 2), "-") -> 133.82 | V4: =IFERROR(ROUND(VALUE(U4)*VALUE(Q4), 2), "-") -> 2378031.3
A5: =IF(ISBLANK(B5),"",TEXT(B5,"dddd")) -> Monday | B5: 46244 | C5: 2 | D5: 3173.58 | E5: 17665 | F5: =D5*E5 -> 56061291 | H5: 46245 | I5: 1 | J5: =SUMIFS($D$2:$D1002, $B$2:$B1002, H5, $C$2:$C1002, I5) -> 53792.55 | K5: =SUMIFS($F$2:$F1002, $B$2:$B1002, H5, $C$2:$C1002, I5) -> 9.5246288e+08 | L5: =IFERROR(K5/J5, 0) -> 17706.223 | N5: 46247 | O5: =SUMIF($H$2:$H1002, N5, $J$2:$J1002) -> 224750.43 | P5: =SUMIF($H$2:$H1002, N5, $K$2:$K1002) -> 3996285414 | Q5: =IF(N5="", "", IFERROR(P5/O5, "-")) -> 17780.991 | R5: 0.07 | S5: =O5*$R5% -> 157.3253 | T5: =O5-S5 -> 224593.1 | U5: =IFERROR(ROUND(ABS(VALUE(T5)-VALUE(SUMMARY!C17)), 2), "-") -> 110.47 | V5: =IFERROR(ROUND(VALUE(U5)*VALUE(Q5), 2), "-") -> 1964266.1
A6: =IF(ISBLANK(B6),"",TEXT(B6,"dddd")) -> Monday | B6: 46244 | C6: 2 | D6: 49300.31 | E6: 17665 | F6: =D6*E6 -> 8.7088998e+08 | H6: 46245 | I6: 2 | J6: =SUMIFS($D$2:$D1003, $B$2:$B1003, H6, $C$2:$C1003, I6) -> 56742.22 | K6: =SUMIFS($F$2:$F1003, $B$2:$B1003, H6, $C$2:$C1003, I6) -> 1005115261 | L6: =IFERROR(K6/J6, 0) -> 17713.711 | N6: 46248 | O6: =SUMIF($H$2:$H1003, N6, $J$2:$J1003) -> 168761.53 | P6: =SUMIF($H$2:$H1003, N6, $K$2:$K1003) -> 2992276608 | Q6: =IF(N6="", "", IFERROR(P6/O6, "-")) -> 17730.798 | R6: 0.07 | S6: =O6*$R6% -> 118.13307 | T6: =O6-S6 -> 168643.4 | V6: =IFERROR(ROUND(VALUE(U6)*VALUE(Q6), 2), "-") -> 0
A7: =IF(ISBLANK(B7),"",TEXT(B7,"dddd")) -> Monday | B7: 46244 | C7: 2 | D7: 899.37 | E7: 17665 | F7: =D7*E7 -> 15887371 | H7: 46246 | I7: 1 | J7: =SUMIFS($D$2:$D1004, $B$2:$B1004, H7, $C$2:$C1004, I7) -> 56144.37 | K7: =SUMIFS($F$2:$F1004, $B$2:$B1004, H7, $C$2:$C1004, I7) -> 9.9814425e+08 | L7: =IFERROR(K7/J7, 0) -> 17778.172 | N7: 46249 | O7: =SUMIF($H$2:$H1004, N7, $J$2:$J1004) -> 92083.22 | P7: =SUMIF($H$2:$H1004, N7, $K$2:$K1004) -> 1629862445 | Q7: =IF(N7="", "", IFERROR(P7/O7, "-")) -> 17699.885 | R7: 0.07 | S7: =O7*$R7% -> 64.458254 | T7: =O7-S7 -> 92018.762 | V7: =IFERROR(ROUND(VALUE(U7)*VALUE(Q7), 2), "-") -> 0
A8: =IF(ISBLANK(B8),"",TEXT(B8,"dddd")) -> Monday | B8: 46244 | C8: 3 | D8: 1269.19 | E8: 17665 | F8: =D8*E8 -> 22420241 | H8: 46246 | I8: 2 | J8: =SUMIFS($D$2:$D1005, $B$2:$B1005, H8, $C$2:$C1005, I8) -> 56210.64 | K8: =SUMIFS($F$2:$F1005, $B$2:$B1005, H8, $C$2:$C1005, I8) -> 9.9924999e+08 | L8: =IFERROR(K8/J8, 0) -> 17776.883 | N8: 46251 | O8: =SUMIF($H$2:$H1005, N8, $J$2:$J1005) -> 56108.35 | P8: =SUMIF($H$2:$H1005, N8, $K$2:$K1005) -> 9.9468423e+08 | Q8: =IF(N8="", "", IFERROR(P8/O8, "-")) -> 17727.918 | R8: 0 | S8: =O8*$R8% -> 0 | T8: =O8-S8 -> 56108.35 | V8: =IFERROR(ROUND(VALUE(U8)*VALUE(Q8), 2), "-") -> 0
A9: =IF(ISBLANK(B9),"",TEXT(B9,"dddd")) -> Monday | B9: 46244 | C9: 3 | D9: 899.37 | E9: 17665 | F9: =D9*E9 -> 15887371 | H9: 46246 | I9: 3 | J9: =SUMIFS($D$2:$D1006, $B$2:$B1006, H9, $C$2:$C1006, I9) -> 56280.58 | K9: =SUMIFS($F$2:$F1006, $B$2:$B1006, H9, $C$2:$C1006, I9) -> 9.9943054e+08 | L9: =IFERROR(K9/J9, 0) -> 17758 | N9: 46252 | O9: =SUMIF($H$2:$H1006, N9, $J$2:$J1006) -> 27980.4 | P9: =SUMIF($H$2:$H1006, N9, $K$2:$K1006) -> 497211708 | Q9: =IF(N9="", "", IFERROR(P9/O9, "-")) -> 17770 | R9: 0 | S9: =O9*$R9% -> 0 | T9: =O9-S9 -> 27980.4 | V9: =IFERROR(ROUND(VALUE(U9)*VALUE(Q9), 2), "-") -> 0
A10: =IF(ISBLANK(B10),"",TEXT(B10,"dddd")) -> Monday | B10: 46244 | C10: 3 | D10: 1166.22 | E10: 17665 | F10: =D10*E10 -> 20601276 | H10: 46246 | I10: 4 | J10: =SUMIFS($D$2:$D1007, $B$2:$B1007, H10, $C$2:$C1007, I10) -> 56109.89 | K10: =SUMIFS($F$2:$F1007, $B$2:$B1007, H10, $C$2:$C1007, I10) -> 9.9692888e+08 | L10: =IFERROR(K10/J10, 0) -> 17767.436 | O10: =SUMIF($H$2:$H1007, N10, $J$2:$J1007) -> 0 | P10: =SUMIF($H$2:$H1007, N10, $K$2:$K1007) -> 0 | Q10: =IF(N10="", "", IFERROR(P10/O10, "-")) | R10: 0 | S10: =O10*$R10% -> 0 | T10: =O10-S10 -> 0 | V10: =IFERROR(ROUND(VALUE(U10)*VALUE(Q10), 2), "-") -> 0
A11: =IF(ISBLANK(B11),"",TEXT(B11,"dddd")) -> Monday | B11: 46244 | C11: 3 | D11: 19751.63 | E11: 17652 | F11: =D11*E11 -> 3.4865577e+08 | H11: 46246 | I11: 5 | J11: =SUMIFS($D$2:$D1008, $B$2:$B1008, H11, $C$2:$C1008, I11) -> 56310.57 | K11: =SUMIFS($F$2:$F1008, $B$2:$B1008, H11, $C$2:$C1008, I11) -> 1000717223 | L11: =IFERROR(K11/J11, 0) -> 17771.392 | O11: =SUMIF($H$2:$H1008, N11, $J$2:$J1008) -> 0 | P11: =SUMIF($H$2:$H1008, N11, $K$2:$K1008) -> 0 | Q11: =IF(N11="", "", IFERROR(P11/O11, "-")) | R11: 0 | S11: =O11*$R11% -> 0 | T11: =O11-S11 -> 0 | V11: =IFERROR(ROUND(VALUE(U11)*VALUE(Q11), 2), "-") -> 0
A12: =IF(ISBLANK(B12),"",TEXT(B12,"dddd")) -> Monday | B12: 46244 | C12: 3 | D12: 1998.61 | E12: 17652 | F12: =D12*E12 -> 35279464 | H12: 46247 | I12: 1 | J12: =SUMIFS($D$2:$D1009, $B$2:$B1009, H12, $C$2:$C1009, I12) -> 56064.56 | K12: =SUMIFS($F$2:$F1009, $B$2:$B1009, H12, $C$2:$C1009, I12) -> 997949168 | L12: =IFERROR(K12/J12, 0) -> 17800 | O12: =SUMIF($H$2:$H1009, N12, $J$2:$J1009) -> 0 | P12: =SUMIF($H$2:$H1009, N12, $K$2:$K1009) -> 0 | Q12: =IF(N12="", "", IFERROR(P12/O12, "-")) | R12: 0 | S12: =O12*$R12% -> 0 | T12: =O12-S12 -> 0 | V12: =IFERROR(ROUND(VALUE(U12)*VALUE(Q12), 2), "-") -> 0
A13: =IF(ISBLANK(B13),"",TEXT(B13,"dddd")) -> Monday | B13: 46244 | C13: 3 | D13: 1666.45 | E13: 17652 | F13: =D13*E13 -> 29416175 | H13: 46247 | I13: 2 | J13: =SUMIFS($D$2:$D1010, $B$2:$B1010, H13, $C$2:$C1010, I13) -> 55782.71 | K13: =SUMIFS($F$2:$F1010, $B$2:$B1010, H13, $C$2:$C1010, I13) -> 9.9226285e+08 | L13: =IFERROR(K13/J13, 0) -> 17788 | O13: =SUMIF($H$2:$H1010, N13, $J$2:$J1010) -> 0 | P13: =SUMIF($H$2:$H1010, N13, $K$2:$K1010) -> 0 | Q13: =IF(N13="", "", IFERROR(P13/O13, "-")) | R13: 0 | S13: =O13*$R13% -> 0 | T13: =O13-S13 -> 0 | V13: =IFERROR(ROUND(VALUE(U13)*VALUE(Q13), 2), "-") -> 0
A14: =IF(ISBLANK(B14),"",TEXT(B14,"dddd")) -> Monday | B14: 46244 | C14: 3 | D14: 898.48 | E14: 17655 | F14: =D14*E14 -> 15862664 | H14: 46247 | I14: 3 | J14: =SUMIFS($D$2:$D1011, $B$2:$B1011, H14, $C$2:$C1011, I14) -> 55960.8 | K14: =SUMIFS($F$2:$F1011, $B$2:$B1011, H14, $C$2:$C1011, I14) -> 994833129 | L14: =IFERROR(K14/J14, 0) -> 17777.321 | O14: =SUMIF($H$2:$H1011, N14, $J$2:$J1011) -> 0 | P14: =SUMIF($H$2:$H1011, N14, $K$2:$K1011) -> 0 | Q14: =IF(N14="", "", IFERROR(P14/O14, "-")) | R14: 0 | S14: =O14*$R14% -> 0 | T14: =O14-S14 -> 0 | V14: =IFERROR(ROUND(VALUE(U14)*VALUE(Q14), 2), "-") -> 0
A15: =IF(ISBLANK(B15),"",TEXT(B15,"dddd")) -> Monday | B15: 46244 | C15: 3 | D15: 849.41 | E15: 17655 | F15: =D15*E15 -> 14996334 | H15: 46247 | I15: 4 | J15: =SUMIFS($D$2:$D1012, $B$2:$B1012, H15, $C$2:$C1012, I15) -> 56942.36 | K15: =SUMIFS($F$2:$F1012, $B$2:$B1012, H15, $C$2:$C1012, I15) -> 1011240272 | L15: =IFERROR(K15/J15, 0) -> 17759.016 | O15: =SUMIF($H$2:$H1012, N15, $J$2:$J1012) -> 0 | P15: =SUMIF($H$2:$H1012, N15, $K$2:$K1012) -> 0 | Q15: =IF(N15="", "", IFERROR(P15/O15, "-")) | R15: 0 | S15: =O15*$R15% -> 0 | T15: =O15-S15 -> 0 | V15: =IFERROR(ROUND(VALUE(U15)*VALUE(Q15), 2), "-") -> 0
A16: =IF(ISBLANK(B16),"",TEXT(B16,"dddd")) -> Monday | B16: 46244 | C16: 3 | D16: 1131.65 | E16: 17655 | F16: =D16*E16 -> 19979281 | H16: 46248 | I16: 1 | J16: =SUMIFS($D$2:$D1013, $B$2:$B1013, H16, $C$2:$C1013, I16) -> 56774.58 | K16: =SUMIFS($F$2:$F1013, $B$2:$B1013, H16, $C$2:$C1013, I16) -> 1007200140 | L16: =IFERROR(K16/J16, 0) -> 17740.336 | O16: =SUMIF($H$2:$H1013, N16, $J$2:$J1013) -> 0 | P16: =SUMIF($H$2:$H1013, N16, $K$2:$K1013) -> 0 | Q16: =IF(N16="", "", IFERROR(P16/O16, "-")) | R16: 0 | S16: =O16*$R16% -> 0 | T16: =O16-S16 -> 0 | V16: =IFERROR(ROUND(VALUE(U16)*VALUE(Q16), 2), "-") -> 0
A17: =IF(ISBLANK(B17),"",TEXT(B17,"dddd")) -> Monday | B17: 46244 | C17: 3 | D17: 1132.03 | E17: 17655 | F17: =D17*E17 -> 19985990 | H17: 46248 | I17: 2 | J17: =SUMIFS($D$2:$D1014, $B$2:$B1014, H17, $C$2:$C1014, I17) -> 55504.17 | K17: =SUMIFS($F$2:$F1014, $B$2:$B1014, H17, $C$2:$C1014, I17) -> 9.8454356e+08 | L17: =IFERROR(K17/J17, 0) -> 17738.191 | O17: =SUMIF($H$2:$H1014, N17, $J$2:$J1014) -> 0 | P17: =SUMIF($H$2:$H1014, N17, $K$2:$K1014) -> 0 | Q17: =IF(N17="", "", IFERROR(P17/O17, "-")) | R17: 0 | S17: =O17*$R17% -> 0 | T17: =O17-S17 -> 0 | V17: =IFERROR(ROUND(VALUE(U17)*VALUE(Q17), 2), "-") -> 0
A18: =IF(ISBLANK(B18),"",TEXT(B18,"dddd")) -> Monday | B18: 46244 | C18: 3 | D18: 3599.42 | E18: 17662 | F18: =D18*E18 -> 63572956 | H18: 46248 | I18: 3 | J18: =SUMIFS($D$2:$D1015, $B$2:$B1015, H18, $C$2:$C1015, I18) -> 56482.78 | K18: =SUMIFS($F$2:$F1015, $B$2:$B1015, H18, $C$2:$C1015, I18) -> 1000532908 | L18: =IFERROR(K18/J18, 0) -> 17713.946 | O18: =SUMIF($H$2:$H1015, N18, $J$2:$J1015) -> 0 | P18: =SUMIF($H$2:$H1015, N18, $K$2:$K1015) -> 0 | Q18: =IF(N18="", "", IFERROR(P18/O18, "-")) | R18: 0 | S18: =O18*$R18% -> 0 | T18: =O18-S18 -> 0 | V18: =IFERROR(ROUND(VALUE(U18)*VALUE(Q18), 2), "-") -> 0
A19: =IF(ISBLANK(B19),"",TEXT(B19,"dddd")) -> Monday | B19: 46244 | C19: 3 | D19: 999.3 | E19: 17662 | F19: =D19*E19 -> 17649637 | H19: 46249 | I19: 1 | J19: =SUMIFS($D$2:$D1016, $B$2:$B1016, H19, $C$2:$C1016, I19) -> 54951.44 | K19: =SUMIFS($F$2:$F1016, $B$2:$B1016, H19, $C$2:$C1016, I19) -> 9.7313421e+08 | L19: =IFERROR(K19/J19, 0) -> 17708.985 | O19: =SUMIF($H$2:$H1016, N19, $J$2:$J1016) -> 0 | P19: =SUMIF($H$2:$H1016, N19, $K$2:$K1016) -> 0 | Q19: =IF(N19="", "", IFERROR(P19/O19, "-")) | R19: 0 | S19: =O19*$R19% -> 0 | T19: =O19-S19 -> 0 | V19: =IFERROR(ROUND(VALUE(U19)*VALUE(Q19), 2), "-") -> 0
A20: =IF(ISBLANK(B20),"",TEXT(B20,"dddd")) -> Monday | B20: 46244 | C20: 3 | D20: 3219.83 | E20: 17662 | F20: =D20*E20 -> 56868637 | H20: 46249 | I20: 2 | J20: =SUMIFS($D$2:$D1017, $B$2:$B1017, H20, $C$2:$C1017, I20) -> 37131.78 | K20: =SUMIFS($F$2:$F1017, $B$2:$B1017, H20, $C$2:$C1017, I20) -> 6.5672823e+08 | L20: =IFERROR(K20/J20, 0) -> 17686.419 | O20: =SUMIF($H$2:$H1017, N20, $J$2:$J1017) -> 0 | P20: =SUMIF($H$2:$H1017, N20, $K$2:$K1017) -> 0 | Q20: =IF(N20="", "", IFERROR(P20/O20, "-")) | R20: 0 | S20: =O20*$R20% -> 0 | T20: =O20-S20 -> 0 | V20: =IFERROR(ROUND(VALUE(U20)*VALUE(Q20), 2), "-") -> 0
A21: =IF(ISBLANK(B21),"",TEXT(B21,"dddd")) -> Monday | B21: 46244 | C21: 3 | D21: 3998.64 | E21: 17662 | F21: =D21*E21 -> 70623980 | H21: 46251 | J21: =SUMIFS($D$2:$D1018, $B$2:$B1018, H21, $C$2:$C1018, I21) -> 0 | K21: =SUMIFS($F$2:$F1018, $B$2:$B1018, H21, $C$2:$C1018, I21) -> 0 | L21: =IFERROR(K21/J21, 0) -> 0 | O21: =SUMIF($H$2:$H1018, N21, $J$2:$J1018) -> 0 | P21: =SUMIF($H$2:$H1018, N21, $K$2:$K1018) -> 0 | Q21: =IF(N21="", "", IFERROR(P21/O21, "-")) | R21: 0 | S21: =O21*$R21% -> 0 | T21: =O21-S21 -> 0 | V21: =IFERROR(ROUND(VALUE(U21)*VALUE(Q21), 2), "-") -> 0
A22: =IF(ISBLANK(B22),"",TEXT(B22,"dddd")) -> Monday | B22: 46244 | C22: 3 | D22: 1226.6 | E22: 17662 | F22: =D22*E22 -> 21664209 | H22: 46251 | I22: 1 | J22: =SUMIFS($D$2:$D1019, $B$2:$B1019, H22, $C$2:$C1019, I22) -> 28788.08 | K22: =SUMIFS($F$2:$F1019, $B$2:$B1019, H22, $C$2:$C1019, I22) -> 5.1049684e+08 | L22: =IFERROR(K22/J22, 0) -> 17732.924 | O22: =SUMIF($H$2:$H1019, N22, $J$2:$J1019) -> 0 | P22: =SUMIF($H$2:$H1019, N22, $K$2:$K1019) -> 0 | Q22: =IF(N22="", "", IFERROR(P22/O22, "-")) | R22: 0 | S22: =O22*$R22% -> 0 | T22: =O22-S22 -> 0 | V22: =IFERROR(ROUND(VALUE(U22)*VALUE(Q22), 2), "-") -> 0
A23: =IF(ISBLANK(B23),"",TEXT(B23,"dddd")) -> Monday | B23: 46244 | C23: 3 | D23: 2498.25 | E23: 17662 | F23: =D23*E23 -> 44124092 | H23: 46251 | I23: 2 | J23: =SUMIFS($D$2:$D1020, $B$2:$B1020, H23, $C$2:$C1020, I23) -> 27320.27 | K23: =SUMIFS($F$2:$F1020, $B$2:$B1020, H23, $C$2:$C1020, I23) -> 4.8418739e+08 | L23: =IFERROR(K23/J23, 0) -> 17722.643 | O23: =SUMIF($H$2:$H1020, N23, $J$2:$J1020) -> 0 | P23: =SUMIF($H$2:$H1020, N23, $K$2:$K1020) -> 0 | Q23: =IF(N23="", "", IFERROR(P23/O23, "-")) | R23: 0 | S23: =O23*$R23% -> 0 | T23: =O23-S23 -> 0 | V23: =IFERROR(ROUND(VALUE(U23)*VALUE(Q23), 2), "-") -> 0
A24: =IF(ISBLANK(B24),"",TEXT(B24,"dddd")) -> Monday | B24: 46244 | C24: 3 | D24: 2428.3 | E24: 17662 | F24: =D24*E24 -> 42888635 | H24: 46252 | I24: 1 | J24: =SUMIFS($D$2:$D1021, $B$2:$B1021, H24, $C$2:$C1021, I24) -> 27980.4 | K24: =SUMIFS($F$2:$F1021, $B$2:$B1021, H24, $C$2:$C1021, I24) -> 497211708 | L24: =IFERROR(K24/J24, 0) -> 17770 | O24: =SUMIF($H$2:$H1021, N24, $J$2:$J1021) -> 0 | P24: =SUMIF($H$2:$H1021, N24, $K$2:$K1021) -> 0 | Q24: =IF(N24="", "", IFERROR(P24/O24, "-")) | R24: 0 | S24: =O24*$R24% -> 0 | T24: =O24-S24 -> 0 | V24: =IFERROR(ROUND(VALUE(U24)*VALUE(Q24), 2), "-") -> 0
A25: =IF(ISBLANK(B25),"",TEXT(B25,"dddd")) -> Monday | B25: 46244 | C25: 3 | D25: 1732.79 | E25: 17662 | F25: =D25*E25 -> 30604537 | H25: 46252 | I25: 2 | J25: =SUMIFS($D$2:$D1022, $B$2:$B1022, H25, $C$2:$C1022, I25) -> 0 | K25: =SUMIFS($F$2:$F1022, $B$2:$B1022, H25, $C$2:$C1022, I25) -> 0 | L25: =IFERROR(K25/J25, 0) -> 0 | O25: =SUMIF($H$2:$H1022, N25, $J$2:$J1022) -> 0 | P25: =SUMIF($H$2:$H1022, N25, $K$2:$K1022) -> 0 | Q25: =IF(N25="", "", IFERROR(P25/O25, "-")) | R25: 0 | S25: =O25*$R25% -> 0 | T25: =O25-S25 -> 0 | V25: =IFERROR(ROUND(VALUE(U25)*VALUE(Q25), 2), "-") -> 0
A26: =IF(ISBLANK(B26),"",TEXT(B26,"dddd")) -> Monday | B26: 46244 | C26: 3 | D26: 3504.55 | E26: 17662 | F26: =D26*E26 -> 61897362 | H26: 46252 | J26: =SUMIFS($D$2:$D1023, $B$2:$B1023, H26, $C$2:$C1023, I26) -> 0 | K26: =SUMIFS($F$2:$F1023, $B$2:$B1023, H26, $C$2:$C1023, I26) -> 0 | L26: =IFERROR(K26/J26, 0) -> 0 | O26: =SUMIF($H$2:$H1023, N26, $J$2:$J1023) -> 0 | P26: =SUMIF($H$2:$H1023, N26, $K$2:$K1023) -> 0 | Q26: =IF(N26="", "", IFERROR(P26/O26, "-")) | R26: 0 | S26: =O26*$R26% -> 0 | T26: =O26-S26 -> 0 | V26: =IFERROR(ROUND(VALUE(U26)*VALUE(Q26), 2), "-") -> 0
A27: =IF(ISBLANK(B27),"",TEXT(B27,"dddd")) -> Monday | B27: 46244 | C27: 3 | D27: 1998.6 | E27: 17662 | F27: =D27*E27 -> 35299273 | J27: =SUMIFS($D$2:$D1024, $B$2:$B1024, H27, $C$2:$C1024, I27) -> 0 | K27: =SUMIFS($F$2:$F1024, $B$2:$B1024, H27, $C$2:$C1024, I27) -> 0 | L27: =IFERROR(K27/J27, 0) -> 0 | O27: =SUMIF($H$2:$H1024, N27, $J$2:$J1024) -> 0 | P27: =SUMIF($H$2:$H1024, N27, $K$2:$K1024) -> 0 | Q27: =IF(N27="", "", IFERROR(P27/O27, "-")) | R27: 0 | S27: =O27*$R27% -> 0 | T27: =O27-S27 -> 0 | V27: =IFERROR(ROUND(VALUE(U27)*VALUE(Q27), 2), "-") -> 0
A28: =IF(ISBLANK(B28),"",TEXT(B28,"dddd")) -> Monday | B28: 46244 | C28: 3 | D28: 4325.62 | E28: 17662 | F28: =D28*E28 -> 76399100 | G28: =sum(D2:D28) -> 169529.07 | J28: =SUMIFS($D$2:$D1025, $B$2:$B1025, H28, $C$2:$C1025, I28) -> 0 | K28: =SUMIFS($F$2:$F1025, $B$2:$B1025, H28, $C$2:$C1025, I28) -> 0 | L28: =IFERROR(K28/J28, 0) -> 0 | O28: =SUMIF($H$2:$H1025, N28, $J$2:$J1025) -> 0 | P28: =SUMIF($H$2:$H1025, N28, $K$2:$K1025) -> 0 | Q28: =IF(N28="", "", IFERROR(P28/O28, "-")) | R28: 0 | S28: =O28*$R28% -> 0 | T28: =O28-S28 -> 0 | V28: =IFERROR(ROUND(VALUE(U28)*VALUE(Q28), 2), "-") -> 0
A29: =IF(ISBLANK(B29),"",TEXT(B29,"dddd")) -> Tuesday | B29: 46245 | C29: 1 | D29: 0.01 | E29: 17829 | F29: =D29*E29 -> 178.29 | J29: =SUMIFS($D$2:$D1026, $B$2:$B1026, H29, $C$2:$C1026, I29) -> 0 | K29: =SUMIFS($F$2:$F1026, $B$2:$B1026, H29, $C$2:$C1026, I29) -> 0 | L29: =IFERROR(K29/J29, 0) -> 0 | O29: =SUMIF($H$2:$H1026, N29, $J$2:$J1026) -> 0 | P29: =SUMIF($H$2:$H1026, N29, $K$2:$K1026) -> 0 | Q29: =IF(N29="", "", IFERROR(P29/O29, "-")) | R29: 0 | S29: =O29*$R29% -> 0 | T29: =O29-S29 -> 0 | V29: =IFERROR(ROUND(VALUE(U29)*VALUE(Q29), 2), "-") -> 0
A30: =IF(ISBLANK(B30),"",TEXT(B30,"dddd")) -> Tuesday | B30: 46245 | C30: 1 | D30: 2997.9 | E30: 17710 | F30: =D30*E30 -> 53092809 | J30: =SUMIFS($D$2:$D1027, $B$2:$B1027, H30, $C$2:$C1027, I30) -> 0 | K30: =SUMIFS($F$2:$F1027, $B$2:$B1027, H30, $C$2:$C1027, I30) -> 0 | L30: =IFERROR(K30/J30, 0) -> 0 | O30: =SUMIF($H$2:$H1027, N30, $J$2:$J1027) -> 0 | P30: =SUMIF($H$2:$H1027, N30, $K$2:$K1027) -> 0 | Q30: =IF(N30="", "", IFERROR(P30/O30, "-")) | R30: 0 | S30: =O30*$R30% -> 0 | T30: =O30-S30 -> 0 | V30: =IFERROR(ROUND(VALUE(U30)*VALUE(Q30), 2), "-") -> 0
A31: =IF(ISBLANK(B31),"",TEXT(B31,"dddd")) -> Tuesday | B31: 46245 | C31: 1 | D31: 50794.64 | E31: 17706 | F31: =D31*E31 -> 8.993699e+08 | J31: =SUMIFS($D$2:$D1028, $B$2:$B1028, H31, $C$2:$C1028, I31) -> 0 | K31: =SUMIFS($F$2:$F1028, $B$2:$B1028, H31, $C$2:$C1028, I31) -> 0 | L31: =IFERROR(K31/J31, 0) -> 0 | O31: =SUMIF($H$2:$H1028, N31, $J$2:$J1028) -> 0 | P31: =SUMIF($H$2:$H1028, N31, $K$2:$K1028) -> 0 | Q31: =IF(N31="", "", IFERROR(P31/O31, "-")) | R31: 0 | S31: =O31*$R31% -> 0 | T31: =O31-S31 -> 0 | V31: =IFERROR(ROUND(VALUE(U31)*VALUE(Q31), 2), "-") -> 0
A32: =IF(ISBLANK(B32),"",TEXT(B32,"dddd")) -> Tuesday | B32: 46245 | C32: 2 | D32: 4319.92 | E32: 17710 | F32: =D32*E32 -> 76505783 | J32: =SUMIFS($D$2:$D1029, $B$2:$B1029, H32, $C$2:$C1029, I32) -> 0 | K32: =SUMIFS($F$2:$F1029, $B$2:$B1029, H32, $C$2:$C1029, I32) -> 0 | L32: =IFERROR(K32/J32, 0) -> 0 | O32: =SUMIF($H$2:$H1029, N32, $J$2:$J1029) -> 0 | P32: =SUMIF($H$2:$H1029, N32, $K$2:$K1029) -> 0 | Q32: =IF(N32="", "", IFERROR(P32/O32, "-")) | R32: 0 | S32: =O32*$R32% -> 0 | T32: =O32-S32 -> 0 | V32: =IFERROR(ROUND(VALUE(U32)*VALUE(Q32), 2), "-") -> 0
A33: =IF(ISBLANK(B33),"",TEXT(B33,"dddd")) -> Tuesday | B33: 46245 | C33: 2 | D33: 16925.81 | E33: 17712 | F33: =D33*E33 -> 2.9978995e+08 | J33: =SUMIFS($D$2:$D1030, $B$2:$B1030, H33, $C$2:$C1030, I33) -> 0 | K33: =SUMIFS($F$2:$F1030, $B$2:$B1030, H33, $C$2:$C1030, I33) -> 0 | L33: =IFERROR(K33/J33, 0) -> 0 | O33: =SUMIF($H$2:$H1030, N33, $J$2:$J1030) -> 0 | P33: =SUMIF($H$2:$H1030, N33, $K$2:$K1030) -> 0 | Q33: =IF(N33="", "", IFERROR(P33/O33, "-")) | R33: 0 | S33: =O33*$R33% -> 0 | T33: =O33-S33 -> 0 | V33: =IFERROR(ROUND(VALUE(U33)*VALUE(Q33), 2), "-") -> 0
A34: =IF(ISBLANK(B34),"",TEXT(B34,"dddd")) -> Tuesday | B34: 46245 | C34: 2 | D34: 21312.26 | E34: 17715 | F34: =D34*E34 -> 3.7754669e+08 | J34: =SUMIFS($D$2:$D1031, $B$2:$B1031, H34, $C$2:$C1031, I34) -> 0 | K34: =SUMIFS($F$2:$F1031, $B$2:$B1031, H34, $C$2:$C1031, I34) -> 0 | L34: =IFERROR(K34/J34, 0) -> 0 | O34: =SUMIF($H$2:$H1031, N34, $J$2:$J1031) -> 0 | P34: =SUMIF($H$2:$H1031, N34, $K$2:$K1031) -> 0 | Q34: =IF(N34="", "", IFERROR(P34/O34, "-")) | R34: 0 | S34: =O34*$R34% -> 0 | T34: =O34-S34 -> 0 | V34: =IFERROR(ROUND(VALUE(U34)*VALUE(Q34), 2), "-") -> 0
A35: =IF(ISBLANK(B35),"",TEXT(B35,"dddd")) -> Tuesday | B35: 46245 | C35: 2 | D35: 998.46 | E35: 17715 | F35: =D35*E35 -> 17687719 | J35: =SUMIFS($D$2:$D1032, $B$2:$B1032, H35, $C$2:$C1032, I35) -> 0 | K35: =SUMIFS($F$2:$F1032, $B$2:$B1032, H35, $C$2:$C1032, I35) -> 0 | L35: =IFERROR(K35/J35, 0) -> 0 | O35: =SUMIF($H$2:$H1032, N35, $J$2:$J1032) -> 0 | P35: =SUMIF($H$2:$H1032, N35, $K$2:$K1032) -> 0 | Q35: =IF(N35="", "", IFERROR(P35/O35, "-")) | R35: 0 | S35: =O35*$R35% -> 0 | T35: =O35-S35 -> 0 | V35: =IFERROR(ROUND(VALUE(U35)*VALUE(Q35), 2), "-") -> 0
A36: =IF(ISBLANK(B36),"",TEXT(B36,"dddd")) -> Tuesday | B36: 46245 | C36: 2 | D36: 899.37 | E36: 17713 | F36: =D36*E36 -> 15930541 | J36: =SUMIFS($D$2:$D1033, $B$2:$B1033, H36, $C$2:$C1033, I36) -> 0 | K36: =SUMIFS($F$2:$F1033, $B$2:$B1033, H36, $C$2:$C1033, I36) -> 0 | L36: =IFERROR(K36/J36, 0) -> 0 | O36: =SUMIF($H$2:$H1033, N36, $J$2:$J1033) -> 0 | P36: =SUMIF($H$2:$H1033, N36, $K$2:$K1033) -> 0 | Q36: =IF(N36="", "", IFERROR(P36/O36, "-")) | R36: 0 | S36: =O36*$R36% -> 0 | T36: =O36-S36 -> 0 | V36: =IFERROR(ROUND(VALUE(U36)*VALUE(Q36), 2), "-") -> 0
A37: =IF(ISBLANK(B37),"",TEXT(B37,"dddd")) -> Tuesday | B37: 46245 | C37: 2 | D37: 899.37 | E37: 17713 | F37: =D37*E37 -> 15930541 | J37: =SUMIFS($D$2:$D1034, $B$2:$B1034, H37, $C$2:$C1034, I37) -> 0 | K37: =SUMIFS($F$2:$F1034, $B$2:$B1034, H37, $C$2:$C1034, I37) -> 0 | L37: =IFERROR(K37/J37, 0) -> 0 | O37: =SUMIF($H$2:$H1034, N37, $J$2:$J1034) -> 0 | P37: =SUMIF($H$2:$H1034, N37, $K$2:$K1034) -> 0 | Q37: =IF(N37="", "", IFERROR(P37/O37, "-")) | R37: 0 | S37: =O37*$R37% -> 0 | T37: =O37-S37 -> 0 | V37: =IFERROR(ROUND(VALUE(U37)*VALUE(Q37), 2), "-") -> 0
A38: =IF(ISBLANK(B38),"",TEXT(B38,"dddd")) -> Tuesday | B38: 46245 | C38: 2 | D38: 4991.51 | E38: 17713 | F38: =D38*E38 -> 88414617 | J38: =SUMIFS($D$2:$D1035, $B$2:$B1035, H38, $C$2:$C1035, I38) -> 0 | K38: =SUMIFS($F$2:$F1035, $B$2:$B1035, H38, $C$2:$C1035, I38) -> 0 | L38: =IFERROR(K38/J38, 0) -> 0 | O38: =SUMIF($H$2:$H1035, N38, $J$2:$J1035) -> 0 | P38: =SUMIF($H$2:$H1035, N38, $K$2:$K1035) -> 0 | Q38: =IF(N38="", "", IFERROR(P38/O38, "-")) | R38: 0 | S38: =O38*$R38% -> 0 | T38: =O38-S38 -> 0 | V38: =IFERROR(ROUND(VALUE(U38)*VALUE(Q38), 2), "-") -> 0
A39: =IF(ISBLANK(B39),"",TEXT(B39,"dddd")) -> Tuesday | B39: 46245 | C39: 2 | D39: 4596.78 | E39: 17717 | F39: =D39*E39 -> 81441151 | J39: =SUMIFS($D$2:$D1036, $B$2:$B1036, H39, $C$2:$C1036, I39) -> 0 | K39: =SUMIFS($F$2:$F1036, $B$2:$B1036, H39, $C$2:$C1036, I39) -> 0 | L39: =IFERROR(K39/J39, 0) -> 0 | O39: =SUMIF($H$2:$H1036, N39, $J$2:$J1036) -> 0 | P39: =SUMIF($H$2:$H1036, N39, $K$2:$K1036) -> 0 | Q39: =IF(N39="", "", IFERROR(P39/O39, "-")) | R39: 0 | S39: =O39*$R39% -> 0 | T39: =O39-S39 -> 0 | V39: =IFERROR(ROUND(VALUE(U39)*VALUE(Q39), 2), "-") -> 0
A40: =IF(ISBLANK(B40),"",TEXT(B40,"dddd")) -> Tuesday | B40: 46245 | C40: 2 | D40: 899.37 | E40: 17717 | F40: =D40*E40 -> 15934138 | J40: =SUMIFS($D$2:$D1037, $B$2:$B1037, H40, $C$2:$C1037, I40) -> 0 | K40: =SUMIFS($F$2:$F1037, $B$2:$B1037, H40, $C$2:$C1037, I40) -> 0 | L40: =IFERROR(K40/J40, 0) -> 0 | O40: =SUMIF($H$2:$H1037, N40, $J$2:$J1037) -> 0 | P40: =SUMIF($H$2:$H1037, N40, $K$2:$K1037) -> 0 | Q40: =IF(N40="", "", IFERROR(P40/O40, "-")) | R40: 0 | S40: =O40*$R40% -> 0 | T40: =O40-S40 -> 0 | V40: =IFERROR(ROUND(VALUE(U40)*VALUE(Q40), 2), "-") -> 0
A41: =IF(ISBLANK(B41),"",TEXT(B41,"dddd")) -> Tuesday | B41: 46245 | C41: 2 | D41: 899.37 | E41: 17717 | F41: =D41*E41 -> 15934138 | J41: =SUMIFS($D$2:$D1038, $B$2:$B1038, H41, $C$2:$C1038, I41) -> 0 | K41: =SUMIFS($F$2:$F1038, $B$2:$B1038, H41, $C$2:$C1038, I41) -> 0 | L41: =IFERROR(K41/J41, 0) -> 0 | O41: =SUMIF($H$2:$H1038, N41, $J$2:$J1038) -> 0 | P41: =SUMIF($H$2:$H1038, N41, $K$2:$K1038) -> 0 | Q41: =IF(N41="", "", IFERROR(P41/O41, "-")) | R41: 0 | S41: =O41*$R41% -> 0 | T41: =O41-S41 -> 0 | V41: =IFERROR(ROUND(VALUE(U41)*VALUE(Q41), 2), "-") -> 0
A42: =IF(ISBLANK(B42),"",TEXT(B42,"dddd")) -> Wednesday | B42: 46246 | C42: 1 | D42: 0.01 | E42: 17829 | F42: =E42*D42 -> 178.29
A43: =IF(ISBLANK(B43),"",TEXT(B43,"dddd")) -> Wednesday | B43: 46246 | C43: 1 | D43: 24982.5 | E43: 17771 | F43: =E43*D43 -> 4.4396401e+08
A44: =IF(ISBLANK(B44),"",TEXT(B44,"dddd")) -> Wednesday | B44: 46246 | C44: 1 | D44: 992.31 | E44: 17773 | F44: =E44*D44 -> 17636326
A45: =IF(ISBLANK(B45),"",TEXT(B45,"dddd")) -> Wednesday | B45: 46246 | C45: 1 | D45: 6311.58 | E45: 17773 | F45: =E45*D45 -> 1.1217571e+08
A46: =IF(ISBLANK(B46),"",TEXT(B46,"dddd")) -> Wednesday | B46: 46246 | C46: 1 | D46: 5696.01 | E46: 17768 | F46: =E46*D46 -> 1.0120671e+08
A47: =IF(ISBLANK(B47),"",TEXT(B47,"dddd")) -> Wednesday | B47: 46246 | C47: 1 | D47: 1069.26 | E47: 17776 | F47: =E47*D47 -> 19007166
A48: =IF(ISBLANK(B48),"",TEXT(B48,"dddd")) -> Wednesday | B48: 46246 | C48: 1 | D48: 1064.26 | E48: 17785 | F48: =E48*D48 -> 18927864
A49: =IF(ISBLANK(B49),"",TEXT(B49,"dddd")) -> Wednesday | B49: 46246 | C49: 1 | D49: 9993 | E49: 17792 | F49: =E49*D49 -> 177795456
A50: =IF(ISBLANK(B50),"",TEXT(B50,"dddd")) -> Wednesday | B50: 46246 | C50: 1 | D50: 907.52 | E50: 17800 | F50: =E50*D50 -> 16153856
A51: =IF(ISBLANK(B51),"",TEXT(B51,"dddd")) -> Wednesday | B51: 46246 | C51: 1 | D51: 999.3 | E51: 17800 | F51: =E51*D51 -> 17787540
A52: =IF(ISBLANK(B52),"",TEXT(B52,"dddd")) -> Wednesday | B52: 46246 | C52: 1 | D52: 2772.56 | E52: 17800 | F52: =E52*D52 -> 49351568
A53: =IF(ISBLANK(B53),"",TEXT(B53,"dddd")) -> Wednesday | B53: 46246 | C53: 1 | D53: 1356.06 | E53: 17800 | F53: =E53*D53 -> 24137868
... A164: =IF(ISBLANK(B164),"",TEXT(B164,"dddd")) -> Saturday | B164: 46249 | C164: 2 | D164: 2997.9 | E164: 17662 | F164: =E164*D164 -> 52948910
A165: =IF(ISBLANK(B165),"",TEXT(B165,"dddd")) -> Monday | B165: 46251 | F165: =E165*D165 -> 0
A166: =IF(ISBLANK(B166),"",TEXT(B166,"dddd")) -> Monday | B166: 46251 | C166: 1 | D166: 2848.01 | E166: 17717 | F166: =E166*D166 -> 50458193
A167: =IF(ISBLANK(B167),"",TEXT(B167,"dddd")) -> Monday | B167: 46251 | C167: 1 | D167: 15006.74 | E167: 17735 | F167: =E167*D167 -> 2.6614453e+08
A168: =IF(ISBLANK(B168),"",TEXT(B168,"dddd")) -> Monday | B168: 46251 | C168: 1 | D168: 2997.9 | E168: 17735 | F168: =E168*D168 -> 53167756
A169: =IF(ISBLANK(B169),"",TEXT(B169,"dddd")) -> Monday | B169: 46251 | C169: 1 | D169: 3997.2 | E169: 17735 | F169: =E169*D169 -> 70890342
A170: =IF(ISBLANK(B170),"",TEXT(B170,"dddd")) -> Monday | B170: 46251 | C170: 1 | D170: 2243.63 | E170: 17735 | F170: =E170*D170 -> 39790778
A171: =IF(ISBLANK(B171),"",TEXT(B171,"dddd")) -> Monday | B171: 46251 | C171: 1 | D171: 845.19 | E171: 17735 | F171: =E171*D171 -> 14989445
A172: =IF(ISBLANK(B172),"",TEXT(B172,"dddd")) -> Monday | B172: 46251 | C172: 1 | D172: 849.41 | E172: 17725 | F172: =E172*D172 -> 15055792
A173: =IF(ISBLANK(B173),"",TEXT(B173,"dddd")) -> Monday | B173: 46251 | C173: 2 | D173: 4166.02 | E173: 17724 | F173: =E173*D173 -> 73838538
A174: =IF(ISBLANK(B174),"",TEXT(B174,"dddd")) -> Monday | B174: 46251 | C174: 2 | D174: 5807.06 | E174: 17722 | F174: =E174*D174 -> 1.0291272e+08
A175: =IF(ISBLANK(B175),"",TEXT(B175,"dddd")) -> Monday | B175: 46251 | C175: 2 | D175: 5995.8 | E175: 17722 | F175: =E175*D175 -> 1.0625757e+08
A176: =IF(ISBLANK(B176),"",TEXT(B176,"dddd")) -> Monday | B176: 46251 | C176: 2 | D176: 1998.6 | E176: 17722 | F176: =E176*D176 -> 35419189
A177: =IF(ISBLANK(B177),"",TEXT(B177,"dddd")) -> Monday | B177: 46251 | C177: 2 | D177: 1998.6 | E177: 17722 | F177: =E177*D177 -> 35419189
... A183: =IF(ISBLANK(B183),"",TEXT(B183,"dddd")) -> Monday | B183: 46251 | C183: 2 | D183: 999.3 | E183: 17733 | F183: =E183*D183 -> 17720587
A184: =IF(ISBLANK(B184),"",TEXT(B184,"dddd")) -> Monday | B184: 46251 | F184: =E184*D184 -> 0
A185: =IF(ISBLANK(B185),"",TEXT(B185,"dddd")) -> Tuesday | B185: 46252 | C185: 1 | D185: 27980.4 | E185: 17770 | F185: =E185*D185 -> 497211708
A186: =IF(ISBLANK(B186),"",TEXT(B186,"dddd")) -> Tuesday | B186: 46252 | C186: 2 | E186: 17735 | F186: =E186*D186 -> 0
A187: =IF(ISBLANK(B187),"",TEXT(B187,"dddd")) -> Tuesday | B187: 46252 | E187: 17735 | F187: =E187*D187 -> 0
A188: =IF(ISBLANK(B188),"",TEXT(B188,"dddd")) -> Tuesday | B188: 46252 | E188: 17735 | F188: =E188*D188 -> 0
A189: =IF(ISBLANK(B189),"",TEXT(B189,"dddd")) -> Tuesday | B189: 46252 | E189: 17735 | F189: =E189*D189 -> 0
A190: =IF(ISBLANK(B190),"",TEXT(B190,"dddd")) -> Tuesday | B190: 46252 | E190: 17735 | F190: =E190*D190 -> 0
A191: =IF(ISBLANK(B191),"",TEXT(B191,"dddd")) -> Tuesday | B191: 46252 | E191: 17725 | F191: =E191*D191 -> 0
A192: =IF(ISBLANK(B192),"",TEXT(B192,"dddd")) -> Tuesday | B192: 46252 | E192: 17724 | F192: =E192*D192 -> 0
A193: =IF(ISBLANK(B193),"",TEXT(B193,"dddd")) -> Tuesday | B193: 46252 | E193: 17722 | F193: =E193*D193 -> 0
A194: =IF(ISBLANK(B194),"",TEXT(B194,"dddd")) -> Tuesday | B194: 46252 | E194: 17722 | F194: =E194*D194 -> 0
A195: =IF(ISBLANK(B195),"",TEXT(B195,"dddd")) -> Tuesday | B195: 46252 | E195: 17722 | F195: =E195*D195 -> 0
A196: =IF(ISBLANK(B196),"",TEXT(B196,"dddd")) -> Tuesday | B196: 46252 | E196: 17722 | F196: =E196*D196 -> 0
A197: =IF(ISBLANK(B197),"",TEXT(B197,"dddd")) -> Tuesday | B197: 46252 | E197: 17715 | F197: =E197*D197 -> 0
A198: =IF(ISBLANK(B198),"",TEXT(B198,"dddd")) -> Tuesday | B198: 46252 | E198: 17715 | F198: =E198*D198 -> 0
... A202: =IF(ISBLANK(B202),"",TEXT(B202,"dddd")) -> Tuesday | B202: 46252 | E202: 17733 | F202: =E202*D202 -> 0

Sheet AUG
A1: AUGUST | D1: EXCHANGE | M1: SUMMARY | P1: Notes : Purple color is for input
A2: Day | B2: Date | C2: ID | D2: NOMINAL | E2: RATE BUY | F2: BUY | G2: RATE SELL | H2: SELL | I2: FEE (%) | J2: FEE (RP) | L2: PROFIT | M2: DATE | N2: TOTAL (DAILY)
A3: =IF(ISBLANK(B3),"",TEXT(B3,"dddd")) -> Monday | B3: 46244 | C3: 1 | D3: 56529.11 | E3: =IFERROR(__xludf.DUMMYFUNCTION("IFNA(FILTER(BUY_AUG!$L$2:$L$200, BUY_AUG!$H$2:$H$200=B3, BUY_AUG!$I$2:$I$200=C3), ""-"")"),17664.016100178887) -> 17664.016 | F3: =IFERROR(VALUE(E3)*VALUE(D3), "-") -> 9.9853111e+08 | G3: 17690 | H3: =IFERROR(VALUE(G3)*VALUE(D3), "-") -> 9.9999996e+08 | I3: 0.07 | J3: =IF(OR(I3="-", F3="-", I3="", F3=""), "-", VALUE(I3)%*VALUE(F3)) -> 698971.78 | K3: =IF(OR(H3="-", F3="-", H3="", F3=""), "-", VALUE(H3)-VALUE(F3)) -> 1468846.7 | L3: =IF(OR(H3="-", F3="-", J3="-", H3="", F3="", J3=""), "-", VALUE(H3)-VALUE(F3)-VALUE(J3)) -> 769874.95 | M3: {=UNIQUE(B3:B100)} -> 46244 | N3: =SUMIF(B2:B99, M3, L2:L99) -> 2887033.6
A4: =IF(ISBLANK(B4),"",TEXT(B4,"dddd")) -> Monday | B4: 46244 | C4: 2 | D4: 56513.13 | E4: =IFERROR(__xludf.DUMMYFUNCTION("IFNA(FILTER(BUY_AUG!$L$2:$L$200, BUY_AUG!$H$2:$H$200=B4, BUY_AUG!$I$2:$I$200=C4), ""-"")"),17665.0) -> 17665 | F4: =IFERROR(VALUE(E4)*VALUE(D4), "-") -> 9.9830444e+08 | G4: 17695 | H4: =IFERROR(VALUE(G4)*VALUE(D4), "-") -> 9.9999984e+08 | I4: 0.07 | J4: =IF(OR(I4="-", F4="-", I4="", F4=""), "-", VALUE(I4)%*VALUE(F4)) -> 698813.11 | K4: =IF(OR(H4="-", F4="-", H4="", F4=""), "-", VALUE(H4)-VALUE(F4)) -> 1695393.9 | L4: =IF(OR(H4="-", F4="-", J4="-", H4="", F4="", J4=""), "-", VALUE(H4)-VALUE(F4)-VALUE(J4)) -> 996580.79 | M4: 46245 | N4: =SUMIF(B3:B100, M4, L3:L100) -> -271803.38
A5: =IF(ISBLANK(B5),"",TEXT(B5,"dddd")) -> Monday | B5: 46244 | C5: 3 | D5: 56529.11 | E5: =IFERROR(__xludf.DUMMYFUNCTION("IFNA(FILTER(BUY_AUG!$L$2:$L$200, BUY_AUG!$H$2:$H$200=B5, BUY_AUG!$I$2:$I$200=C5), ""-"")"),17657.816505497805) -> 17657.817 | F5: =IFERROR(VALUE(E5)*VALUE(D5), "-") -> 9.9818065e+08 | G5: 17690 | H5: =IFERROR(VALUE(G5)*VALUE(D5), "-") -> 9.9999996e+08 | I5: 0.07 | J5: =IF(OR(I5="-", F5="-", I5="", F5=""), "-", VALUE(I5)%*VALUE(F5)) -> 698726.46 | K5: =IF(OR(H5="-", F5="-", H5="", F5=""), "-", VALUE(H5)-VALUE(F5)) -> 1819304.3 | L5: =IF(OR(H5="-", F5="-", J5="-", H5="", F5="", J5=""), "-", VALUE(H5)-VALUE(F5)-VALUE(J5)) -> 1120577.8 | M5: 46246 | N5: =SUMIF(B4:B101, M5, L4:L101) -> 7911027
A6: =IF(ISBLANK(B6),"",TEXT(B6,"dddd")) -> Tuesday | B6: 46245 | C6: 1 | D6: 56529.11 | E6: =IFERROR(__xludf.DUMMYFUNCTION("IFNA(FILTER(BUY_AUG!$L$2:$L$200, BUY_AUG!$H$2:$H$200=B6, BUY_AUG!$I$2:$I$200=C6), ""-"")"),17706.222945928384) -> 17706.223 | F6: =IFERROR(VALUE(E6)*VALUE(D6), "-") -> 1000917025 | G6: 17690 | H6: =IFERROR(VALUE(G6)*VALUE(D6), "-") -> 9.9999996e+08 | I6: 0.07 | J6: =IF(OR(I6="-", F6="-", I6="", F6=""), "-", VALUE(I6)%*VALUE(F6)) -> 700641.92 | K6: =IF(OR(H6="-", F6="-", H6="", F6=""), "-", VALUE(H6)-VALUE(F6)) -> -917068.69 | L6: =IF(OR(H6="-", F6="-", J6="-", H6="", F6="", J6=""), "-", VALUE(H6)-VALUE(F6)-VALUE(J6)) -> -1617710.6 | M6: 46247 | N6: =SUMIF(B5:B102, M6, L5:L102) -> 5661500.8
A7: =IF(ISBLANK(B7),"",TEXT(B7,"dddd")) -> Tuesday | B7: 46245 | C7: 2 | D7: 56338.02 | E7: =IFERROR(__xludf.DUMMYFUNCTION("IFNA(FILTER(BUY_AUG!$L$2:$L$200, BUY_AUG!$H$2:$H$200=B7, BUY_AUG!$I$2:$I$200=C7), ""-"")"),17713.710545868656) -> 17713.711 | F7: =IFERROR(VALUE(E7)*VALUE(D7), "-") -> 997955379 | G7: 17750 | H7: =IFERROR(VALUE(G7)*VALUE(D7), "-") -> 999999855 | I7: 0.07 | J7: =IF(OR(I7="-", F7="-", I7="", F7=""), "-", VALUE(I7)%*VALUE(F7)) -> 698568.77 | K7: =IF(OR(H7="-", F7="-", H7="", F7=""), "-", VALUE(H7)-VALUE(F7)) -> 2044476 | L7: =IF(OR(H7="-", F7="-", J7="-", H7="", F7="", J7=""), "-", VALUE(H7)-VALUE(F7)-VALUE(J7)) -> 1345907.2 | M7: 46248 | N7: =SUMIF(B6:B103, M7, L6:L103) -> 5641891.7
A8: =IF(ISBLANK(B8),"",TEXT(B8,"dddd")) -> Wednesday | B8: 46246 | C8: 1 | D8: 56100.98 | E8: =IFERROR(__xludf.DUMMYFUNCTION("IFNA(FILTER(BUY_AUG!$L$2:$L$200, BUY_AUG!$H$2:$H$200=B8, BUY_AUG!$I$2:$I$200=C8), ""-"")"),17778.171636799914) -> 17778.172 | F8: =IFERROR(VALUE(E8)*VALUE(D8), "-") -> 9.9737285e+08 | G8: 17825 | H8: =IFERROR(VALUE(G8)*VALUE(D8), "-") -> 9.9999997e+08 | I8: 0.07 | J8: =IF(OR(I8="-", F8="-", I8="", F8=""), "-", VALUE(I8)%*VALUE(F8)) -> 698161 | K8: =IF(OR(H8="-", F8="-", H8="", F8=""), "-", VALUE(H8)-VALUE(F8)) -> 2627117.1 | L8: =IF(OR(H8="-", F8="-", J8="-", H8="", F8="", J8=""), "-", VALUE(H8)-VALUE(F8)-VALUE(J8)) -> 1928956.1 | M8: 46249 | N8: =SUMIF(B7:B104, M8, L7:L104) -> 2720945.7
A9: =IF(ISBLANK(B9),"",TEXT(B9,"dddd")) -> Wednesday | B9: 46246 | C9: 2 | D9: 56100.98 | E9: =IFERROR(__xludf.DUMMYFUNCTION("IFNA(FILTER(BUY_AUG!$L$2:$L$200, BUY_AUG!$H$2:$H$200=B9, BUY_AUG!$I$2:$I$200=C9), ""-"")"),17776.883331162924) -> 17776.883 | F9: =IFERROR(VALUE(E9)*VALUE(D9), "-") -> 9.9730058e+08 | G9: 17825 | H9: =IFERROR(VALUE(G9)*VALUE(D9), "-") -> 9.9999997e+08 | I9: 0.07 | J9: =IF(OR(I9="-", F9="-", I9="", F9=""), "-", VALUE(I9)%*VALUE(F9)) -> 698110.4 | K9: =IF(OR(H9="-", F9="-", H9="", F9=""), "-", VALUE(H9)-VALUE(F9)) -> 2699392.3 | L9: =IF(OR(H9="-", F9="-", J9="-", H9="", F9="", J9=""), "-", VALUE(H9)-VALUE(F9)-VALUE(J9)) -> 2001281.9 | M9: 46251 | N9: =SUMIF(B8:B105, M9, L8:L105) -> 917765.12
A10: =IF(ISBLANK(B10),"",TEXT(B10,"dddd")) -> Wednesday | B10: 46246 | C10: 3 | D10: 56179.77 | E10: =IFERROR(__xludf.DUMMYFUNCTION("IFNA(FILTER(BUY_AUG!$L$2:$L$200, BUY_AUG!$H$2:$H$200=B10, BUY_AUG!$I$2:$I$200=C10), ""-"")"),17758.0) -> 17758 | F10: =IFERROR(VALUE(E10)*VALUE(D10), "-") -> 9.9764036e+08 | G10: 17800 | H10: =IFERROR(VALUE(G10)*VALUE(D10), "-") -> 999999906 | I10: 0.07 | J10: =IF(OR(I10="-", F10="-", I10="", F10=""), "-", VALUE(I10)%*VALUE(F10)) -> 698348.25 | K10: =IF(OR(H10="-", F10="-", H10="", F10=""), "-", VALUE(H10)-VALUE(F10)) -> 2359550.3 | L10: =IF(OR(H10="-", F10="-", J10="-", H10="", F10="", J10=""), "-", VALUE(H10)-VALUE(F10)-VALUE(J10)) -> 1661202.1 | M10: 46252 | N10: =SUMIF(B9:B106, M10, L9:L106) -> 493286.38
A11: =IF(ISBLANK(B11),"",TEXT(B11,"dddd")) -> Wednesday | B11: 46246 | C11: 4 | D11: 56179.77 | E11: =IFERROR(__xludf.DUMMYFUNCTION("IFNA(FILTER(BUY_AUG!$L$2:$L$200, BUY_AUG!$H$2:$H$200=B11, BUY_AUG!$I$2:$I$200=C11), ""-"")"),17767.436055212365) -> 17767.436 | F11: =IFERROR(VALUE(E11)*VALUE(D11), "-") -> 9.9817047e+08 | G11: 17800 | H11: =IFERROR(VALUE(G11)*VALUE(D11), "-") -> 999999906 | I11: 0.07 | J11: =IF(OR(I11="-", F11="-", I11="", F11=""), "-", VALUE(I11)%*VALUE(F11)) -> 698719.33 | K11: =IF(OR(H11="-", F11="-", H11="", F11=""), "-", VALUE(H11)-VALUE(F11)) -> 1829434.9 | L11: =IF(OR(H11="-", F11="-", J11="-", H11="", F11="", J11=""), "-", VALUE(H11)-VALUE(F11)-VALUE(J11)) -> 1130715.6 | N11: =SUMIF(B10:B107, M11, L10:L107) -> 0
A12: =IF(ISBLANK(B12),"",TEXT(B12,"dddd")) -> Wednesday | B12: 46246 | C12: 5 | D12: 56163.99 | E12: =IFERROR(__xludf.DUMMYFUNCTION("IFNA(FILTER(BUY_AUG!$L$2:$L$200, BUY_AUG!$H$2:$H$200=B12, BUY_AUG!$I$2:$I$200=C12), ""-"")"),17771.392168113376) -> 17771.392 | F12: =IFERROR(VALUE(E12)*VALUE(D12), "-") -> 998112292 | G12: 17805 | H12: =IFERROR(VALUE(G12)*VALUE(D12), "-") -> 999999842 | I12: 0.07 | J12: =IF(OR(I12="-", F12="-", I12="", F12=""), "-", VALUE(I12)%*VALUE(F12)) -> 698678.6 | K12: =IF(OR(H12="-", F12="-", H12="", F12=""), "-", VALUE(H12)-VALUE(F12)) -> 1887549.9 | L12: =IF(OR(H12="-", F12="-", J12="-", H12="", F12="", J12=""), "-", VALUE(H12)-VALUE(F12)-VALUE(J12)) -> 1188871.3 | N12: =SUMIF(B11:B108, M12, L11:L108) -> 0
A13: =IF(ISBLANK(B13),"",TEXT(B13,"dddd")) -> Thursday | B13: 46247 | C13: 1 | D13: 56116.72 | E13: =IFERROR(__xludf.DUMMYFUNCTION("IFNA(FILTER(BUY_AUG!$L$2:$L$200, BUY_AUG!$H$2:$H$200=B13, BUY_AUG!$I$2:$I$200=C13), ""-"")"),17799.999999999996) -> 17800 | F13: =IFERROR(VALUE(E13)*VALUE(D13), "-") -> 998877616 | G13: 17820 | H13: =IFERROR(VALUE(G13)*VALUE(D13), "-") -> 9.9999995e+08 | I13: 0.07 | J13: =IF(OR(I13="-", F13="-", I13="", F13=""), "-", VALUE(I13)%*VALUE(F13)) -> 699214.33 | K13: =IF(OR(H13="-", F13="-", H13="", F13=""), "-", VALUE(H13)-VALUE(F13)) -> 1122334.4 | L13: =IF(OR(H13="-", F13="-", J13="-", H13="", F13="", J13=""), "-", VALUE(H13)-VALUE(F13)-VALUE(J13)) -> 423120.07 | N13: =SUMIF(B12:B109, M13, L12:L109) -> 0
A14: =IF(ISBLANK(B14),"",TEXT(B14,"dddd")) -> Thursday | B14: 46247 | C14: 2 | D14: 56116.72 | E14: =IFERROR(__xludf.DUMMYFUNCTION("IFNA(FILTER(BUY_AUG!$L$2:$L$200, BUY_AUG!$H$2:$H$200=B14, BUY_AUG!$I$2:$I$200=C14), ""-"")"),17788.0) -> 17788 | F14: =IFERROR(VALUE(E14)*VALUE(D14), "-") -> 9.9820422e+08 | G14: 17820 | H14: =IFERROR(VALUE(G14)*VALUE(D14), "-") -> 9.9999995e+08 | I14: 0.07 | J14: =IF(OR(I14="-", F14="-", I14="", F14=""), "-", VALUE(I14)%*VALUE(F14)) -> 698742.95 | K14: =IF(OR(H14="-", F14="-", H14="", F14=""), "-", VALUE(H14)-VALUE(F14)) -> 1795735 | L14: =IF(OR(H14="-", F14="-", J14="-", H14="", F14="", J14=""), "-", VALUE(H14)-VALUE(F14)-VALUE(J14)) -> 1096992.1 | N14: =SUMIF(B13:B110, M14, L13:L110) -> 0
A15: =IF(ISBLANK(B15),"",TEXT(B15,"dddd")) -> Thursday | B15: 46247 | C15: 3 | D15: 56116.72 | E15: =IFERROR(__xludf.DUMMYFUNCTION("IFNA(FILTER(BUY_AUG!$L$2:$L$200, BUY_AUG!$H$2:$H$200=B15, BUY_AUG!$I$2:$I$200=C15), ""-"")"),17777.321428571428) -> 17777.321 | F15: =IFERROR(VALUE(E15)*VALUE(D15), "-") -> 997604969 | G15: 17820 | H15: =IFERROR(VALUE(G15)*VALUE(D15), "-") -> 9.9999995e+08 | I15: 0.07 | J15: =IF(OR(I15="-", F15="-", I15="", F15=""), "-", VALUE(I15)%*VALUE(F15)) -> 698323.48 | K15: =IF(OR(H15="-", F15="-", H15="", F15=""), "-", VALUE(H15)-VALUE(F15)) -> 2394981.4 | L15: =IF(OR(H15="-", F15="-", J15="-", H15="", F15="", J15=""), "-", VALUE(H15)-VALUE(F15)-VALUE(J15)) -> 1696658 | N15: =SUMIF(B14:B111, M15, L14:L111) -> 0
A16: =IF(ISBLANK(B16),"",TEXT(B16,"dddd")) -> Thursday | B16: 46247 | C16: 4 | D16: 56132.47 | E16: =IFERROR(__xludf.DUMMYFUNCTION("IFNA(FILTER(BUY_AUG!$L$2:$L$200, BUY_AUG!$H$2:$H$200=B16, BUY_AUG!$I$2:$I$200=C16), ""-"")"),17759.01581072509) -> 17759.016 | F16: =IFERROR(VALUE(E16)*VALUE(D16), "-") -> 9.9685742e+08 | G16: 17815 | H16: =IFERROR(VALUE(G16)*VALUE(D16), "-") -> 9.9999995e+08 | I16: 0.07 | J16: =IF(OR(I16="-", F16="-", I16="", F16=""), "-", VALUE(I16)%*VALUE(F16)) -> 697800.2 | K16: =IF(OR(H16="-", F16="-", H16="", F16=""), "-", VALUE(H16)-VALUE(F16)) -> 3142530.8 | L16: =IF(OR(H16="-", F16="-", J16="-", H16="", F16="", J16=""), "-", VALUE(H16)-VALUE(F16)-VALUE(J16)) -> 2444730.6 | N16: =SUMIF(B15:B112, M16, L15:L112) -> 0
A17: =IF(ISBLANK(B17),"",TEXT(B17,"dddd")) -> Friday | B17: 46248 | C17: 1 | D17: 56242.96 | E17: =IFERROR(__xludf.DUMMYFUNCTION("IFNA(FILTER(BUY_AUG!L16:L120, BUY_AUG!H16:H120=B17, BUY_AUG!I16:I120=C17), ""-"")"),17740.336250307795) -> 17740.336 | F17: =IFERROR(VALUE(E17)*VALUE(D17), "-") -> 9.9776902e+08 | G17: 17780 | H17: =IFERROR(VALUE(G17)*VALUE(D17), "-") -> 9.9999983e+08 | I17: 0.07 | J17: =IF(OR(I17="-", F17="-", I17="", F17=""), "-", VALUE(I17)%*VALUE(F17)) -> 698438.32 | K17: =IF(OR(H17="-", F17="-", H17="", F17=""), "-", VALUE(H17)-VALUE(F17)) -> 2230806.7 | L17: =IF(OR(H17="-", F17="-", J17="-", H17="", F17="", J17=""), "-", VALUE(H17)-VALUE(F17)-VALUE(J17)) -> 1532368.4 | N17: =SUMIF(B16:B113, M17, L16:L113) -> 0
A18: =IF(ISBLANK(B18),"",TEXT(B18,"dddd")) -> Friday | B18: 46248 | C18: 2 | D18: 56258.79 | E18: =IFERROR(__xludf.DUMMYFUNCTION("IFNA(FILTER(BUY_AUG!L17:L121, BUY_AUG!H17:H121=B18, BUY_AUG!I17:I121=C18), ""-"")"),17738.190854669116) -> 17738.191 | F18: =IFERROR(VALUE(E18)*VALUE(D18), "-") -> 9.9792915e+08 | G18: 17775 | H18: =IFERROR(VALUE(G18)*VALUE(D18), "-") -> 9.9999999e+08 | I18: 0.07 | J18: =IF(OR(I18="-", F18="-", I18="", F18=""), "-", VALUE(I18)%*VALUE(F18)) -> 698550.41 | K18: =IF(OR(H18="-", F18="-", H18="", F18=""), "-", VALUE(H18)-VALUE(F18)) -> 2070838 | L18: =IF(OR(H18="-", F18="-", J18="-", H18="", F18="", J18=""), "-", VALUE(H18)-VALUE(F18)-VALUE(J18)) -> 1372287.6 | N18: =SUMIF(B17:B114, M18, L17:L114) -> 0
A19: =IF(ISBLANK(B19),"",TEXT(B19,"dddd")) -> Friday | B19: 46248 | C19: 3 | D19: 56258.79 | E19: =IFERROR(__xludf.DUMMYFUNCTION("IFNA(FILTER(BUY_AUG!L18:L122, BUY_AUG!H18:H122=B19, BUY_AUG!I18:I122=C19), ""-"")"),17713.945871290325) -> 17713.946 | F19: =IFERROR(VALUE(E19)*VALUE(D19), "-") -> 9.9656516e+08 | G19: 17775 | H19: =IFERROR(VALUE(G19)*VALUE(D19), "-") -> 9.9999999e+08 | I19: 0.07 | J19: =IF(OR(I19="-", F19="-", I19="", F19=""), "-", VALUE(I19)%*VALUE(F19)) -> 697595.61 | K19: =IF(OR(H19="-", F19="-", H19="", F19=""), "-", VALUE(H19)-VALUE(F19)) -> 3434831.4 | L19: =IF(OR(H19="-", F19="-", J19="-", H19="", F19="", J19=""), "-", VALUE(H19)-VALUE(F19)-VALUE(J19)) -> 2737235.8 | N19: =SUMIF(B18:B115, M19, L18:L115) -> 0
A20: =IF(ISBLANK(B20),"",TEXT(B20,"dddd")) -> Saturday | B20: 46249 | C20: 1 | D20: 56338.02 | E20: =IFERROR(__xludf.DUMMYFUNCTION("IFNA(FILTER(BUY_AUG!L19:L123, BUY_AUG!H19:H123=B20, BUY_AUG!I19:I123=C20), ""-"")"),17708.98471159263) -> 17708.985 | F20: =IFERROR(VALUE(E20)*VALUE(D20), "-") -> 9.9768913e+08 | G20: 17750 | H20: =IFERROR(VALUE(G20)*VALUE(D20), "-") -> 999999855 | I20: 0.07 | J20: =IF(OR(I20="-", F20="-", I20="", F20=""), "-", VALUE(I20)%*VALUE(F20)) -> 698382.39 | K20: =IF(OR(H20="-", F20="-", H20="", F20=""), "-", VALUE(H20)-VALUE(F20)) -> 2310720.1 | L20: =IF(OR(H20="-", F20="-", J20="-", H20="", F20="", J20=""), "-", VALUE(H20)-VALUE(F20)-VALUE(J20)) -> 1612337.7 | N20: =SUMIF(B19:B116, M20, L19:L116) -> 0
A21: =IF(ISBLANK(B21),"",TEXT(B21,"dddd")) -> Saturday | B21: 46249 | C21: 2 | D21: 42313.11 | E21: =IFERROR(__xludf.DUMMYFUNCTION("IFNA(FILTER(BUY_AUG!L20:L124, BUY_AUG!H20:H124=B21, BUY_AUG!I20:I124=C21), ""-"")"),17686.41940138609) -> 17686.419 | F21: =IFERROR(VALUE(E21)*VALUE(D21), "-") -> 7.4836741e+08 | G21: 17725 | H21: =IFERROR(VALUE(G21)*VALUE(D21), "-") -> 7.4999987e+08 | I21: 0.07 | J21: =IF(OR(I21="-", F21="-", I21="", F21=""), "-", VALUE(I21)%*VALUE(F21)) -> 523857.19 | K21: =IF(OR(H21="-", F21="-", H21="", F21=""), "-", VALUE(H21)-VALUE(F21)) -> 1632465.1 | L21: =IF(OR(H21="-", F21="-", J21="-", H21="", F21="", J21=""), "-", VALUE(H21)-VALUE(F21)-VALUE(J21)) -> 1108607.9 | N21: =SUMIF(B20:B117, M21, L20:L117) -> 0
A22: =IF(ISBLANK(B22),"",TEXT(B22,"dddd")) -> Monday | B22: 46251 | C22: 1 | D22: 28176.95 | E22: =IFERROR(__xludf.DUMMYFUNCTION("IFNA(FILTER(BUY_AUG!L21:L125, BUY_AUG!H21:H125=B22, BUY_AUG!I21:I125=C22), ""-"")"),17732.924200571902) -> 17732.924 | F22: =IFERROR(VALUE(E22)*VALUE(D22), "-") -> 4.9965972e+08 | G22: 17745 | H22: =IFERROR(VALUE(G22)*VALUE(D22), "-") -> 4.9999998e+08 | I22: 0.07 | J22: =IF(OR(I22="-", F22="-", I22="", F22=""), "-", VALUE(I22)%*VALUE(F22)) -> 349761.8 | K22: =IF(OR(H22="-", F22="-", H22="", F22=""), "-", VALUE(H22)-VALUE(F22)) -> 340259.2 | L22: =IF(OR(H22="-", F22="-", J22="-", H22="", F22="", J22=""), "-", VALUE(H22)-VALUE(F22)-VALUE(J22)) -> -9502.6063 | N22: =SUMIF(B21:B118, M22, L21:L118) -> 0
A23: =IF(ISBLANK(B23),"",TEXT(B23,"dddd")) -> Monday | B23: 46251 | C23: 2 | D23: 28140.47 | E23: =IFERROR(__xludf.DUMMYFUNCTION("IFNA(FILTER(BUY_AUG!L22:L126, BUY_AUG!H22:H126=B23, BUY_AUG!I22:I126=C23), ""-"")"),17722.642755726793) -> 17722.643 | F23: =IFERROR(VALUE(E23)*VALUE(D23), "-") -> 4.987235e+08 | G23: 17768 | H23: =IFERROR(VALUE(G23)*VALUE(D23), "-") -> 499999871 | I23: 0.07 | J23: =IF(OR(I23="-", F23="-", I23="", F23=""), "-", VALUE(I23)%*VALUE(F23)) -> 349106.45 | K23: =IF(OR(H23="-", F23="-", H23="", F23=""), "-", VALUE(H23)-VALUE(F23)) -> 1276374.2 | L23: =IF(OR(H23="-", F23="-", J23="-", H23="", F23="", J23=""), "-", VALUE(H23)-VALUE(F23)-VALUE(J23)) -> 927267.72 | N23: =SUMIF(B22:B119, M23, L22:L119) -> 0
A24: =IF(ISBLANK(B24),"",TEXT(B24,"dddd")) -> Tuesday | B24: 46252 | C24: 1 | D24: 28089.88 | E24: =IFERROR(__xludf.DUMMYFUNCTION("IFNA(FILTER(BUY_AUG!L23:L127, BUY_AUG!H23:H127=B24, BUY_AUG!I23:I127=C24), ""-"")"),17770.0) -> 17770 | F24: =IFERROR(VALUE(E24)*VALUE(D24), "-") -> 4.9915717e+08 | G24: 17800 | H24: =IFERROR(VALUE(G24)*VALUE(D24), "-") -> 499999864 | I24: 0.07 | J24: =IF(OR(I24="-", F24="-", I24="", F24=""), "-", VALUE(I24)%*VALUE(F24)) -> 349410.02 | K24: =IF(OR(H24="-", F24="-", H24="", F24=""), "-", VALUE(H24)-VALUE(F24)) -> 842696.4 | L24: =IF(OR(H24="-", F24="-", J24="-", H24="", F24="", J24=""), "-", VALUE(H24)-VALUE(F24)-VALUE(J24)) -> 493286.38 | N24: =SUMIF(B23:B120, M24, L23:L120) -> 0
A25: =IF(ISBLANK(B25),"",TEXT(B25,"dddd")) -> Monday | B25: 46251 | C25: 2 | E25: =IFERROR(__xludf.DUMMYFUNCTION("IFNA(FILTER(BUY_AUG!L24:L128, BUY_AUG!H24:H128=B25, BUY_AUG!I24:I128=C25), ""-"")"),"-") -> - | F25: =IFERROR(VALUE(E25)*VALUE(D25), "-") -> - | G25: 17800 | H25: =IFERROR(VALUE(G25)*VALUE(D25), "-") -> 0 | I25: 0.07 | J25: =IF(OR(I25="-", F25="-", I25="", F25=""), "-", VALUE(I25)%*VALUE(F25)) -> - | K25: =IF(OR(H25="-", F25="-", H25="", F25=""), "-", VALUE(H25)-VALUE(F25)) -> - | L25: =IF(OR(H25="-", F25="-", J25="-", H25="", F25="", J25=""), "-", VALUE(H25)-VALUE(F25)-VALUE(J25)) -> - | N25: =SUMIF(B24:B121, M25, L24:L121) -> 0

Sheet BUY_SEP
A1: Day | B1: Date | C1: ID | D1: Nominal | E1: Price | F1: Total | G1: >> AVG >> | H1: Date | I1: ID | J1: Nominal | K1: Total | L1: RATE | M1: >> DAILY >> | N1: Date | O1: Nominal | P1: Total | Q1: Rate | R1: Fee (%) | S1: Fee ($) | T1: GrandTotal | U1: Sisa | V1: Sisa (Rp)
A2: =IF(ISBLANK(B2),"",TEXT(B2,"dddd")) -> Tuesday | B2: 46266 | C2: 1 | D2: 29365.07 | E2: 17640 | F2: =D2*E2 -> 5.1799983e+08 | H2: {=INDEX(UNIQUE(B2:C1110), , 1)} -> 46266 | I2: {=INDEX(UNIQUE(B2:C1110), , 2)} -> 1 | J2: =SUMIFS($D$2:$D1110, $B$2:$B1110, H2, $C$2:$C1110, I2) -> 215341.18 | K2: =SUMIFS($F$2:$F1110, $B$2:$B1110, H2, $C$2:$C1110, I2) -> 3796812293 | L2: =IFERROR(K2/J2, 0) -> 17631.613 | N2: {=UNIQUE(H2:H1118)} -> 46266 | O2: =SUMIF($H$2:$H1110, N2, $J$2:$J1110) -> 290649.21 | P2: =SUMIF($H$2:$H1110, N2, $K$2:$K1110) -> 5124818650 | Q2: =IF(N2="", "", IFERROR(P2/O2, "-")) -> 17632.316 | R2: 0 | S2: =O2*$R2% -> 0 | T2: =O2-S2 -> 290649.21 | U2: =IFERROR(ROUND(ABS(VALUE(T2)-VALUE(SUMMARY!C14)), 2), "-") -> 121077.86 | V2: =IFERROR(ROUND(VALUE(U2)*VALUE(Q2), 2), "-") -> 2134883061
A3: =IF(ISBLANK(B3),"",TEXT(B3,"dddd")) -> Tuesday | B3: 46266 | C3: 1 | D3: 113475 | E3: 17625 | F3: =D3*E3 -> 1999996875 | H3: 46266 | I3: 2 | J3: =SUMIFS($D$2:$D1111, $B$2:$B1111, H3, $C$2:$C1111, I3) -> 75308.03 | K3: =SUMIFS($F$2:$F1111, $B$2:$B1111, H3, $C$2:$C1111, I3) -> 1328006358 | L3: =IFERROR(K3/J3, 0) -> 17634.326 | N3: 46267 | O3: =SUMIF($H$2:$H1111, N3, $J$2:$J1111) -> 392877.52 | P3: =SUMIF($H$2:$H1111, N3, $K$2:$K1111) -> 6936581493 | Q3: =IF(N3="", "", IFERROR(P3/O3, "-")) -> 17655.837 | R3: 0 | S3: =O3*$R3% -> 0 | T3: =O3-S3 -> 392877.52 | U3: =IFERROR(ROUND(ABS(VALUE(T3)-VALUE(SUMMARY!C15)), 2), "-") -> 280010.39 | V3: =IFERROR(ROUND(VALUE(U3)*VALUE(Q3), 2), "-") -> 4943817832
A4: =IF(ISBLANK(B4),"",TEXT(B4,"dddd")) -> Tuesday | B4: 46266 | C4: 1 | D4: 15990.92 | E4: 17635 | F4: =D4*E4 -> 2.8199987e+08 | H4: 46267 | I4: 1 | J4: =SUMIFS($D$2:$D1112, $B$2:$B1112, H4, $C$2:$C1112, I4) -> 137635.15 | K4: =SUMIFS($F$2:$F1112, $B$2:$B1112, H4, $C$2:$C1112, I4) -> 2432005082 | L4: =IFERROR(K4/J4, 0) -> 17669.942 | N4: 46268 | O4: =SUMIF($H$2:$H1112, N4, $J$2:$J1112) -> 604148.6 | P4: =SUMIF($H$2:$H1112, N4, $K$2:$K1112) -> 10643627027 | Q4: =IF(N4="", "", IFERROR(P4/O4, "-")) -> 17617.565 | R4: 0 | S4: =O4*$R4% -> 0 | T4: =O4-S4 -> 604148.6 | U4: =IFERROR(ROUND(ABS(VALUE(T4)-VALUE(SUMMARY!C16)), 2), "-") -> 323423.11 | V4: =IFERROR(ROUND(VALUE(U4)*VALUE(Q4), 2), "-") -> 5697927554
A5: =IF(ISBLANK(B5),"",TEXT(B5,"dddd")) -> Tuesday | B5: 46266 | C5: 1 | D5: 1944.28 | E5: 17617 | F5: =D5*E5 -> 34252381 | H5: 46267 | I5: 2 | J5: =SUMIFS($D$2:$D1113, $B$2:$B1113, H5, $C$2:$C1113, I5) -> 56971.53 | K5: =SUMIFS($F$2:$F1113, $B$2:$B1113, H5, $C$2:$C1113, I5) -> 1006196473 | L5: =IFERROR(K5/J5, 0) -> 17661.391 | N5: 46269 | O5: =SUMIF($H$2:$H1113, N5, $J$2:$J1113) -> 719391.82 | P5: =SUMIF($H$2:$H1113, N5, $K$2:$K1113) -> 12633523056 | Q5: =IF(N5="", "", IFERROR(P5/O5, "-")) -> 17561.394 | R5: 0 | S5: =O5*$R5% -> 0 | T5: =O5-S5 -> 719391.82 | U5: =IFERROR(ROUND(ABS(VALUE(T5)-VALUE(SUMMARY!C17)), 2), "-") -> 494909.19 | V5: =IFERROR(ROUND(VALUE(U5)*VALUE(Q5), 2), "-") -> 8691295187
A6: =IF(ISBLANK(B6),"",TEXT(B6,"dddd")) -> Tuesday | B6: 46266 | C6: 1 | D6: 4135.08 | E6: 17645 | F6: =D6*E6 -> 72963487 | H6: 46267 | I6: 3 | J6: =SUMIFS($D$2:$D1114, $B$2:$B1114, H6, $C$2:$C1114, I6) -> 113313.33 | K6: =SUMIFS($F$2:$F1114, $B$2:$B1114, H6, $C$2:$C1114, I6) -> 1999049840 | L6: =IFERROR(K6/J6, 0) -> 17641.789 | N6: 46270 | O6: =SUMIF($H$2:$H1114, N6, $J$2:$J1114) -> 85470.08 | P6: =SUMIF($H$2:$H1114, N6, $K$2:$K1114) -> 1499999904 | Q6: =IF(N6="", "", IFERROR(P6/O6, "-")) -> 17550 | R6: 0 | S6: =O6*$R6% -> 0 | T6: =O6-S6 -> 85470.08 | U6: =IFERROR(ROUND(ABS(VALUE(T6)-VALUE(SUMMARY!C18)), 2), "-") -> 83290.46 | V6: =IFERROR(ROUND(VALUE(U6)*VALUE(Q6), 2), "-") -> 1461747573
A7: =IF(ISBLANK(B7),"",TEXT(B7,"dddd")) -> Tuesday | B7: 46266 | C7: 1 | D7: 50430.83 | E7: 17640 | F7: =D7*E7 -> 8.8959984e+08 | H7: 46267 | I7: 4 | J7: =SUMIFS($D$2:$D1115, $B$2:$B1115, H7, $C$2:$C1115, I7) -> 28325.83 | K7: =SUMIFS($F$2:$F1115, $B$2:$B1115, H7, $C$2:$C1115, I7) -> 4.9978094e+08 | L7: =IFERROR(K7/J7, 0) -> 17644 | N7: 46272 | O7: =SUMIF($H$2:$H1115, N7, $J$2:$J1115) -> 113226.87 | P7: =SUMIF($H$2:$H1115, N7, $K$2:$K1115) -> 1988211089 | Q7: =IF(N7="", "", IFERROR(P7/O7, "-")) -> 17559.534 | R7: 0 | S7: =O7*$R7% -> 0 | T7: =O7-S7 -> 113226.87 | U7: =IFERROR(ROUND(ABS(VALUE(T7)-VALUE(SUMMARY!C19)), 2), "-") -> 14575.74 | V7: =IFERROR(ROUND(VALUE(U7)*VALUE(Q7), 2), "-") -> 2.559432e+08
A8: =IF(ISBLANK(B8),"",TEXT(B8,"dddd")) -> Tuesday | B8: 46266 | C8: 2 | D8: 2053.98 | E8: 17637 | F8: =D8*E8 -> 36226045 | H8: 46267 | I8: 5 | J8: =SUMIFS($D$2:$D1116, $B$2:$B1116, H8, $C$2:$C1116, I8) -> 56631.68 | K8: =SUMIFS($F$2:$F1116, $B$2:$B1116, H8, $C$2:$C1116, I8) -> 999549152 | L8: =IFERROR(K8/J8, 0) -> 17650 | N8: 46273 | O8: =SUMIF($H$2:$H1116, N8, $J$2:$J1116) -> 396691.3 | P8: =SUMIF($H$2:$H1116, N8, $K$2:$K1116) -> 6963384601 | Q8: =IF(N8="", "", IFERROR(P8/O8, "-")) -> 17553.661 | R8: 0 | S8: =O8*$R8% -> 0 | T8: =O8-S8 -> 396691.3 | U8: =IFERROR(ROUND(ABS(VALUE(T8)-VALUE(SUMMARY!C20)), 2), "-") -> 396691.3 | V8: =IFERROR(ROUND(VALUE(U8)*VALUE(Q8), 2), "-") -> 6963384601
A9: =IF(ISBLANK(B9),"",TEXT(B9,"dddd")) -> Tuesday | B9: 46266 | C9: 2 | D9: 5997 | E9: 17637 | F9: =D9*E9 -> 105769089 | H9: 46268 | I9: 1 | J9: =SUMIFS($D$2:$D1117, $B$2:$B1117, H9, $C$2:$C1117, I9) -> 446783.42 | K9: =SUMIFS($F$2:$F1117, $B$2:$B1117, H9, $C$2:$C1117, I9) -> 7875999498 | L9: =IFERROR(K9/J9, 0) -> 17628.227 | N9: 46274 | O9: =SUMIF($H$2:$H1117, N9, $J$2:$J1117) -> 55379.37 | P9: =SUMIF($H$2:$H1117, N9, $K$2:$K1117) -> 966508492 | Q9: =IF(N9="", "", IFERROR(P9/O9, "-")) -> 17452.501 | R9: 0 | S9: =O9*$R9% -> 0 | T9: =O9-S9 -> 55379.37 | U9: =IFERROR(ROUND(ABS(VALUE(T9)-VALUE(SUMMARY!C21)), 2), "-") -> 938.05 | V9: =IFERROR(ROUND(VALUE(U9)*VALUE(Q9), 2), "-") -> 16371318
A10: =IF(ISBLANK(B10),"",TEXT(B10,"dddd")) -> Tuesday | B10: 46266 | C10: 2 | D10: 3998 | E10: 17637 | F10: =D10*E10 -> 70512726 | H10: 46268 | I10: 2 | J10: =SUMIFS($D$2:$D1118, $B$2:$B1118, H10, $C$2:$C1118, I10) -> 157365.18 | K10: =SUMIFS($F$2:$F1118, $B$2:$B1118, H10, $C$2:$C1118, I10) -> 2767627529 | L10: =IFERROR(K10/J10, 0) -> 17587.293 | N10: 46275 | O10: =SUMIF($H$2:$H1118, N10, $J$2:$J1118) -> 144807.59 | P10: =SUMIF($H$2:$H1118, N10, $K$2:$K1118) -> 2531674670 | Q10: =IF(N10="", "", IFERROR(P10/O10, "-")) -> 17483.025 | R10: 0 | S10: =O10*$R10% -> 0 | T10: =O10-S10 -> 144807.59 | U10: =IFERROR(ROUND(ABS(VALUE(T10)-VALUE(SUMMARY!C22)), 2), "-") -> 116717.71 | V10: =IFERROR(ROUND(VALUE(U10)*VALUE(Q10), 2), "-") -> 2040578605
A11: =IF(ISBLANK(B11),"",TEXT(B11,"dddd")) -> Tuesday | B11: 46266 | C11: 2 | D11: 2998.5 | E11: 17637 | F11: =D11*E11 -> 52884544 | H11: 46269 | I11: 1 | J11: =SUMIFS($D$2:$D1119, $B$2:$B1119, H11, $C$2:$C1119, I11) -> 263858.85 | K11: =SUMIFS($F$2:$F1119, $B$2:$B1119, H11, $C$2:$C1119, I11) -> 4635999995 | L11: =IFERROR(K11/J11, 0) -> 17570 | N11: 46276 | O11: =SUMIF($H$2:$H1119, N11, $J$2:$J1119) -> 157987.81 | P11: =SUMIF($H$2:$H1119, N11, $K$2:$K1119) -> 2766536793 | Q11: =IF(N11="", "", IFERROR(P11/O11, "-")) -> 17511.078 | R11: 0 | S11: =O11*$R11% -> 0 | T11: =O11-S11 -> 157987.81 | U11: =IFERROR(ROUND(ABS(VALUE(T11)-VALUE(SUMMARY!C23)), 2), "-") -> 157987.81 | V11: =IFERROR(ROUND(VALUE(U11)*VALUE(Q11), 2), "-") -> 2766536793
A12: =IF(ISBLANK(B12),"",TEXT(B12,"dddd")) -> Tuesday | B12: 46266 | C12: 2 | D12: 2998.5 | E12: 17635 | F12: =D12*E12 -> 52878548 | H12: 46269 | I12: 2 | J12: =SUMIFS($D$2:$D1120, $B$2:$B1120, H12, $C$2:$C1120, I12) -> 130904.95 | K12: =SUMIFS($F$2:$F1120, $B$2:$B1120, H12, $C$2:$C1120, I12) -> 2299999972 | L12: =IFERROR(K12/J12, 0) -> 17570 | N12: 46277 | O12: =SUMIF($H$2:$H1120, N12, $J$2:$J1120) -> 183366.67 | P12: =SUMIF($H$2:$H1120, N12, $K$2:$K1120) -> 3207999892 | Q12: =IF(N12="", "", IFERROR(P12/O12, "-")) -> 17495 | R12: 0 | S12: =O12*$R12% -> 0 | T12: =O12-S12 -> 183366.67 | U12: =IFERROR(ROUND(ABS(VALUE(T12)-VALUE(SUMMARY!C24)), 2), "-") -> 183366.67 | V12: =IFERROR(ROUND(VALUE(U12)*VALUE(Q12), 2), "-") -> 3207999892
A13: =IF(ISBLANK(B13),"",TEXT(B13,"dddd")) -> Tuesday | B13: 46266 | C13: 2 | D13: 569.72 | E13: 17630 | F13: =D13*E13 -> 10044164 | H13: 46269 | I13: 3 | J13: =SUMIFS($D$2:$D1121, $B$2:$B1121, H13, $C$2:$C1121, I13) -> 92655.84 | K13: =SUMIFS($F$2:$F1121, $B$2:$B1121, H13, $C$2:$C1121, I13) -> 1627499830 | L13: =IFERROR(K13/J13, 0) -> 17565 | N13: 46278 | O13: =SUMIF($H$2:$H1121, N13, $J$2:$J1121) -> 341391.81 | P13: =SUMIF($H$2:$H1121, N13, $K$2:$K1121) -> 5970942757 | Q13: =IF(N13="", "", IFERROR(P13/O13, "-")) -> 17490 | R13: 0 | S13: =O13*$R13% -> 0 | T13: =O13-S13 -> 341391.81 | U13: =IFERROR(ROUND(ABS(VALUE(T13)-VALUE(SUMMARY!C25)), 2), "-") -> 341391.81 | V13: =IFERROR(ROUND(VALUE(U13)*VALUE(Q13), 2), "-") -> 5970942757
A14: =IF(ISBLANK(B14),"",TEXT(B14,"dddd")) -> Tuesday | B14: 46266 | C14: 2 | D14: 575.72 | E14: 17626 | F14: =D14*E14 -> 10147641 | H14: 46269 | I14: 4 | J14: =SUMIFS($D$2:$D1122, $B$2:$B1122, H14, $C$2:$C1122, I14) -> 166164.15 | K14: =SUMIFS($F$2:$F1122, $B$2:$B1122, H14, $C$2:$C1122, I14) -> 2915350012 | L14: =IFERROR(K14/J14, 0) -> 17545 | N14: 46279 | O14: =SUMIF($H$2:$H1122, N14, $J$2:$J1122) -> 757237.55 | P14: =SUMIF($H$2:$H1122, N14, $K$2:$K1122) -> 13294416267 | Q14: =IF(N14="", "", IFERROR(P14/O14, "-")) -> 17556.467 | R14: 0 | S14: =O14*$R14% -> 0 | T14: =O14-S14 -> 757237.55 | U14: =IFERROR(ROUND(ABS(VALUE(T14)-VALUE(SUMMARY!C26)), 2), "-") -> 757237.55 | V14: =IFERROR(ROUND(VALUE(U14)*VALUE(Q14), 2), "-") -> 13294416267
... A23: =IF(ISBLANK(B23),"",TEXT(B23,"dddd")) -> Tuesday | B23: 46266 | C23: 2 | D23: 3998 | E23: 17650 | F23: =D23*E23 -> 70564700 | H23: 46274 | I23: 1 | J23: =SUMIFS($D$2:$D1131, $B$2:$B1131, H23, $C$2:$C1131, I23) -> 55379.37 | K23: =SUMIFS($F$2:$F1131, $B$2:$B1131, H23, $C$2:$C1131, I23) -> 966508492 | L23: =IFERROR(K23/J23, 0) -> 17452.501 | N23: 46288 | O23: =SUMIF($H$2:$H1131, N23, $J$2:$J1131) -> 323528.46 | P23: =SUMIF($H$2:$H1131, N23, $K$2:$K1131) -> 5744907945 | Q23: =IF(N23="", "", IFERROR(P23/O23, "-")) -> 17757.04 | R23: 0 | S23: =O23*$R23% -> 0 | T23: =O23-S23 -> 323528.46 | U23: =IFERROR(ROUND(ABS(VALUE(T23)-VALUE(SUMMARY!C35)), 2), "-") -> 323528.46 | V23: =IFERROR(ROUND(VALUE(U23)*VALUE(Q23), 2), "-") -> 5744907945
A24: =IF(ISBLANK(B24),"",TEXT(B24,"dddd")) -> Tuesday | B24: 46266 | C24: 2 | D24: 3998 | E24: 17650 | F24: =D24*E24 -> 70564700 | H24: 46275 | I24: 1 | J24: =SUMIFS($D$2:$D1132, $B$2:$B1132, H24, $C$2:$C1132, I24) -> 57208.23 | K24: =SUMIFS($F$2:$F1132, $B$2:$B1132, H24, $C$2:$C1132, I24) -> 9.9999986e+08 | L24: =IFERROR(K24/J24, 0) -> 17480 | N24: 46289 | O24: =SUMIF($H$2:$H1132, N24, $J$2:$J1132) -> 949290.33 | P24: =SUMIF($H$2:$H1132, N24, $K$2:$K1132) -> 16891685971 | Q24: =IF(N24="", "", IFERROR(P24/O24, "-")) -> 17794.015 | R24: 0 | S24: =O24*$R24% -> 0 | T24: =O24-S24 -> 949290.33 | V24: =IFERROR(ROUND(VALUE(U24)*VALUE(Q24), 2), "-") -> 0
A25: =IF(ISBLANK(B25),"",TEXT(B25,"dddd")) -> Tuesday | B25: 46266 | C25: 2 | D25: 2298.85 | E25: 17650 | F25: =D25*E25 -> 40574702 | H25: 46275 | I25: 2 | J25: =SUMIFS($D$2:$D1133, $B$2:$B1133, H25, $C$2:$C1133, I25) -> 68630.25 | K25: =SUMIFS($F$2:$F1133, $B$2:$B1133, H25, $C$2:$C1133, I25) -> 1199999921 | L25: =IFERROR(K25/J25, 0) -> 17485 | N25: 46290 | O25: =SUMIF($H$2:$H1133, N25, $J$2:$J1133) -> 777902.2 | P25: =SUMIF($H$2:$H1133, N25, $K$2:$K1133) -> 13833723315 | Q25: =IF(N25="", "", IFERROR(P25/O25, "-")) -> 17783.371 | R25: 0 | S25: =O25*$R25% -> 0 | T25: =O25-S25 -> 777902.2 | V25: =IFERROR(ROUND(VALUE(U25)*VALUE(Q25), 2), "-") -> 0
A26: =IF(ISBLANK(B26),"",TEXT(B26,"dddd")) -> Wednesday | B26: 46267 | C26: 1 | D26: 9995 | E26: 17663 | F26: =D26*E26 -> 176541685 | H26: 46275 | I26: 3 | J26: =SUMIFS($D$2:$D1134, $B$2:$B1134, H26, $C$2:$C1134, I26) -> 18969.11 | K26: =SUMIFS($F$2:$F1134, $B$2:$B1134, H26, $C$2:$C1134, I26) -> 3.3167489e+08 | L26: =IFERROR(K26/J26, 0) -> 17485 | N26: 46291 | O26: =SUMIF($H$2:$H1134, N26, $J$2:$J1134) -> 764191.16 | P26: =SUMIF($H$2:$H1134, N26, $K$2:$K1134) -> 13556818757 | Q26: =IF(N26="", "", IFERROR(P26/O26, "-")) -> 17740.088 | R26: 0 | S26: =O26*$R26% -> 0 | T26: =O26-S26 -> 764191.16 | V26: =IFERROR(ROUND(VALUE(U26)*VALUE(Q26), 2), "-") -> 0
A27: =IF(ISBLANK(B27),"",TEXT(B27,"dddd")) -> Wednesday | B27: 46267 | C27: 1 | D27: 9995 | E27: 17666 | F27: =D27*E27 -> 176571670 | H27: 46276 | I27: 1 | J27: =SUMIFS($D$2:$D1135, $B$2:$B1135, H27, $C$2:$C1135, I27) -> 27013.12 | K27: =SUMIFS($F$2:$F1135, $B$2:$B1135, H27, $C$2:$C1135, I27) -> 4.7316997e+08 | L27: =IFERROR(K27/J27, 0) -> 17516.302 | N27: 46292 | O27: =SUMIF($H$2:$H1135, N27, $J$2:$J1135) -> 322691.29 | P27: =SUMIF($H$2:$H1135, N27, $K$2:$K1135) -> 5744895425 | Q27: =IF(N27="", "", IFERROR(P27/O27, "-")) -> 17803.069 | R27: 0 | S27: =O27*$R27% -> 0 | T27: =O27-S27 -> 322691.29 | V27: =IFERROR(ROUND(VALUE(U27)*VALUE(Q27), 2), "-") -> 0
A28: =IF(ISBLANK(B28),"",TEXT(B28,"dddd")) -> Wednesday | B28: 46267 | C28: 1 | D28: 14146 | E28: 17664 | F28: =D28*E28 -> 249874944 | H28: 46276 | I28: 2 | J28: =SUMIFS($D$2:$D1136, $B$2:$B1136, H28, $C$2:$C1136, I28) -> 130974.69 | K28: =SUMIFS($F$2:$F1136, $B$2:$B1136, H28, $C$2:$C1136, I28) -> 2293366822 | L28: =IFERROR(K28/J28, 0) -> 17510 | N28: 46293 | O28: =SUMIF($H$2:$H1136, N28, $J$2:$J1136) -> 327349.11 | P28: =SUMIF($H$2:$H1136, N28, $K$2:$K1136) -> 5848585993 | Q28: =IF(N28="", "", IFERROR(P28/O28, "-")) -> 17866.51 | R28: 0 | S28: =O28*$R28% -> 0 | T28: =O28-S28 -> 327349.11 | V28: =IFERROR(ROUND(VALUE(U28)*VALUE(Q28), 2), "-") -> 0
A29: =IF(ISBLANK(B29),"",TEXT(B29,"dddd")) -> Wednesday | B29: 46267 | C29: 1 | D29: 13843.98 | E29: 17666 | F29: =D29*E29 -> 2.4456775e+08 | H29: 46277 | I29: 1 | J29: =SUMIFS($D$2:$D1137, $B$2:$B1137, H29, $C$2:$C1137, I29) -> 183366.67 | K29: =SUMIFS($F$2:$F1137, $B$2:$B1137, H29, $C$2:$C1137, I29) -> 3207999892 | L29: =IFERROR(K29/J29, 0) -> 17495 | N29: 46294 | O29: =SUMIF($H$2:$H1137, N29, $J$2:$J1137) -> 410698.62 | P29: =SUMIF($H$2:$H1137, N29, $K$2:$K1137) -> 7356223636 | Q29: =IF(N29="", "", IFERROR(P29/O29, "-")) -> 17911.489 | R29: 0 | S29: =O29*$R29% -> 0 | T29: =O29-S29 -> 410698.62 | V29: =IFERROR(ROUND(VALUE(U29)*VALUE(Q29), 2), "-") -> 0
A30: =IF(ISBLANK(B30),"",TEXT(B30,"dddd")) -> Wednesday | B30: 46267 | C30: 1 | D30: 32483.75 | E30: 17675 | F30: =D30*E30 -> 5.7415028e+08 | H30: 46278 | I30: 1 | J30: =SUMIFS($D$2:$D1138, $B$2:$B1138, H30, $C$2:$C1138, I30) -> 57175.52 | K30: =SUMIFS($F$2:$F1138, $B$2:$B1138, H30, $C$2:$C1138, I30) -> 9.9999984e+08 | L30: =IFERROR(K30/J30, 0) -> 17490 | N30: 46295 | O30: =SUMIF($H$2:$H1138, N30, $J$2:$J1138) -> 0 | P30: =SUMIF($H$2:$H1138, N30, $K$2:$K1138) -> 0 | Q30: =IF(N30="", "", IFERROR(P30/O30, "-")) -> - | R30: 0 | S30: =O30*$R30% -> 0 | T30: =O30-S30 -> 0 | V30: =IFERROR(ROUND(VALUE(U30)*VALUE(Q30), 2), "-") -> -
A31: =IF(ISBLANK(B31),"",TEXT(B31,"dddd")) -> Wednesday | B31: 46267 | C31: 1 | D31: 5647.18 | E31: 17675 | F31: =D31*E31 -> 99813906 | H31: 46278 | I31: 2 | J31: =SUMIFS($D$2:$D1139, $B$2:$B1139, H31, $C$2:$C1139, I31) -> 125786.16 | K31: =SUMIFS($F$2:$F1139, $B$2:$B1139, H31, $C$2:$C1139, I31) -> 2199999938 | L31: =IFERROR(K31/J31, 0) -> 17490 | O31: =SUMIF($H$2:$H1139, N31, $J$2:$J1139) -> 0 | P31: =SUMIF($H$2:$H1139, N31, $K$2:$K1139) -> 0 | Q31: =IF(N31="", "", IFERROR(P31/O31, "-")) | R31: 0 | S31: =O31*$R31% -> 0 | T31: =O31-S31 -> 0 | V31: =IFERROR(ROUND(VALUE(U31)*VALUE(Q31), 2), "-") -> 0
A32: =IF(ISBLANK(B32),"",TEXT(B32,"dddd")) -> Wednesday | B32: 46267 | C32: 1 | D32: 19990 | E32: 17671 | F32: =D32*E32 -> 353243290 | H32: 46278 | I32: 3 | J32: =SUMIFS($D$2:$D1140, $B$2:$B1140, H32, $C$2:$C1140, I32) -> 158430.13 | K32: =SUMIFS($F$2:$F1140, $B$2:$B1140, H32, $C$2:$C1140, I32) -> 2770942974 | L32: =IFERROR(K32/J32, 0) -> 17490 | O32: =SUMIF($H$2:$H1140, N32, $J$2:$J1140) -> 0 | P32: =SUMIF($H$2:$H1140, N32, $K$2:$K1140) -> 0 | Q32: =IF(N32="", "", IFERROR(P32/O32, "-")) | R32: 0 | S32: =O32*$R32% -> 0 | T32: =O32-S32 -> 0 | V32: =IFERROR(ROUND(VALUE(U32)*VALUE(Q32), 2), "-") -> 0
A33: =IF(ISBLANK(B33),"",TEXT(B33,"dddd")) -> Wednesday | B33: 46267 | C33: 1 | D33: 5637.18 | E33: 17671 | F33: =D33*E33 -> 99614608 | H33: 46279 | I33: 1 | J33: =SUMIFS($D$2:$D1141, $B$2:$B1141, H33, $C$2:$C1141, I33) -> 142409 | K33: =SUMIFS($F$2:$F1141, $B$2:$B1141, H33, $C$2:$C1141, I33) -> 2499989995 | L33: =IFERROR(K33/J33, 0) -> 17555 | O33: =SUMIF($H$2:$H1141, N33, $J$2:$J1141) -> 0 | P33: =SUMIF($H$2:$H1141, N33, $K$2:$K1141) -> 0 | Q33: =IF(N33="", "", IFERROR(P33/O33, "-")) | R33: 0 | S33: =O33*$R33% -> 0 | T33: =O33-S33 -> 0 | V33: =IFERROR(ROUND(VALUE(U33)*VALUE(Q33), 2), "-") -> 0
A34: =IF(ISBLANK(B34),"",TEXT(B34,"dddd")) -> Wednesday | B34: 46267 | C34: 1 | D34: 13993 | E34: 17671 | F34: =D34*E34 -> 247270303 | H34: 46279 | I34: 2 | J34: =SUMIFS($D$2:$D1142, $B$2:$B1142, H34, $C$2:$C1142, I34) -> 113927.65 | K34: =SUMIFS($F$2:$F1142, $B$2:$B1142, H34, $C$2:$C1142, I34) -> 1999999896 | L34: =IFERROR(K34/J34, 0) -> 17555 | O34: =SUMIF($H$2:$H1142, N34, $J$2:$J1142) -> 0 | P34: =SUMIF($H$2:$H1142, N34, $K$2:$K1142) -> 0 | Q34: =IF(N34="", "", IFERROR(P34/O34, "-")) | R34: 0 | S34: =O34*$R34% -> 0 | T34: =O34-S34 -> 0 | V34: =IFERROR(ROUND(VALUE(U34)*VALUE(Q34), 2), "-") -> 0
A35: =IF(ISBLANK(B35),"",TEXT(B35,"dddd")) -> Wednesday | B35: 46267 | C35: 1 | D35: 5472.27 | E35: 17671 | F35: =D35*E35 -> 96700483 | H35: 46279 | I35: 3 | J35: =SUMIFS($D$2:$D1143, $B$2:$B1143, H35, $C$2:$C1143, I35) -> 147668.85 | K35: =SUMIFS($F$2:$F1143, $B$2:$B1143, H35, $C$2:$C1143, I35) -> 2592326662 | L35: =IFERROR(K35/J35, 0) -> 17555 | O35: =SUMIF($H$2:$H1143, N35, $J$2:$J1143) -> 0 | P35: =SUMIF($H$2:$H1143, N35, $K$2:$K1143) -> 0 | Q35: =IF(N35="", "", IFERROR(P35/O35, "-")) | R35: 0 | S35: =O35*$R35% -> 0 | T35: =O35-S35 -> 0 | V35: =IFERROR(ROUND(VALUE(U35)*VALUE(Q35), 2), "-") -> 0
A36: =IF(ISBLANK(B36),"",TEXT(B36,"dddd")) -> Wednesday | B36: 46267 | C36: 1 | D36: 6431.79 | E36: 17671 | F36: =D36*E36 -> 1.1365616e+08 | H36: 46279 | I36: 4 | J36: =SUMIFS($D$2:$D1144, $B$2:$B1144, H36, $C$2:$C1144, I36) -> 113895.21 | K36: =SUMIFS($F$2:$F1144, $B$2:$B1144, H36, $C$2:$C1144, I36) -> 1999999888 | L36: =IFERROR(K36/J36, 0) -> 17560 | O36: =SUMIF($H$2:$H1144, N36, $J$2:$J1144) -> 0 | P36: =SUMIF($H$2:$H1144, N36, $K$2:$K1144) -> 0 | Q36: =IF(N36="", "", IFERROR(P36/O36, "-")) | R36: 0 | S36: =O36*$R36% -> 0 | T36: =O36-S36 -> 0 | V36: =IFERROR(ROUND(VALUE(U36)*VALUE(Q36), 2), "-") -> 0
A37: =IF(ISBLANK(B37),"",TEXT(B37,"dddd")) -> Wednesday | B37: 46267 | C37: 2 | D37: 4294.49 | E37: 17665 | F37: =D37*E37 -> 75862166 | H37: 46279 | I37: 5 | J37: =SUMIFS($D$2:$D1145, $B$2:$B1145, H37, $C$2:$C1145, I37) -> 108320.04 | K37: =SUMIFS($F$2:$F1145, $B$2:$B1145, H37, $C$2:$C1145, I37) -> 1902099902 | L37: =IFERROR(K37/J37, 0) -> 17560 | O37: =SUMIF($H$2:$H1145, N37, $J$2:$J1145) -> 0 | P37: =SUMIF($H$2:$H1145, N37, $K$2:$K1145) -> 0 | Q37: =IF(N37="", "", IFERROR(P37/O37, "-")) | R37: 0 | S37: =O37*$R37% -> 0 | T37: =O37-S37 -> 0 | V37: =IFERROR(ROUND(VALUE(U37)*VALUE(Q37), 2), "-") -> 0
A38: =IF(ISBLANK(B38),"",TEXT(B38,"dddd")) -> Wednesday | B38: 46267 | C38: 2 | D38: 4997.5 | E38: 17665 | F38: =D38*E38 -> 88280838 | H38: 46279 | I38: 6 | J38: =SUMIFS($D$2:$D1146, $B$2:$B1146, H38, $C$2:$C1146, I38) -> 131016.8 | K38: =SUMIFS($F$2:$F1146, $B$2:$B1146, H38, $C$2:$C1146, I38) -> 2299999924 | L38: =IFERROR(K38/J38, 0) -> 17555 | O38: =SUMIF($H$2:$H1146, N38, $J$2:$J1146) -> 0 | P38: =SUMIF($H$2:$H1146, N38, $K$2:$K1146) -> 0 | Q38: =IF(N38="", "", IFERROR(P38/O38, "-")) | R38: 0 | S38: =O38*$R38% -> 0 | T38: =O38-S38 -> 0 | V38: =IFERROR(ROUND(VALUE(U38)*VALUE(Q38), 2), "-") -> 0
A39: =IF(ISBLANK(B39),"",TEXT(B39,"dddd")) -> Wednesday | B39: 46267 | C39: 2 | D39: 8957.54 | E39: 17665 | F39: =D39*E39 -> 1.5823494e+08 | H39: 46280 | I39: 1 | J39: =SUMIFS($D$2:$D1147, $B$2:$B1147, H39, $C$2:$C1147, I39) -> 130570.53 | K39: =SUMIFS($F$2:$F1147, $B$2:$B1147, H39, $C$2:$C1147, I39) -> 2299999886 | L39: =IFERROR(K39/J39, 0) -> 17615 | O39: =SUMIF($H$2:$H1147, N39, $J$2:$J1147) -> 0 | P39: =SUMIF($H$2:$H1147, N39, $K$2:$K1147) -> 0 | Q39: =IF(N39="", "", IFERROR(P39/O39, "-")) | R39: 0 | S39: =O39*$R39% -> 0 | T39: =O39-S39 -> 0 | V39: =IFERROR(ROUND(VALUE(U39)*VALUE(Q39), 2), "-") -> 0
A40: =IF(ISBLANK(B40),"",TEXT(B40,"dddd")) -> Wednesday | B40: 46267 | C40: 2 | D40: 2703.98 | E40: 17660 | F40: =D40*E40 -> 47752287 | H40: 46281 | I40: 1 | J40: =SUMIFS($D$2:$D1148, $B$2:$B1148, H40, $C$2:$C1148, I40) -> 28420.79 | K40: =SUMIFS($F$2:$F1148, $B$2:$B1148, H40, $C$2:$C1148, I40) -> 4.9969563e+08 | L40: =IFERROR(K40/J40, 0) -> 17582.046 | O40: =SUMIF($H$2:$H1148, N40, $J$2:$J1148) -> 0 | P40: =SUMIF($H$2:$H1148, N40, $K$2:$K1148) -> 0 | Q40: =IF(N40="", "", IFERROR(P40/O40, "-")) | R40: 0 | S40: =O40*$R40% -> 0 | T40: =O40-S40 -> 0 | V40: =IFERROR(ROUND(VALUE(U40)*VALUE(Q40), 2), "-") -> 0
A41: =IF(ISBLANK(B41),"",TEXT(B41,"dddd")) -> Wednesday | B41: 46267 | C41: 2 | D41: 2998.5 | E41: 17656 | F41: =D41*E41 -> 52941516 | H41: 46281 | I41: 2 | J41: =SUMIFS($D$2:$D1149, $B$2:$B1149, H41, $C$2:$C1149, I41) -> 28422.38 | K41: =SUMIFS($F$2:$F1149, $B$2:$B1149, H41, $C$2:$C1149, I41) -> 4.9978429e+08 | L41: =IFERROR(K41/J41, 0) -> 17584.182 | O41: =SUMIF($H$2:$H1149, N41, $J$2:$J1149) -> 0 | P41: =SUMIF($H$2:$H1149, N41, $K$2:$K1149) -> 0 | Q41: =IF(N41="", "", IFERROR(P41/O41, "-")) | R41: 0 | S41: =O41*$R41% -> 0 | T41: =O41-S41 -> 0 | V41: =IFERROR(ROUND(VALUE(U41)*VALUE(Q41), 2), "-") -> 0
A42: =IF(ISBLANK(B42),"",TEXT(B42,"dddd")) -> Wednesday | B42: 46267 | C42: 2 | D42: 1541.73 | E42: 17660 | F42: =D42*E42 -> 27226952 | H42: 46281 | I42: 3 | J42: =SUMIFS($D$2:$D1150, $B$2:$B1150, H42, $C$2:$C1150, I42) -> 26077 | K42: =SUMIFS($F$2:$F1150, $B$2:$B1150, H42, $C$2:$C1150, I42) -> 459998280 | L42: =IFERROR(K42/J42, 0) -> 17640
A43: =IF(ISBLANK(B43),"",TEXT(B43,"dddd")) -> Wednesday | B43: 46267 | C43: 2 | D43: 1975.79 | E43: 17660 | F43: =D43*E43 -> 34892451 | H43: 46281 | I43: 4 | J43: =SUMIFS($D$2:$D1151, $B$2:$B1151, H43, $C$2:$C1151, I43) -> 85397.1 | K43: =SUMIFS($F$2:$F1151, $B$2:$B1151, H43, $C$2:$C1151, I43) -> 1500000062 | L43: =IFERROR(K43/J43, 0) -> 17565
A44: =IF(ISBLANK(B44),"",TEXT(B44,"dddd")) -> Wednesday | B44: 46267 | C44: 2 | D44: 29502 | E44: 17660 | F44: =D44*E44 -> 521005320 | H44: 46281 | I44: 5 | J44: =SUMIFS($D$2:$D1152, $B$2:$B1152, H44, $C$2:$C1152, I44) -> 125284.73 | K44: =SUMIFS($F$2:$F1152, $B$2:$B1152, H44, $C$2:$C1152, I44) -> 2199999859 | L44: =IFERROR(K44/J44, 0) -> 17560
A45: =IF(ISBLANK(B45),"",TEXT(B45,"dddd")) -> Wednesday | B45: 46267 | C45: 3 | D45: 1699.15 | E45: 17647 | F45: =D45*E45 -> 29984900 | H45: 46281 | I45: 6 | J45: =SUMIFS($D$2:$D1153, $B$2:$B1153, H45, $C$2:$C1153, I45) -> 159544.15 | K45: =SUMIFS($F$2:$F1153, $B$2:$B1153, H45, $C$2:$C1153, I45) -> 2799999833 | L45: =IFERROR(K45/J45, 0) -> 17550
A46: =IF(ISBLANK(B46),"",TEXT(B46,"dddd")) -> Wednesday | B46: 46267 | C46: 3 | D46: 24987.5 | E46: 17647 | F46: =D46*E46 -> 4.4095441e+08 | H46: 46282 | I46: 1 | J46: =SUMIFS($D$2:$D1154, $B$2:$B1154, H46, $C$2:$C1154, I46) -> 14739.22 | K46: =SUMIFS($F$2:$F1154, $B$2:$B1154, H46, $C$2:$C1154, I46) -> 2.5999984e+08 | L46: =IFERROR(K46/J46, 0) -> 17640
A47: =IF(ISBLANK(B47),"",TEXT(B47,"dddd")) -> Wednesday | B47: 46267 | C47: 3 | D47: 3998 | E47: 17645 | F47: =D47*E47 -> 70544710 | H47: 46282 | I47: 2 | J47: =SUMIFS($D$2:$D1155, $B$2:$B1155, H47, $C$2:$C1155, I47) -> 85009.91 | K47: =SUMIFS($F$2:$F1155, $B$2:$B1155, H47, $C$2:$C1155, I47) -> 1499999862 | L47: =IFERROR(K47/J47, 0) -> 17645
A48: =IF(ISBLANK(B48),"",TEXT(B48,"dddd")) -> Wednesday | B48: 46267 | C48: 3 | D48: 4997.5 | E48: 17645 | F48: =D48*E48 -> 88180888 | H48: 46282 | I48: 3 | J48: =SUMIFS($D$2:$D1156, $B$2:$B1156, H48, $C$2:$C1156, I48) -> 28368.81 | K48: =SUMIFS($F$2:$F1156, $B$2:$B1156, H48, $C$2:$C1156, I48) -> 4.9977333e+08 | L48: =IFERROR(K48/J48, 0) -> 17617
A49: =IF(ISBLANK(B49),"",TEXT(B49,"dddd")) -> Wednesday | B49: 46267 | C49: 3 | D49: 5665.14 | E49: 17643 | F49: =D49*E49 -> 99950065 | H49: 46282 | I49: 4 | J49: =SUMIFS($D$2:$D1157, $B$2:$B1157, H49, $C$2:$C1157, I49) -> 49975 | K49: =SUMIFS($F$2:$F1157, $B$2:$B1157, H49, $C$2:$C1157, I49) -> 880309625 | L49: =IFERROR(K49/J49, 0) -> 17615
A50: =IF(ISBLANK(B50),"",TEXT(B50,"dddd")) -> Wednesday | B50: 46267 | C50: 3 | D50: 15294.38 | E50: 17643 | F50: =D50*E50 -> 2.6983875e+08 | H50: 46282 | I50: 5 | J50: =SUMIFS($D$2:$D1158, $B$2:$B1158, H50, $C$2:$C1158, I50) -> 42924.57 | K50: =SUMIFS($F$2:$F1158, $B$2:$B1158, H50, $C$2:$C1158, I50) -> 7.559249e+08 | L50: =IFERROR(K50/J50, 0) -> 17610.541
A51: =IF(ISBLANK(B51),"",TEXT(B51,"dddd")) -> Wednesday | B51: 46267 | C51: 3 | D51: 5667.06 | E51: 17637 | F51: =D51*E51 -> 99949937 | H51: 46283 | I51: 1 | J51: =SUMIFS($D$2:$D1159, $B$2:$B1159, H51, $C$2:$C1159, I51) -> 128749.97 | K51: =SUMIFS($F$2:$F1159, $B$2:$B1159, H51, $C$2:$C1159, I51) -> 2267890479 | L51: =IFERROR(K51/J51, 0) -> 17614.687
A52: =IF(ISBLANK(B52),"",TEXT(B52,"dddd")) -> Wednesday | B52: 46267 | C52: 3 | D52: 24987.5 | E52: 17637 | F52: =D52*E52 -> 4.4070454e+08 | H52: 46283 | I52: 2 | J52: =SUMIFS($D$2:$D1160, $B$2:$B1160, H52, $C$2:$C1160, I52) -> 35842.5 | K52: =SUMIFS($F$2:$F1160, $B$2:$B1160, H52, $C$2:$C1160, I52) -> 6.3136564e+08 | L52: =IFERROR(K52/J52, 0) -> 17615
A53: =IF(ISBLANK(B53),"",TEXT(B53,"dddd")) -> Wednesday | B53: 46267 | C53: 3 | D53: 26017.1 | E53: 17640 | F53: =D53*E53 -> 458941644 | H53: 46283 | I53: 3 | J53: =SUMIFS($D$2:$D1161, $B$2:$B1161, H53, $C$2:$C1161, I53) -> 185364.35 | K53: =SUMIFS($F$2:$F1161, $B$2:$B1161, H53, $C$2:$C1161, I53) -> 3266108383 | L53: =IFERROR(K53/J53, 0) -> 17619.938
... A109: =IF(ISBLANK(B109),"",TEXT(B109,"dddd")) -> Monday | B109: 46272 | C109: 1 | D109: 1479.2 | E109: 17565 | F109: =D109*E109 -> 25982148 | H109: 46294 | I109: 2 | J109: =SUMIFS($D$2:$D1217, $B$2:$B1217, H109, $C$2:$C1217, I109) -> 292375.59 | K109: =SUMIFS($F$2:$F1217, $B$2:$B1217, H109, $C$2:$C1217, I109) -> 5234984939 | L109: =IFERROR(K109/J109, 0) -> 17905
A110: =IF(ISBLANK(B110),"",TEXT(B110,"dddd")) -> Monday | B110: 46272 | C110: 1 | D110: 49975 | E110: 17560 | F110: =D110*E110 -> 877561000 | H110: 46295 | J110: =SUMIFS($D$2:$D1218, $B$2:$B1218, H110, $C$2:$C1218, I110) -> 0 | K110: =SUMIFS($F$2:$F1218, $B$2:$B1218, H110, $C$2:$C1218, I110) -> 0 | L110: =IFERROR(K110/J110, 0) -> 0
A111: =IF(ISBLANK(B111),"",TEXT(B111,"dddd")) -> Monday | B111: 46272 | C111: 1 | D111: 6139.53 | E111: 17560 | F111: =D111*E111 -> 1.0781015e+08 | J111: =SUMIFS($D$2:$D1219, $B$2:$B1219, H111, $C$2:$C1219, I111) -> 0 | K111: =SUMIFS($F$2:$F1219, $B$2:$B1219, H111, $C$2:$C1219, I111) -> 0 | L111: =IFERROR(K111/J111, 0) -> 0
A112: =IF(ISBLANK(B112),"",TEXT(B112,"dddd")) -> Monday | B112: 46272 | C112: 1 | D112: 26208.89 | E112: 17555 | F112: =D112*E112 -> 460097064 | J112: =SUMIFS($D$2:$D1220, $B$2:$B1220, H112, $C$2:$C1220, I112) -> 0 | K112: =SUMIFS($F$2:$F1220, $B$2:$B1220, H112, $C$2:$C1220, I112) -> 0 | L112: =IFERROR(K112/J112, 0) -> 0
A113: =IF(ISBLANK(B113),"",TEXT(B113,"dddd")) -> Tuesday | B113: 46273 | C113: 1 | D113: 65988.83 | E113: 17556 | F113: =D113*E113 -> 1158499899 | J113: =SUMIFS($D$2:$D1221, $B$2:$B1221, H113, $C$2:$C1221, I113) -> 0 | K113: =SUMIFS($F$2:$F1221, $B$2:$B1221, H113, $C$2:$C1221, I113) -> 0 | L113: =IFERROR(K113/J113, 0) -> 0
A114: =IF(ISBLANK(B114),"",TEXT(B114,"dddd")) -> Tuesday | B114: 46273 | C114: 2 | D114: 113921.16 | E114: 17556 | F114: =D114*E114 -> 1999999885 | J114: =SUMIFS($D$2:$D1222, $B$2:$B1222, H114, $C$2:$C1222, I114) -> 0 | K114: =SUMIFS($F$2:$F1222, $B$2:$B1222, H114, $C$2:$C1222, I114) -> 0 | L114: =IFERROR(K114/J114, 0) -> 0
A115: =IF(ISBLANK(B115),"",TEXT(B115,"dddd")) -> Tuesday | B115: 46273 | C115: 3 | D115: 28480.29 | E115: 17556 | F115: =D115*E115 -> 4.9999997e+08 | J115: =SUMIFS($D$2:$D1223, $B$2:$B1223, H115, $C$2:$C1223, I115) -> 0 | K115: =SUMIFS($F$2:$F1223, $B$2:$B1223, H115, $C$2:$C1223, I115) -> 0 | L115: =IFERROR(K115/J115, 0) -> 0
A116: =IF(ISBLANK(B116),"",TEXT(B116,"dddd")) -> Tuesday | B116: 46273 | C116: 4 | D116: 131345.32 | E116: 17557 | F116: =D116*E116 -> 2306029783 | J116: =SUMIFS($D$2:$D1224, $B$2:$B1224, H116, $C$2:$C1224, I116) -> 0 | K116: =SUMIFS($F$2:$F1224, $B$2:$B1224, H116, $C$2:$C1224, I116) -> 0 | L116: =IFERROR(K116/J116, 0) -> 0
A117: =IF(ISBLANK(B117),"",TEXT(B117,"dddd")) -> Tuesday | B117: 46273 | C117: 5 | D117: 4960.48 | E117: 17530 | F117: =D117*E117 -> 86957214 | J117: =SUMIFS($D$2:$D1225, $B$2:$B1225, H117, $C$2:$C1225, I117) -> 0 | K117: =SUMIFS($F$2:$F1225, $B$2:$B1225, H117, $C$2:$C1225, I117) -> 0 | L117: =IFERROR(K117/J117, 0) -> 0
A118: =IF(ISBLANK(B118),"",TEXT(B118,"dddd")) -> Tuesday | B118: 46273 | C118: 5 | D118: 2998.5 | E118: 17532 | F118: =D118*E118 -> 52569702 | J118: =SUMIFS($D$2:$D1226, $B$2:$B1226, H118, $C$2:$C1226, I118) -> 0 | K118: =SUMIFS($F$2:$F1226, $B$2:$B1226, H118, $C$2:$C1226, I118) -> 0 | L118: =IFERROR(K118/J118, 0) -> 0
A119: =IF(ISBLANK(B119),"",TEXT(B119,"dddd")) -> Tuesday | B119: 46273 | C119: 5 | D119: 1710.33 | E119: 17532 | F119: =D119*E119 -> 29985506 | J119: =SUMIFS($D$2:$D1227, $B$2:$B1227, H119, $C$2:$C1227, I119) -> 0 | K119: =SUMIFS($F$2:$F1227, $B$2:$B1227, H119, $C$2:$C1227, I119) -> 0 | L119: =IFERROR(K119/J119, 0) -> 0
A120: =IF(ISBLANK(B120),"",TEXT(B120,"dddd")) -> Tuesday | B120: 46273 | C120: 5 | D120: 2798.6 | E120: 17540 | F120: =D120*E120 -> 49087444 | J120: =SUMIFS($D$2:$D1228, $B$2:$B1228, H120, $C$2:$C1228, I120) -> 0 | K120: =SUMIFS($F$2:$F1228, $B$2:$B1228, H120, $C$2:$C1228, I120) -> 0 | L120: =IFERROR(K120/J120, 0) -> 0
A121: =IF(ISBLANK(B121),"",TEXT(B121,"dddd")) -> Tuesday | B121: 46273 | C121: 5 | D121: 2280.01 | E121: 17535 | F121: =D121*E121 -> 39979975 | J121: =SUMIFS($D$2:$D1229, $B$2:$B1229, H121, $C$2:$C1229, I121) -> 0 | K121: =SUMIFS($F$2:$F1229, $B$2:$B1229, H121, $C$2:$C1229, I121) -> 0 | L121: =IFERROR(K121/J121, 0) -> 0
A122: =IF(ISBLANK(B122),"",TEXT(B122,"dddd")) -> Tuesday | B122: 46273 | C122: 5 | D122: 1618.64 | E122: 17530 | F122: =D122*E122 -> 28374759 | J122: =SUMIFS($D$2:$D1230, $B$2:$B1230, H122, $C$2:$C1230, I122) -> 0 | K122: =SUMIFS($F$2:$F1230, $B$2:$B1230, H122, $C$2:$C1230, I122) -> 0 | L122: =IFERROR(K122/J122, 0) -> 0
... A200: =IF(ISBLANK(B200),"",TEXT(B200,"dddd")) -> Friday | B200: 46283 | C200: 6 | D200: 9106.45 | E200: 17617 | F200: =D200*E200 -> 1.6042833e+08 | J200: =SUMIFS($D$2:$D1308, $B$2:$B1308, H200, $C$2:$C1308, I200) -> 0 | K200: =SUMIFS($F$2:$F1308, $B$2:$B1308, H200, $C$2:$C1308, I200) -> 0 | L200: =IFERROR(K200/J200, 0) -> 0
A201: =IF(ISBLANK(B201),"",TEXT(B201,"dddd")) -> Friday | B201: 46283 | C201: 6 | D201: 9478.06 | E201: 17618 | F201: =D201*E201 -> 1.6698446e+08
A202: =IF(ISBLANK(B202),"",TEXT(B202,"dddd")) -> Friday | B202: 46283 | C202: 6 | D202: 6196.9 | E202: 17618 | F202: =D202*E202 -> 1.0917698e+08
A203: =IF(ISBLANK(B203),"",TEXT(B203,"dddd")) -> Friday | B203: 46283 | C203: 6 | D203: 3971.22 | E203: 17618 | F203: =D203*E203 -> 69964954
A204: =IF(ISBLANK(B204),"",TEXT(B204,"dddd")) -> Friday | B204: 46283 | C204: 6 | D204: 4628.06 | E204: 17618 | F204: =D204*E204 -> 81537161
A205: =IF(ISBLANK(B205),"",TEXT(B205,"dddd")) -> Friday | B205: 46283 | C205: 6 | D205: 15838.64 | E205: 17618 | F205: =D205*E205 -> 2.7904516e+08
A206: =IF(ISBLANK(B206),"",TEXT(B206,"dddd")) -> Friday | B206: 46283 | C206: 6 | D206: 4997.5 | E206: 17618 | F206: =D206*E206 -> 88045955
A207: =IF(ISBLANK(B207),"",TEXT(B207,"dddd")) -> Friday | B207: 46283 | C207: 6 | D207: 6996.5 | E207: 17620 | F207: =D207*E207 -> 123278330
A208: =IF(ISBLANK(B208),"",TEXT(B208,"dddd")) -> Friday | B208: 46283 | C208: 6 | D208: 2498.75 | E208: 17620 | F208: =D208*E208 -> 44027975
A209: =IF(ISBLANK(B209),"",TEXT(B209,"dddd")) -> Friday | B209: 46283 | C209: 6 | D209: 4997.5 | E209: 17620 | F209: =D209*E209 -> 88055950
A210: =IF(ISBLANK(B210),"",TEXT(B210,"dddd")) -> Friday | B210: 46283 | C210: 6 | D210: 9995 | E210: 17626 | F210: =D210*E210 -> 176171870
A211: =IF(ISBLANK(B211),"",TEXT(B211,"dddd")) -> Friday | B211: 46283 | C211: 6 | D211: 2498.75 | E211: 17626 | F211: =D211*E211 -> 44042968
A212: =IF(ISBLANK(B212),"",TEXT(B212,"dddd")) -> Friday | B212: 46283 | C212: 6 | D212: 2998.5 | E212: 17626 | F212: =D212*E212 -> 52851561
... A353: =IF(ISBLANK(B353),"",TEXT(B353,"dddd")) -> Tuesday | B353: 46294 | C353: 2 | D353: 292375.59 | E353: 17905 | F353: =D353*E353 -> 5234984939
A354: =IF(ISBLANK(B354),"",TEXT(B354,"dddd")) -> Wednesday | B354: 46295 | F354: =D354*E354 -> 0
A355: =IF(ISBLANK(B355),"",TEXT(B355,"dddd")) -> Wednesday | B355: 46295 | F355: =D355*E355 -> 0
A356: =IF(ISBLANK(B356),"",TEXT(B356,"dddd")) -> Wednesday | B356: 46295 | F356: =D356*E356 -> 0
A357: =IF(ISBLANK(B357),"",TEXT(B357,"dddd")) -> Wednesday | B357: 46295 | F357: =D357*E357 -> 0
A358: =IF(ISBLANK(B358),"",TEXT(B358,"dddd")) -> Wednesday | B358: 46295 | F358: =D358*E358 -> 0
A359: =IF(ISBLANK(B359),"",TEXT(B359,"dddd")) -> Wednesday | B359: 46295 | F359: =D359*E359 -> 0
A360: =IF(ISBLANK(B360),"",TEXT(B360,"dddd")) -> Wednesday | B360: 46295 | F360: =D360*E360 -> 0
A361: =IF(ISBLANK(B361),"",TEXT(B361,"dddd")) -> Wednesday | B361: 46295 | F361: =D361*E361 -> 0
A362: =IF(ISBLANK(B362),"",TEXT(B362,"dddd")) -> Wednesday | B362: 46295 | F362: =D362*E362 -> 0
A363: =IF(ISBLANK(B363),"",TEXT(B363,"dddd")) -> Wednesday | B363: 46295 | F363: =D363*E363 -> 0
A364: =IF(ISBLANK(B364),"",TEXT(B364,"dddd")) -> Wednesday | B364: 46295 | F364: =D364*E364 -> 0
A365: =IF(ISBLANK(B365),"",TEXT(B365,"dddd")) -> Wednesday | B365: 46295 | F365: =D365*E365 -> 0
... A464: =IF(ISBLANK(B464),"",TEXT(B464,"dddd")) -> Wednesday | B464: 46295 | F464: =D464*E464 -> 0

Sheet SEP
A1: SEPTEMBER | D1: EXCHANGE | M1: SUMMARY
A2: Day | B2: Date | C2: ID | D2: NOMINAL | E2: RATE BUY | F2: BUY | G2: RATE SELL | H2: SELL | I2: FEE (%) | J2: FEE (RP) | K2: OMSET | L2: PROFIT | M2: DATE | N2: TOTAL (DAILY)
A3: =IF(ISBLANK(B3),"",TEXT(B3,"dddd")) -> Tuesday | B3: 46266 | C3: 1 | D3: 49908.72 | E3: =IFERROR(__xludf.DUMMYFUNCTION("IFNA(FILTER(BUY_SEP!$L$2:$L$1218, BUY_SEP!$H$2:$H$1218=B3, BUY_SEP!$I$2:$I$1218=C3), ""-"")"),17631.61273918904) -> 17631.613 | F3: =IFERROR(VALUE(E3)*VALUE(D3), "-") -> 8.7997122e+08 | G3: 17675 | H3: =IFERROR(VALUE(G3)*VALUE(D3), "-") -> 882136626 | I3: 0 | J3: =IF(OR(I3="-", F3="-", I3="", F3=""), "-", VALUE(I3)%*VALUE(F3)) -> 0 | K3: =IF(OR(H3="-", F3="-", H3="", F3=""), "-", VALUE(H3)-VALUE(F3)) -> 2165402.7 | L3: =IF(OR(H3="-", F3="-", J3="-", H3="", F3="", J3=""), "-", VALUE(H3)-VALUE(F3)-VALUE(J3)) -> 2165402.7 | M3: {=UNIQUE(B3:B101)} -> 46266 | N3: =SUMIF(B$3:B$900, M3, L$3:L$900) -> 8103901.2
A4: =IF(ISBLANK(B4),"",TEXT(B4,"dddd")) -> Tuesday | B4: 46266 | C4: 1 | D4: 63245.45 | E4: =IFERROR(__xludf.DUMMYFUNCTION("IFNA(FILTER(BUY_SEP!$L$2:$L$1218, BUY_SEP!$H$2:$H$1218=B4, BUY_SEP!$I$2:$I$1218=C4), ""-"")"),17631.61273918904) -> 17631.613 | F4: =IFERROR(VALUE(E4)*VALUE(D4), "-") -> 1115119282 | G4: 17675 | H4: =IFERROR(VALUE(G4)*VALUE(D4), "-") -> 1117863329 | I4: 0 | J4: =IF(OR(I4="-", F4="-", I4="", F4=""), "-", VALUE(I4)%*VALUE(F4)) -> 0 | K4: =IF(OR(H4="-", F4="-", H4="", F4=""), "-", VALUE(H4)-VALUE(F4)) -> 2744046.8 | L4: =IF(OR(H4="-", F4="-", J4="-", H4="", F4="", J4=""), "-", VALUE(H4)-VALUE(F4)-VALUE(J4)) -> 2744046.8 | M4: 46267 | N4: =SUMIF(B$3:B$900, M4, L$3:L$900) -> 12366953
A5: =IF(ISBLANK(B5),"",TEXT(B5,"dddd")) -> Tuesday | B5: 46266 | C5: 1 | D5: 28312.57 | E5: =IFERROR(__xludf.DUMMYFUNCTION("IFNA(FILTER(BUY_SEP!$L$2:$L$1218, BUY_SEP!$H$2:$H$1218=B5, BUY_SEP!$I$2:$I$1218=C5), ""-"")"),17631.61273918904) -> 17631.613 | F5: =IFERROR(VALUE(E5)*VALUE(D5), "-") -> 4.9919627e+08 | G5: 17660 | H5: =IFERROR(VALUE(G5)*VALUE(D5), "-") -> 4.9999999e+08 | I5: 0 | J5: =IF(OR(I5="-", F5="-", I5="", F5=""), "-", VALUE(I5)%*VALUE(F5)) -> 0 | K5: =IF(OR(H5="-", F5="-", H5="", F5=""), "-", VALUE(H5)-VALUE(F5)) -> 803716.31 | L5: =IF(OR(H5="-", F5="-", J5="-", H5="", F5="", J5=""), "-", VALUE(H5)-VALUE(F5)-VALUE(J5)) -> 803716.31 | M5: 46268 | N5: =SUMIF(B$3:B$900, M5, L$3:L$900) -> 19989582
A6: =IF(ISBLANK(B6),"",TEXT(B6,"dddd")) -> Tuesday | B6: 46266 | C6: 1 | D6: 30000 | E6: =IFERROR(__xludf.DUMMYFUNCTION("IFNA(FILTER(BUY_SEP!$L$2:$L$1218, BUY_SEP!$H$2:$H$1218=B6, BUY_SEP!$I$2:$I$1218=C6), ""-"")"),17631.61273918904) -> 17631.613 | F6: =IFERROR(VALUE(E6)*VALUE(D6), "-") -> 5.2894838e+08 | G6: 17665 | H6: =IFERROR(VALUE(G6)*VALUE(D6), "-") -> 529950000 | I6: 0 | J6: =IF(OR(I6="-", F6="-", I6="", F6=""), "-", VALUE(I6)%*VALUE(F6)) -> 0 | K6: =IF(OR(H6="-", F6="-", H6="", F6=""), "-", VALUE(H6)-VALUE(F6)) -> 1001617.8 | L6: =IF(OR(H6="-", F6="-", J6="-", H6="", F6="", J6=""), "-", VALUE(H6)-VALUE(F6)-VALUE(J6)) -> 1001617.8 | M6: 46269 | N6: =SUMIF(B$3:B$900, M6, L$3:L$900) -> 25595749
A7: =IF(ISBLANK(B7),"",TEXT(B7,"dddd")) -> Tuesday | B7: 46266 | C7: 1 | D7: 3401.93 | E7: =IFERROR(__xludf.DUMMYFUNCTION("IFNA(FILTER(BUY_SEP!$L$2:$L$1218, BUY_SEP!$H$2:$H$1218=B7, BUY_SEP!$I$2:$I$1218=C7), ""-"")"),17631.61273918904) -> 17631.613 | F7: =IFERROR(VALUE(E7)*VALUE(D7), "-") -> 59981512 | G7: 17637 | H7: =IFERROR(VALUE(G7)*VALUE(D7), "-") -> 59999839 | I7: 0.05 | J7: =IF(OR(I7="-", F7="-", I7="", F7=""), "-", VALUE(I7)%*VALUE(F7)) -> 29990.756 | K7: =IF(OR(H7="-", F7="-", H7="", F7=""), "-", VALUE(H7)-VALUE(F7)) -> 18327.084 | L7: =IF(OR(H7="-", F7="-", J7="-", H7="", F7="", J7=""), "-", VALUE(H7)-VALUE(F7)-VALUE(J7)) -> -11663.672 | M7: 46270 | N7: =SUMIF(B$3:B$900, M7, L$3:L$900) -> 2133712.5
A8: =IF(ISBLANK(B8),"",TEXT(B8,"dddd")) -> Tuesday | B8: 46266 | C8: 1 | D8: 15126.62 | E8: =IFERROR(__xludf.DUMMYFUNCTION("IFNA(FILTER(BUY_SEP!$L$2:$L$1218, BUY_SEP!$H$2:$H$1218=B8, BUY_SEP!$I$2:$I$1218=C8), ""-"")"),17631.61273918904) -> 17631.613 | F8: =IFERROR(VALUE(E8)*VALUE(D8), "-") -> 2.6670671e+08 | G8: 17651 | H8: =IFERROR(VALUE(G8)*VALUE(D8), "-") -> 2.6699997e+08 | I8: 0.05 | J8: =IF(OR(I8="-", F8="-", I8="", F8=""), "-", VALUE(I8)%*VALUE(F8)) -> 133353.35 | K8: =IF(OR(H8="-", F8="-", H8="", F8=""), "-", VALUE(H8)-VALUE(F8)) -> 293263.73 | L8: =IF(OR(H8="-", F8="-", J8="-", H8="", F8="", J8=""), "-", VALUE(H8)-VALUE(F8)-VALUE(J8)) -> 159910.37 | M8: 46272 | N8: =SUMIF(B$3:B$900, M8, L$3:L$900) -> 1613297.4
A9: =IF(ISBLANK(B9),"",TEXT(B9,"dddd")) -> Tuesday | B9: 46266 | C9: 2 | D9: 73612.68 | E9: =IFERROR(__xludf.DUMMYFUNCTION("IFNA(FILTER(BUY_SEP!$L$2:$L$1218, BUY_SEP!$H$2:$H$1218=B9, BUY_SEP!$I$2:$I$1218=C9), ""-"")"),17634.32608288917) -> 17634.326 | F9: =IFERROR(VALUE(E9)*VALUE(D9), "-") -> 1298110003 | G9: 17660 | H9: =IFERROR(VALUE(G9)*VALUE(D9), "-") -> 1299999929 | I9: 0.05 | J9: =IF(OR(I9="-", F9="-", I9="", F9=""), "-", VALUE(I9)%*VALUE(F9)) -> 649055 | K9: =IF(OR(H9="-", F9="-", H9="", F9=""), "-", VALUE(H9)-VALUE(F9)) -> 1889925.8 | L9: =IF(OR(H9="-", F9="-", J9="-", H9="", F9="", J9=""), "-", VALUE(H9)-VALUE(F9)-VALUE(J9)) -> 1240870.8 | M9: 46273 | N9: =SUMIF(B$3:B$900, M9, L$3:L$900) -> 6771268.6
A10: =IF(ISBLANK(B10),"",TEXT(B10,"dddd")) -> Wednesday | B10: 46267 | C10: 1 | D10: 45209.01 | E10: =IFERROR(__xludf.DUMMYFUNCTION("IFNA(FILTER(BUY_SEP!$L$2:$L$1218, BUY_SEP!$H$2:$H$1218=B10, BUY_SEP!$I$2:$I$1218=C10), ""-"")"),17669.94174431459) -> 17669.942 | F10: =IFERROR(VALUE(E10)*VALUE(D10), "-") -> 798840573 | G10: 17695 | H10: =IFERROR(VALUE(G10)*VALUE(D10), "-") -> 799973432 | I10: 0.05 | J10: =IF(OR(I10="-", F10="-", I10="", F10=""), "-", VALUE(I10)%*VALUE(F10)) -> 399420.29 | K10: =IF(OR(H10="-", F10="-", H10="", F10=""), "-", VALUE(H10)-VALUE(F10)) -> 1132858.9 | L10: =IF(OR(H10="-", F10="-", J10="-", H10="", F10="", J10=""), "-", VALUE(H10)-VALUE(F10)-VALUE(J10)) -> 733438.65 | M10: 46274 | N10: =SUMIF(B$3:B$900, M10, L$3:L$900) -> 1073974.6
A11: =IF(ISBLANK(B11),"",TEXT(B11,"dddd")) -> Wednesday | B11: 46267 | C11: 1 | D11: 69511.16 | E11: =IFERROR(__xludf.DUMMYFUNCTION("IFNA(FILTER(BUY_SEP!$L$2:$L$1218, BUY_SEP!$H$2:$H$1218=B11, BUY_SEP!$I$2:$I$1218=C11), ""-"")"),17669.94174431459) -> 17669.942 | F11: =IFERROR(VALUE(E11)*VALUE(D11), "-") -> 1228258148 | G11: 17700 | H11: =IFERROR(VALUE(G11)*VALUE(D11), "-") -> 1230347532 | I11: 0.05 | J11: =IF(OR(I11="-", F11="-", I11="", F11=""), "-", VALUE(I11)%*VALUE(F11)) -> 614129.07 | K11: =IF(OR(H11="-", F11="-", H11="", F11=""), "-", VALUE(H11)-VALUE(F11)) -> 2089384.2 | L11: =IF(OR(H11="-", F11="-", J11="-", H11="", F11="", J11=""), "-", VALUE(H11)-VALUE(F11)-VALUE(J11)) -> 1475255.1 | M11: 46275 | N11: =SUMIF(B$3:B$900, M11, L$3:L$900) -> 2455721
A12: =IF(ISBLANK(B12),"",TEXT(B12,"dddd")) -> Wednesday | B12: 46267 | C12: 1 | D12: 56983.05 | E12: =IFERROR(__xludf.DUMMYFUNCTION("IFNA(FILTER(BUY_SEP!$L$2:$L$1218, BUY_SEP!$H$2:$H$1218=B12, BUY_SEP!$I$2:$I$1218=C12), ""-"")"),17669.94174431459) -> 17669.942 | F12: =IFERROR(VALUE(E12)*VALUE(D12), "-") -> 1006887174 | G12: 17700 | H12: =IFERROR(VALUE(G12)*VALUE(D12), "-") -> 1008599985 | I12: 0.05 | J12: =IF(OR(I12="-", F12="-", I12="", F12=""), "-", VALUE(I12)%*VALUE(F12)) -> 503443.59 | K12: =IF(OR(H12="-", F12="-", H12="", F12=""), "-", VALUE(H12)-VALUE(F12)) -> 1712811.1 | L12: =IF(OR(H12="-", F12="-", J12="-", H12="", F12="", J12=""), "-", VALUE(H12)-VALUE(F12)-VALUE(J12)) -> 1209367.5 | M12: 46276 | N12: =SUMIF(B$3:B$900, M12, L$3:L$900) -> 2368814.1
A13: =IF(ISBLANK(B13),"",TEXT(B13,"dddd")) -> Wednesday | B13: 46267 | C13: 2 | D13: 56497.17 | E13: =IFERROR(__xludf.DUMMYFUNCTION("IFNA(FILTER(BUY_SEP!$L$2:$L$1218, BUY_SEP!$H$2:$H$1218=B13, BUY_SEP!$I$2:$I$1218=C13), ""-"")"),17661.391109734985) -> 17661.391 | F13: =IFERROR(VALUE(E13)*VALUE(D13), "-") -> 997818616 | G13: 17700 | H13: =IFERROR(VALUE(G13)*VALUE(D13), "-") -> 999999909 | I13: 0.05 | J13: =IF(OR(I13="-", F13="-", I13="", F13=""), "-", VALUE(I13)%*VALUE(F13)) -> 498909.31 | K13: =IF(OR(H13="-", F13="-", H13="", F13=""), "-", VALUE(H13)-VALUE(F13)) -> 2181293 | L13: =IF(OR(H13="-", F13="-", J13="-", H13="", F13="", J13=""), "-", VALUE(H13)-VALUE(F13)-VALUE(J13)) -> 1682383.7 | M13: 46277 | N13: =SUMIF(B$3:B$900, M13, L$3:L$900) -> 3663145.8
A14: =IF(ISBLANK(B14),"",TEXT(B14,"dddd")) -> Wednesday | B14: 46267 | C14: 3 | D14: 113058.22 | E14: =IFERROR(__xludf.DUMMYFUNCTION("IFNA(FILTER(BUY_SEP!$L$2:$L$1218, BUY_SEP!$H$2:$H$1218=B14, BUY_SEP!$I$2:$I$1218=C14), ""-"")"),17641.78883570009) -> 17641.789 | F14: =IFERROR(VALUE(E14)*VALUE(D14), "-") -> 1994549243 | G14: 17690 | H14: =IFERROR(VALUE(G14)*VALUE(D14), "-") -> 1999999912 | I14: 0.05 | J14: =IF(OR(I14="-", F14="-", I14="", F14=""), "-", VALUE(I14)%*VALUE(F14)) -> 997274.62 | K14: =IF(OR(H14="-", F14="-", H14="", F14=""), "-", VALUE(H14)-VALUE(F14)) -> 5450668.4 | L14: =IF(OR(H14="-", F14="-", J14="-", H14="", F14="", J14=""), "-", VALUE(H14)-VALUE(F14)-VALUE(J14)) -> 4453393.8 | M14: 46278 | N14: =SUMIF(B$3:B$900, M14, L$3:L$900) -> 7167687
A15: =IF(ISBLANK(B15),"",TEXT(B15,"dddd")) -> Wednesday | B15: 46267 | C15: 4 | D15: 28264.55 | E15: =IFERROR(__xludf.DUMMYFUNCTION("IFNA(FILTER(BUY_SEP!$L$2:$L$1218, BUY_SEP!$H$2:$H$1218=B15, BUY_SEP!$I$2:$I$1218=C15), ""-"")"),17644.0) -> 17644 | F15: =IFERROR(VALUE(E15)*VALUE(D15), "-") -> 4.9869972e+08 | G15: 17690 | H15: =IFERROR(VALUE(G15)*VALUE(D15), "-") -> 4.9999989e+08 | I15: 0.05 | J15: =IF(OR(I15="-", F15="-", I15="", F15=""), "-", VALUE(I15)%*VALUE(F15)) -> 249349.86 | K15: =IF(OR(H15="-", F15="-", H15="", F15=""), "-", VALUE(H15)-VALUE(F15)) -> 1300169.3 | L15: =IF(OR(H15="-", F15="-", J15="-", H15="", F15="", J15=""), "-", VALUE(H15)-VALUE(F15)-VALUE(J15)) -> 1050819.4 | M15: 46279 | N15: =SUMIF(B$3:B$900, M15, L$3:L$900) -> 10436185
A16: =IF(ISBLANK(B16),"",TEXT(B16,"dddd")) -> Wednesday | B16: 46267 | C16: 5 | D16: 56529.11 | E16: =IFERROR(__xludf.DUMMYFUNCTION("IFNA(FILTER(BUY_SEP!$L$2:$L$1218, BUY_SEP!$H$2:$H$1218=B16, BUY_SEP!$I$2:$I$1218=C16), ""-"")"),17650.0) -> 17650 | F16: =IFERROR(VALUE(E16)*VALUE(D16), "-") -> 9.9773879e+08 | G16: 17690 | H16: =IFERROR(VALUE(G16)*VALUE(D16), "-") -> 9.9999996e+08 | I16: 0.05 | J16: =IF(OR(I16="-", F16="-", I16="", F16=""), "-", VALUE(I16)%*VALUE(F16)) -> 498869.4 | K16: =IF(OR(H16="-", F16="-", H16="", F16=""), "-", VALUE(H16)-VALUE(F16)) -> 2261164.4 | L16: =IF(OR(H16="-", F16="-", J16="-", H16="", F16="", J16=""), "-", VALUE(H16)-VALUE(F16)-VALUE(J16)) -> 1762295 | M16: 46280 | N16: =SUMIF(B$3:B$900, M16, L$3:L$900) -> 1304964.5
A17: =IF(ISBLANK(B17),"",TEXT(B17,"dddd")) -> Thursday | B17: 46268 | C17: 1 | D17: 141522.78 | E17: =IFERROR(__xludf.DUMMYFUNCTION("IFNA(FILTER(BUY_SEP!$L$2:$L$1218, BUY_SEP!$H$2:$H$1218=B17, BUY_SEP!$I$2:$I$1218=C17), ""-"")"),17628.226888880523) -> 17628.227 | F17: =IFERROR(VALUE(E17)*VALUE(D17), "-") -> 2494795676 | G17: 17665 | H17: =IFERROR(VALUE(G17)*VALUE(D17), "-") -> 2499999909 | I17: 0 | J17: =IF(OR(I17="-", F17="-", I17="", F17=""), "-", VALUE(I17)%*VALUE(F17)) -> 0 | K17: =IF(OR(H17="-", F17="-", H17="", F17=""), "-", VALUE(H17)-VALUE(F17)) -> 5204232.9 | L17: =IF(OR(H17="-", F17="-", J17="-", H17="", F17="", J17=""), "-", VALUE(H17)-VALUE(F17)-VALUE(J17)) -> 5204232.9 | M17: 46281 | N17: =SUMIF(B$3:B$900, M17, L$3:L$900) -> 13974642
A18: =IF(ISBLANK(B18),"",TEXT(B18,"dddd")) -> Thursday | B18: 46268 | C18: 1 | D18: 33172.94 | E18: =IFERROR(__xludf.DUMMYFUNCTION("IFNA(FILTER(BUY_SEP!$L$2:$L$1218, BUY_SEP!$H$2:$H$1218=B18, BUY_SEP!$I$2:$I$1218=C18), ""-"")"),17628.226888880523) -> 17628.227 | F18: =IFERROR(VALUE(E18)*VALUE(D18), "-") -> 5.8478011e+08 | G18: 17665 | H18: =IFERROR(VALUE(G18)*VALUE(D18), "-") -> 5.8599999e+08 | I18: 0 | J18: =IF(OR(I18="-", F18="-", I18="", F18=""), "-", VALUE(I18)%*VALUE(F18)) -> 0 | K18: =IF(OR(H18="-", F18="-", H18="", F18=""), "-", VALUE(H18)-VALUE(F18)) -> 1219872.2 | L18: =IF(OR(H18="-", F18="-", J18="-", H18="", F18="", J18=""), "-", VALUE(H18)-VALUE(F18)-VALUE(J18)) -> 1219872.2 | M18: 46282 | N18: =SUMIF(B$3:B$900, M18, L$3:L$900) -> 4908642.1
A19: =IF(ISBLANK(B19),"",TEXT(B19,"dddd")) -> Thursday | B19: 46268 | C19: 1 | D19: 135900.33 | E19: =IFERROR(__xludf.DUMMYFUNCTION("IFNA(FILTER(BUY_SEP!$L$2:$L$1218, BUY_SEP!$H$2:$H$1218=B19, BUY_SEP!$I$2:$I$1218=C19), ""-"")"),17628.226888880523) -> 17628.227 | F19: =IFERROR(VALUE(E19)*VALUE(D19), "-") -> 2395681852 | G19: 17660 | H19: =IFERROR(VALUE(G19)*VALUE(D19), "-") -> 2399999828 | I19: 0 | J19: =IF(OR(I19="-", F19="-", I19="", F19=""), "-", VALUE(I19)%*VALUE(F19)) -> 0 | K19: =IF(OR(H19="-", F19="-", H19="", F19=""), "-", VALUE(H19)-VALUE(F19)) -> 4317976.3 | L19: =IF(OR(H19="-", F19="-", J19="-", H19="", F19="", J19=""), "-", VALUE(H19)-VALUE(F19)-VALUE(J19)) -> 4317976.3 | M19: 46283 | N19: =SUMIF(B$3:B$900, M19, L$3:L$900) -> 19150722
A20: =IF(ISBLANK(B20),"",TEXT(B20,"dddd")) -> Thursday | B20: 46268 | C20: 1 | D20: 45325.77 | E20: =IFERROR(__xludf.DUMMYFUNCTION("IFNA(FILTER(BUY_SEP!$L$2:$L$1218, BUY_SEP!$H$2:$H$1218=B20, BUY_SEP!$I$2:$I$1218=C20), ""-"")"),17628.226888880523) -> 17628.227 | F20: =IFERROR(VALUE(E20)*VALUE(D20), "-") -> 7.9901296e+08 | G20: 17650 | H20: =IFERROR(VALUE(G20)*VALUE(D20), "-") -> 7.9999984e+08 | I20: 0 | J20: =IF(OR(I20="-", F20="-", I20="", F20=""), "-", VALUE(I20)%*VALUE(F20)) -> 0 | K20: =IF(OR(H20="-", F20="-", H20="", F20=""), "-", VALUE(H20)-VALUE(F20)) -> 986883.03 | L20: =IF(OR(H20="-", F20="-", J20="-", H20="", F20="", J20=""), "-", VALUE(H20)-VALUE(F20)-VALUE(J20)) -> 986883.03 | M20: 46284 | N20: =SUMIF(B$3:B$900, M20, L$3:L$900) -> 16222263
A21: =IF(ISBLANK(B21),"",TEXT(B21,"dddd")) -> Thursday | B21: 46268 | C21: 1 | D21: 79320.11 | E21: =IFERROR(__xludf.DUMMYFUNCTION("IFNA(FILTER(BUY_SEP!$L$2:$L$1218, BUY_SEP!$H$2:$H$1218=B21, BUY_SEP!$I$2:$I$1218=C21), ""-"")"),17628.226888880523) -> 17628.227 | F21: =IFERROR(VALUE(E21)*VALUE(D21), "-") -> 1398272896 | G21: 17650 | H21: =IFERROR(VALUE(G21)*VALUE(D21), "-") -> 1399999942 | I21: 0 | J21: =IF(OR(I21="-", F21="-", I21="", F21=""), "-", VALUE(I21)%*VALUE(F21)) -> 0 | K21: =IF(OR(H21="-", F21="-", H21="", F21=""), "-", VALUE(H21)-VALUE(F21)) -> 1727045.6 | L21: =IF(OR(H21="-", F21="-", J21="-", H21="", F21="", J21=""), "-", VALUE(H21)-VALUE(F21)-VALUE(J21)) -> 1727045.6 | M21: 46285 | N21: =SUMIF(B$3:B$900, M21, L$3:L$900) -> 12686598
A22: =IF(ISBLANK(B22),"",TEXT(B22,"dddd")) -> Thursday | B22: 46268 | C22: 2 | D22: 107693.67 | E22: =IFERROR(__xludf.DUMMYFUNCTION("IFNA(FILTER(BUY_SEP!$L$2:$L$1218, BUY_SEP!$H$2:$H$1218=B22, BUY_SEP!$I$2:$I$1218=C22), ""-"")"),17587.29300109465) -> 17587.293 | F22: =IFERROR(VALUE(E22)*VALUE(D22), "-") -> 1894040129 | G22: 17640 | H22: =IFERROR(VALUE(G22)*VALUE(D22), "-") -> 1899716339 | I22: 0.05 | J22: =IF(OR(I22="-", F22="-", I22="", F22=""), "-", VALUE(I22)%*VALUE(F22)) -> 947020.06 | K22: =IF(OR(H22="-", F22="-", H22="", F22=""), "-", VALUE(H22)-VALUE(F22)) -> 5676210.1 | L22: =IF(OR(H22="-", F22="-", J22="-", H22="", F22="", J22=""), "-", VALUE(H22)-VALUE(F22)-VALUE(J22)) -> 4729190.1 | M22: 46286 | N22: =SUMIF(B$3:B$900, M22, L$3:L$900) -> 13484028
A23: =IF(ISBLANK(B23),"",TEXT(B23,"dddd")) -> Thursday | B23: 46268 | C23: 2 | D23: 62406.51 | E23: =IFERROR(__xludf.DUMMYFUNCTION("IFNA(FILTER(BUY_SEP!$L$2:$L$1218, BUY_SEP!$H$2:$H$1218=B23, BUY_SEP!$I$2:$I$1218=C23), ""-"")"),17587.29300109465) -> 17587.293 | F23: =IFERROR(VALUE(E23)*VALUE(D23), "-") -> 1097561577 | G23: 17625 | H23: =IFERROR(VALUE(G23)*VALUE(D23), "-") -> 1099914739 | I23: 0.05 | J23: =IF(OR(I23="-", F23="-", I23="", F23=""), "-", VALUE(I23)%*VALUE(F23)) -> 548780.79 | K23: =IF(OR(H23="-", F23="-", H23="", F23=""), "-", VALUE(H23)-VALUE(F23)) -> 2353162.2 | L23: =IF(OR(H23="-", F23="-", J23="-", H23="", F23="", J23=""), "-", VALUE(H23)-VALUE(F23)-VALUE(J23)) -> 1804381.4 | M23: 46287 | N23: =SUMIF(B$3:B$900, M23, L$3:L$900) -> 20974341
A24: =IF(ISBLANK(B24),"",TEXT(B24,"dddd")) -> Friday | B24: 46269 | C24: 1 | D24: 266893.81 | E24: =IFERROR(__xludf.DUMMYFUNCTION("IFNA(FILTER(BUY_SEP!$L$2:$L$1218, BUY_SEP!$H$2:$H$1218=B24, BUY_SEP!$I$2:$I$1218=C24), ""-"")"),17570.0) -> 17570 | F24: =IFERROR(VALUE(E24)*VALUE(D24), "-") -> 4689324242 | G24: 17610 | H24: =IFERROR(VALUE(G24)*VALUE(D24), "-") -> 4699999994 | I24: 0 | J24: =IF(OR(I24="-", F24="-", I24="", F24=""), "-", VALUE(I24)%*VALUE(F24)) -> 0 | K24: =IF(OR(H24="-", F24="-", H24="", F24=""), "-", VALUE(H24)-VALUE(F24)) -> 10675752 | L24: =IF(OR(H24="-", F24="-", J24="-", H24="", F24="", J24=""), "-", VALUE(H24)-VALUE(F24)-VALUE(J24)) -> 10675752 | M24: 46288 | N24: =SUMIF(B$3:B$900, M24, L$3:L$900) -> 7197091.5
A25: =IF(ISBLANK(B25),"",TEXT(B25,"dddd")) -> Friday | B25: 46269 | C25: 2 | D25: 113571 | E25: =IFERROR(__xludf.DUMMYFUNCTION("IFNA(FILTER(BUY_SEP!$L$2:$L$1218, BUY_SEP!$H$2:$H$1218=B25, BUY_SEP!$I$2:$I$1218=C25), ""-"")"),17570.0) -> 17570 | F25: =IFERROR(VALUE(E25)*VALUE(D25), "-") -> 1995442470 | G25: 17610 | H25: =IFERROR(VALUE(G25)*VALUE(D25), "-") -> 1999985310 | I25: 0 | J25: =IF(OR(I25="-", F25="-", I25="", F25=""), "-", VALUE(I25)%*VALUE(F25)) -> 0 | K25: =IF(OR(H25="-", F25="-", H25="", F25=""), "-", VALUE(H25)-VALUE(F25)) -> 4542840 | L25: =IF(OR(H25="-", F25="-", J25="-", H25="", F25="", J25=""), "-", VALUE(H25)-VALUE(F25)-VALUE(J25)) -> 4542840 | M25: 46289 | N25: =SUMIF(B$3:B$900, M25, L$3:L$900) -> 20411990
A26: =IF(ISBLANK(B26),"",TEXT(B26,"dddd")) -> Friday | B26: 46269 | C26: 2 | D26: 17050.29 | E26: =IFERROR(__xludf.DUMMYFUNCTION("IFNA(FILTER(BUY_SEP!$L$2:$L$1218, BUY_SEP!$H$2:$H$1218=B26, BUY_SEP!$I$2:$I$1218=C26), ""-"")"),17570.0) -> 17570 | F26: =IFERROR(VALUE(E26)*VALUE(D26), "-") -> 2.995736e+08 | G26: 17595 | H26: =IFERROR(VALUE(G26)*VALUE(D26), "-") -> 2.9999985e+08 | I26: 0 | J26: =IF(OR(I26="-", F26="-", I26="", F26=""), "-", VALUE(I26)%*VALUE(F26)) -> 0 | K26: =IF(OR(H26="-", F26="-", H26="", F26=""), "-", VALUE(H26)-VALUE(F26)) -> 426257.25 | L26: =IF(OR(H26="-", F26="-", J26="-", H26="", F26="", J26=""), "-", VALUE(H26)-VALUE(F26)-VALUE(J26)) -> 426257.25 | M26: 46290 | N26: =SUMIF(B$3:B$900, M26, L$3:L$900) -> 22878630
A27: =IF(ISBLANK(B27),"",TEXT(B27,"dddd")) -> Friday | B27: 46269 | C27: 3 | D27: 92355.78 | E27: =IFERROR(__xludf.DUMMYFUNCTION("IFNA(FILTER(BUY_SEP!$L$2:$L$1218, BUY_SEP!$H$2:$H$1218=B27, BUY_SEP!$I$2:$I$1218=C27), ""-"")"),17565.0) -> 17565 | F27: =IFERROR(VALUE(E27)*VALUE(D27), "-") -> 1622229276 | G27: 17595 | H27: =IFERROR(VALUE(G27)*VALUE(D27), "-") -> 1624999949 | I27: 0 | J27: =IF(OR(I27="-", F27="-", I27="", F27=""), "-", VALUE(I27)%*VALUE(F27)) -> 0 | K27: =IF(OR(H27="-", F27="-", H27="", F27=""), "-", VALUE(H27)-VALUE(F27)) -> 2770673.4 | L27: =IF(OR(H27="-", F27="-", J27="-", H27="", F27="", J27=""), "-", VALUE(H27)-VALUE(F27)-VALUE(J27)) -> 2770673.4 | M27: 46291 | N27: =SUMIF(B$3:B$900, M27, L$3:L$900) -> 15258059
A28: =IF(ISBLANK(B28),"",TEXT(B28,"dddd")) -> Friday | B28: 46269 | C28: 4 | D28: 73947.66 | E28: =IFERROR(__xludf.DUMMYFUNCTION("IFNA(FILTER(BUY_SEP!$L$2:$L$1218, BUY_SEP!$H$2:$H$1218=B28, BUY_SEP!$I$2:$I$1218=C28), ""-"")"),17545.0) -> 17545 | F28: =IFERROR(VALUE(E28)*VALUE(D28), "-") -> 1297411695 | G28: 17580 | H28: =IFERROR(VALUE(G28)*VALUE(D28), "-") -> 1299999863 | I28: 0 | J28: =IF(OR(I28="-", F28="-", I28="", F28=""), "-", VALUE(I28)%*VALUE(F28)) -> 0 | K28: =IF(OR(H28="-", F28="-", H28="", F28=""), "-", VALUE(H28)-VALUE(F28)) -> 2588168.1 | L28: =IF(OR(H28="-", F28="-", J28="-", H28="", F28="", J28=""), "-", VALUE(H28)-VALUE(F28)-VALUE(J28)) -> 2588168.1 | M28: 46292 | N28: =SUMIF(B$3:B$900, M28, L$3:L$900) -> 6385818.2
A29: =IF(ISBLANK(B29),"",TEXT(B29,"dddd")) -> Friday | B29: 46269 | C29: 5 | D29: 56866.64 | E29: =IFERROR(__xludf.DUMMYFUNCTION("IFNA(FILTER(BUY_SEP!$L$2:$L$1218, BUY_SEP!$H$2:$H$1218=B29, BUY_SEP!$I$2:$I$1218=C29), ""-"")"),17546.084400490337) -> 17546.084 | F29: =IFERROR(VALUE(E29)*VALUE(D29), "-") -> 997786865 | G29: 17585 | H29: =IFERROR(VALUE(G29)*VALUE(D29), "-") -> 9.9999986e+08 | I29: 0.05 | J29: =IF(OR(I29="-", F29="-", I29="", F29=""), "-", VALUE(I29)%*VALUE(F29)) -> 498893.43 | K29: =IF(OR(H29="-", F29="-", H29="", F29=""), "-", VALUE(H29)-VALUE(F29)) -> 2212999.4 | L29: =IF(OR(H29="-", F29="-", J29="-", H29="", F29="", J29=""), "-", VALUE(H29)-VALUE(F29)-VALUE(J29)) -> 1714106 | M29: 46293 | N29: =SUMIF(B$3:B$900, M29, L$3:L$900) -> 9169580.7
A30: =IF(ISBLANK(B30),"",TEXT(B30,"dddd")) -> Friday | B30: 46269 | C30: 4 | D30: 95931.72 | E30: =IFERROR(__xludf.DUMMYFUNCTION("IFNA(FILTER(BUY_SEP!$L$2:$L$1218, BUY_SEP!$H$2:$H$1218=B30, BUY_SEP!$I$2:$I$1218=C30), ""-"")"),17545.0) -> 17545 | F30: =IFERROR(VALUE(E30)*VALUE(D30), "-") -> 1683122027 | G30: 17575 | H30: =IFERROR(VALUE(G30)*VALUE(D30), "-") -> 1685999979 | I30: 0 | J30: =IF(OR(I30="-", F30="-", I30="", F30=""), "-", VALUE(I30)%*VALUE(F30)) -> 0 | K30: =IF(OR(H30="-", F30="-", H30="", F30=""), "-", VALUE(H30)-VALUE(F30)) -> 2877951.6 | L30: =IF(OR(H30="-", F30="-", J30="-", H30="", F30="", J30=""), "-", VALUE(H30)-VALUE(F30)-VALUE(J30)) -> 2877951.6 | M30: 46294 | N30: =SUMIF(B$3:B$900, M30, L$3:L$900) -> 5900321
A31: =IF(ISBLANK(B31),"",TEXT(B31,"dddd")) -> Saturday | B31: 46270 | C31: 1 | D31: 85348.5 | E31: =IFERROR(__xludf.DUMMYFUNCTION("IFNA(FILTER(BUY_SEP!$L$2:$L$1218, BUY_SEP!$H$2:$H$1218=B31, BUY_SEP!$I$2:$I$1218=C31), ""-"")"),17550.0) -> 17550 | F31: =IFERROR(VALUE(E31)*VALUE(D31), "-") -> 1497866175 | G31: 17575 | H31: =IFERROR(VALUE(G31)*VALUE(D31), "-") -> 1499999888 | I31: 0 | J31: =IF(OR(I31="-", F31="-", I31="", F31=""), "-", VALUE(I31)%*VALUE(F31)) -> 0 | K31: =IF(OR(H31="-", F31="-", H31="", F31=""), "-", VALUE(H31)-VALUE(F31)) -> 2133712.5 | L31: =IF(OR(H31="-", F31="-", J31="-", H31="", F31="", J31=""), "-", VALUE(H31)-VALUE(F31)-VALUE(J31)) -> 2133712.5 | M31: 46295 | N31: =SUMIF(B$3:B$900, M31, L$3:L$900) -> 0
A32: =IF(ISBLANK(B32),"",TEXT(B32,"dddd")) -> Monday | B32: 46272 | C32: 1 | D32: 56899.01 | E32: =IFERROR(__xludf.DUMMYFUNCTION("IFNA(FILTER(BUY_SEP!$L$2:$L$1218, BUY_SEP!$H$2:$H$1218=B32, BUY_SEP!$I$2:$I$1218=C32), ""-"")"),17559.53413496284) -> 17559.534 | F32: =IFERROR(VALUE(E32)*VALUE(D32), "-") -> 9.9912011e+08 | G32: 17575 | H32: =IFERROR(VALUE(G32)*VALUE(D32), "-") -> 1000000101 | I32: 0.05 | J32: =IF(OR(I32="-", F32="-", I32="", F32=""), "-", VALUE(I32)%*VALUE(F32)) -> 499560.05 | K32: =IF(OR(H32="-", F32="-", H32="", F32=""), "-", VALUE(H32)-VALUE(F32)) -> 879992.41 | L32: =IF(OR(H32="-", F32="-", J32="-", H32="", F32="", J32=""), "-", VALUE(H32)-VALUE(F32)-VALUE(J32)) -> 380432.36 | N32: =SUMIF(B$3:B$900, M32, L$3:L$900) -> 0
A33: =IF(ISBLANK(B33),"",TEXT(B33,"dddd")) -> Monday | B33: 46272 | C33: 1 | D33: 56850.48 | E33: =IFERROR(__xludf.DUMMYFUNCTION("IFNA(FILTER(BUY_SEP!$L$2:$L$1218, BUY_SEP!$H$2:$H$1218=B33, BUY_SEP!$I$2:$I$1218=C33), ""-"")"),17559.53413496284) -> 17559.534 | F33: =IFERROR(VALUE(E33)*VALUE(D33), "-") -> 9.9826794e+08 | G33: 17590 | H33: =IFERROR(VALUE(G33)*VALUE(D33), "-") -> 9.9999994e+08 | I33: 0.05 | J33: =IF(OR(I33="-", F33="-", I33="", F33=""), "-", VALUE(I33)%*VALUE(F33)) -> 499133.97 | K33: =IF(OR(H33="-", F33="-", H33="", F33=""), "-", VALUE(H33)-VALUE(F33)) -> 1731999.1 | L33: =IF(OR(H33="-", F33="-", J33="-", H33="", F33="", J33=""), "-", VALUE(H33)-VALUE(F33)-VALUE(J33)) -> 1232865.1 | N33: =SUMIF(B$3:B$900, M33, L$3:L$900) -> 0
A34: =IF(ISBLANK(B34),"",TEXT(B34,"dddd")) -> Tuesday | B34: 46273 | C34: 1 | D34: 65930.23 | E34: =IFERROR(__xludf.DUMMYFUNCTION("IFNA(FILTER(BUY_SEP!$L$2:$L$1218, BUY_SEP!$H$2:$H$1218=B34, BUY_SEP!$I$2:$I$1218=C34), ""-"")"),17556.0) -> 17556 | F34: =IFERROR(VALUE(E34)*VALUE(D34), "-") -> 1157471118 | G34: 17572 | H34: =IFERROR(VALUE(G34)*VALUE(D34), "-") -> 1158526002 | I34: 0 | J34: =IF(OR(I34="-", F34="-", I34="", F34=""), "-", VALUE(I34)%*VALUE(F34)) -> 0 | K34: =IF(OR(H34="-", F34="-", H34="", F34=""), "-", VALUE(H34)-VALUE(F34)) -> 1054883.7 | L34: =IF(OR(H34="-", F34="-", J34="-", H34="", F34="", J34=""), "-", VALUE(H34)-VALUE(F34)-VALUE(J34)) -> 1054883.7 | N34: =SUMIF(B$3:B$900, M34, L$3:L$900) -> 0
A35: =IF(ISBLANK(B35),"",TEXT(B35,"dddd")) -> Tuesday | B35: 46273 | C35: 2 | D35: 113817.43 | E35: =IFERROR(__xludf.DUMMYFUNCTION("IFNA(FILTER(BUY_SEP!$L$2:$L$1218, BUY_SEP!$H$2:$H$1218=B35, BUY_SEP!$I$2:$I$1218=C35), ""-"")"),17556.0) -> 17556 | F35: =IFERROR(VALUE(E35)*VALUE(D35), "-") -> 1998178801 | G35: 17572 | H35: =IFERROR(VALUE(G35)*VALUE(D35), "-") -> 1999999880 | I35: 0 | J35: =IF(OR(I35="-", F35="-", I35="", F35=""), "-", VALUE(I35)%*VALUE(F35)) -> 0 | K35: =IF(OR(H35="-", F35="-", H35="", F35=""), "-", VALUE(H35)-VALUE(F35)) -> 1821078.9 | L35: =IF(OR(H35="-", F35="-", J35="-", H35="", F35="", J35=""), "-", VALUE(H35)-VALUE(F35)-VALUE(J35)) -> 1821078.9 | N35: =SUMIF(B$3:B$900, M35, L$3:L$900) -> 0
A36: =IF(ISBLANK(B36),"",TEXT(B36,"dddd")) -> Tuesday | B36: 46273 | C36: 3 | D36: 28454.35 | E36: =IFERROR(__xludf.DUMMYFUNCTION("IFNA(FILTER(BUY_SEP!$L$2:$L$1218, BUY_SEP!$H$2:$H$1218=B36, BUY_SEP!$I$2:$I$1218=C36), ""-"")"),17556.0) -> 17556 | F36: =IFERROR(VALUE(E36)*VALUE(D36), "-") -> 4.9954457e+08 | G36: 17572 | H36: =IFERROR(VALUE(G36)*VALUE(D36), "-") -> 4.9999984e+08 | I36: 0 | J36: =IF(OR(I36="-", F36="-", I36="", F36=""), "-", VALUE(I36)%*VALUE(F36)) -> 0 | K36: =IF(OR(H36="-", F36="-", H36="", F36=""), "-", VALUE(H36)-VALUE(F36)) -> 455269.6 | L36: =IF(OR(H36="-", F36="-", J36="-", H36="", F36="", J36=""), "-", VALUE(H36)-VALUE(F36)-VALUE(J36)) -> 455269.6 | N36: =SUMIF(B$3:B$900, M36, L$3:L$900) -> 0
A37: =IF(ISBLANK(B37),"",TEXT(B37,"dddd")) -> Tuesday | B37: 46273 | C37: 4 | D37: 131345.32 | E37: =IFERROR(__xludf.DUMMYFUNCTION("IFNA(FILTER(BUY_SEP!$L$2:$L$1218, BUY_SEP!$H$2:$H$1218=B37, BUY_SEP!$I$2:$I$1218=C37), ""-"")"),17557.0) -> 17557 | F37: =IFERROR(VALUE(E37)*VALUE(D37), "-") -> 2306029783 | G37: 17572 | H37: =IFERROR(VALUE(G37)*VALUE(D37), "-") -> 2307999963 | I37: 0 | J37: =IF(OR(I37="-", F37="-", I37="", F37=""), "-", VALUE(I37)%*VALUE(F37)) -> 0 | K37: =IF(OR(H37="-", F37="-", H37="", F37=""), "-", VALUE(H37)-VALUE(F37)) -> 1970179.8 | L37: =IF(OR(H37="-", F37="-", J37="-", H37="", F37="", J37=""), "-", VALUE(H37)-VALUE(F37)-VALUE(J37)) -> 1970179.8 | N37: =SUMIF(B$3:B$900, M37, L$3:L$900) -> 0
